Workbook

Sheet Overview
C2: YOUR LOGO HERE
C4: Financial Model
G5: Welcome! This template was created by Forecastr's team of Financial Analysts and Fractional CFOs to help our fellow founders create better financial models for their startups and small businesses. Forecastr is an out-of-the-box finance function for your business. We provide the tools and support you need to create an investor-grade financial model. Our analysts work with you every step of the way to build a model that's customized to fit your business, keep it up to date, and generate insightful reports to share with your investors and other stakeholders. ✔ Impress your investors ✔ Hit your growth targets ✔ Never run out of cash
C7: Your Website Link Here
C10: Table of Contents
C12: Assumptions
C14: Financials
I18: SCHEDULE A MODELING SESSION WITH A MEMBER OF OUR TEAM

Sheet Assumptions
B1: Year Counter | G1: 1 | H1: 1 | I1: 1 | J1: 1 | K1: 1 | L1: 1 | M1: 1 | N1: 1 | O1: 1 | P1: 1 | Q1: 1 | R1: 1 | S1: =G1+1 -> 2 | T1: =H1+1 -> 2 | U1: =I1+1 -> 2 | V1: =J1+1 -> 2 | W1: =K1+1 -> 2 | X1: =L1+1 -> 2 | Y1: =M1+1 -> 2 | Z1: =N1+1 -> 2 | ... BN1: =BB1+1 -> 5
B2: Year | G2: =YEAR(G4) -> 2026 | H2: =YEAR(H4) -> 2026 | I2: =YEAR(I4) -> 2026 | J2: =YEAR(J4) -> 2026 | K2: =YEAR(K4) -> 2026 | L2: =YEAR(L4) -> 2026 | M2: =YEAR(M4) -> 2026 | N2: =YEAR(N4) -> 2026 | ... BN2: =YEAR(BN4) -> 2031
B3: Month Counter | G3: 1 | H3: =G3+1 -> 2 | I3: =H3+1 -> 3 | J3: =I3+1 -> 4 | K3: =J3+1 -> 5 | L3: =K3+1 -> 6 | M3: =L3+1 -> 7 | N3: =M3+1 -> 8 | O3: =N3+1 -> 9 | ... BN3: =BM3+1 -> 60
B4: Date | G4: =eomonth(today(),0) -> 46081 | H4: =EOMONTH(G4,1) -> 46112 | I4: =EOMONTH(H4,1) -> 46142 | J4: =EOMONTH(I4,1) -> 46173 | K4: =EOMONTH(J4,1) -> 46203 | L4: =EOMONTH(K4,1) -> 46234 | M4: =EOMONTH(L4,1) -> 46265 | N4: =EOMONTH(M4,1) -> 46295 | O4: =EOMONTH(N4,1) -> 46326 | ... BN4: =EOMONTH(BM4,1) -> 47879
B6: Customer Acquisition:
B8: Build Customer Acquisition Channels
B10: Organic / Word of Mouth
B11: Leads | D11: 1000 | G11: =D11 -> 1000 | H11: =G11 -> 1000 | I11: =G11 -> 1000 | J11: =I11 -> 1000 | K11: =J11 -> 1000 | L11: =K11 -> 1000 | M11: =L11 -> 1000 | N11: =M11 -> 1000 | O11: =N11 -> 1000 | P11: =O11 -> 1000 | Q11: =P11 -> 1000 | ... BN11: =BM11 -> 1000
B12: Conversion Rate | D12: 0.1 | G12: =D12 -> 0.1 | H12: =G12 -> 0.1 | I12: =G12 -> 0.1 | J12: =I12 -> 0.1 | K12: =J12 -> 0.1 | L12: =K12 -> 0.1 | M12: =L12 -> 0.1 | N12: =M12 -> 0.1 | O12: =N12 -> 0.1 | P12: =O12 -> 0.1 | Q12: =P12 -> 0.1 | ... BN12: =BM12 -> 0.1
B13: New Customers | G13: =G11*G12 -> 100 | H13: =H11*H12 -> 100 | I13: =I11*I12 -> 100 | J13: =J11*J12 -> 100 | K13: =K11*K12 -> 100 | L13: =L11*L12 -> 100 | M13: =M11*M12 -> 100 | N13: =N11*N12 -> 100 | ... BN13: =BN11*BN12 -> 100
B15: Paid Advertising
B16: Budget per Month | D16: 2500 | G16: =D16 -> 2500 | H16: =G16+(0.1*G16) -> 2750 | I16: =H16+(0.1*H16) -> 3025 | J16: =I16+(0.1*I16) -> 3327.5 | K16: =J16+(0.1*J16) -> 3660.25 | L16: =K16+(0.1*K16) -> 4026.275 | M16: =L16 -> 4026.275 | N16: =M16 -> 4026.275 | O16: =N16 -> 4026.275 | P16: =O16 -> 4026.275 | Q16: =P16 -> 4026.275 | R16: =Q16 -> 4026.275 | S16: =R16 -> 4026.275 | T16: =S16 -> 4026.275 | ... BN16: =BM16 -> 4026.275
B17: Average CPC | D17: 2 | G17: =D17 -> 2 | H17: =G17 -> 2 | I17: =H17 -> 2 | J17: =I17 -> 2 | K17: =J17 -> 2 | L17: =K17 -> 2 | M17: =L17 -> 2 | N17: =M17 -> 2 | O17: =N17 -> 2 | ... BN17: =BM17 -> 2
B18: Conversion Rate | D18: 0.15 | G18: =D18 -> 0.15 | H18: =G18 -> 0.15 | I18: =H18 -> 0.15 | J18: =I18 -> 0.15 | K18: =J18 -> 0.15 | L18: =K18 -> 0.15 | M18: =L18 -> 0.15 | N18: =M18 -> 0.15 | O18: =N18 -> 0.15 | ... BN18: =BM18 -> 0.15
B19: New Customers | G19: =iferror((G16/G17)*G18,0) -> 187.5 | H19: =iferror((H16/H17)*H18,0) -> 206.25 | I19: =iferror((I16/I17)*I18,0) -> 226.875 | J19: =iferror((J16/J17)*J18,0) -> 249.5625 | K19: =iferror((K16/K17)*K18,0) -> 274.51875 | L19: =iferror((L16/L17)*L18,0) -> 301.97062 | M19: =iferror((M16/M17)*M18,0) -> 301.97062 | N19: =iferror((N16/N17)*N18,0) -> 301.97062 | ... BN19: =iferror((BN16/BN17)*BN18,0) -> 301.97062
B21: Affiliates
B22: Number of Affiliates | D22: 5 | G22: =D22 -> 5 | H22: =G22 -> 5 | I22: =H22 -> 5 | J22: =I22 -> 5 | K22: =J22 -> 5 | L22: =K22 -> 5 | M22: =L22 -> 5 | N22: =M22 -> 5 | O22: =N22 -> 5 | ... BN22: =BM22 -> 5
B23: New Monthly Leads per Affiliate | D23: 50 | G23: =D23 -> 50 | H23: =G23 -> 50 | I23: =H23 -> 50 | J23: =I23 -> 50 | K23: =J23 -> 50 | L23: =K23 -> 50 | M23: =L23 -> 50 | N23: =M23 -> 50 | O23: =N23 -> 50 | ... BN23: =BM23 -> 50
B24: Conversion Rate | D24: 0.05 | G24: =D24 -> 0.05 | H24: =G24 -> 0.05 | I24: =H24 -> 0.05 | J24: =I24 -> 0.05 | K24: =J24 -> 0.05 | L24: =K24 -> 0.05 | M24: =L24 -> 0.05 | N24: =M24 -> 0.05 | O24: =N24 -> 0.05 | ... BN24: =BM24 -> 0.05
B25: New Customers | G25: =G22*G23*G24 -> 12.5 | H25: =H22*H23*H24 -> 12.5 | I25: =I22*I23*I24 -> 12.5 | J25: =J22*J23*J24 -> 12.5 | K25: =K22*K23*K24 -> 12.5 | L25: =L22*L23*L24 -> 12.5 | M25: =M22*M23*M24 -> 12.5 | N25: =N22*N23*N24 -> 12.5 | ... BN25: =BN22*BN23*BN24 -> 12.5
B27: Conferences
B28: Conferences Atteneded | G28: 1 | K28: 1 | L28: 1 | Q28: 1 | R28: 1 | S28: 1 | T28: 1 | U28: 1 | V28: 1 | W28: 1 | X28: 1 | Y28: 1 | Z28: 1 | AA28: 1 | AB28: 1 | AC28: 1 | AD28: 1 | AE28: 1 | AF28: 1 | AG28: 1 | AH28: 1 | AI28: 1 | AJ28: 1 | AK28: 1 | AL28: 1 | AM28: 1 | AN28: 1 | AO28: 1 | AP28: 1 | AQ28: 1 | AR28: 1 | AS28: 1 | AT28: 1 | AU28: 1 | AV28: 1 | AW28: 1 | AX28: 1 | AY28: 1 | AZ28: 1 | BA28: 1 | BB28: 1 | BC28: 1 | BD28: 1 | BE28: 1 | BF28: 1 | BG28: 1 | BH28: 1 | BI28: 1 | BJ28: 1 | BK28: 1 | BL28: 1 | BM28: 1 | BN28: 1
B29: New Leads per Conference | D29: 50 | G29: =D29 -> 50 | H29: =G29 -> 50 | I29: =H29 -> 50 | J29: =I29 -> 50 | K29: =J29 -> 50 | L29: =K29 -> 50 | M29: =L29 -> 50 | N29: =M29 -> 50 | O29: =N29 -> 50 | ... BN29: =BM29 -> 50
B30: Conversion Rate | D30: 0.05 | G30: 0.02 | H30: =G30 -> 0.02 | I30: =H30 -> 0.02 | J30: =I30 -> 0.02 | K30: =J30 -> 0.02 | L30: =K30 -> 0.02 | M30: =L30 -> 0.02 | N30: =M30 -> 0.02 | O30: =N30 -> 0.02 | ... BN30: =BM30 -> 0.02
B31: New Customers | G31: =G28*G29*G30 -> 1 | H31: =H28*H29*H30 -> 0 | I31: =I28*I29*I30 -> 0 | J31: =J28*J29*J30 -> 0 | K31: =K28*K29*K30 -> 1 | L31: =L28*L29*L30 -> 1 | M31: =M28*M29*M30 -> 0 | N31: =N28*N29*N30 -> 0 | ... BN31: =BN28*BN29*BN30 -> 1
B33: Influencers
B34: Number of Influencers | D34: 2 | G34: =D34 -> 2 | H34: =G34 -> 2 | I34: =H34 -> 2 | J34: =I34 -> 2 | K34: =J34 -> 2 | L34: =K34 -> 2 | M34: =L34 -> 2 | N34: =M34 -> 2 | O34: =N34 -> 2 | ... BN34: =BM34 -> 2
B35: New Monthly Posts per Influencer | D35: 5 | G35: =D35 -> 5 | H35: =G35 -> 5 | I35: =H35 -> 5 | J35: =I35 -> 5 | K35: =J35 -> 5 | L35: =K35 -> 5 | M35: =L35 -> 5 | N35: =M35 -> 5 | O35: =N35 -> 5 | ... BN35: =BM35 -> 5
B36: New Monthly Leads per Post | D36: 100 | G36: =D36 -> 100 | H36: =G36 -> 100 | I36: =H36 -> 100 | J36: =I36 -> 100 | K36: =J36 -> 100 | L36: =K36 -> 100 | M36: =L36 -> 100 | N36: =M36 -> 100 | O36: =N36 -> 100 | ... BN36: =BM36 -> 100
B37: Conversion Rate | D37: 0.05 | G37: =D37 -> 0.05 | H37: =G37 -> 0.05 | I37: =H37 -> 0.05 | J37: =I37 -> 0.05 | K37: =J37 -> 0.05 | L37: =K37 -> 0.05 | M37: =L37 -> 0.05 | N37: =M37 -> 0.05 | O37: =N37 -> 0.05 | ... BN37: =BM37 -> 0.05
B38: New Customers | G38: =G34*G35*G36*G37 -> 50 | H38: =H34*H35*H36*H37 -> 50 | I38: =I34*I35*I36*I37 -> 50 | J38: =J34*J35*J36*J37 -> 50 | K38: =K34*K35*K36*K37 -> 50 | L38: =L34*L35*L36*L37 -> 50 | M38: =M34*M35*M36*M37 -> 50 | N38: =N34*N35*N36*N37 -> 50 | ... BN38: =BN34*BN35*BN36*BN37 -> 50
B40: Customer Referrals
B41: Previous Months New Customers | G41: =F71 | H41: =G71 -> 378.5 | I41: =H71 -> 406.9275 | J41: =I71 -> 427.97891 | K41: =J71 -> 450.98218 | L41: =K71 -> 477.28348 | M41: =L71 -> 505.12988 | N41: =M71 -> 504.54757 | ... BN41: =BM71 -> 505.55393
B42: Referral Percentage | D42: 0.3 | G42: =D42 -> 0.3 | H42: =G42 -> 0.3 | I42: =H42 -> 0.3 | J42: =I42 -> 0.3 | K42: =J42 -> 0.3 | L42: =K42 -> 0.3 | M42: =L42 -> 0.3 | N42: =M42 -> 0.3 | O42: =N42 -> 0.3 | ... BN42: =BM42 -> 0.3
B43: Conversion Rate | D43: 0.05 | G43: =D43 -> 0.05 | H43: =G43 -> 0.05 | I43: =H43 -> 0.05 | J43: =I43 -> 0.05 | K43: =J43 -> 0.05 | L43: =K43 -> 0.05 | M43: =L43 -> 0.05 | N43: =M43 -> 0.05 | O43: =N43 -> 0.05 | ... BN43: =BM43 -> 0.05
B44: New Customers | G44: =G41*G42*G43 -> 0 | H44: =H41*H42*H43 -> 5.6775 | I44: =I41*I42*I43 -> 6.1039125 | J44: =J41*J42*J43 -> 6.4196837 | K44: =K41*K42*K43 -> 6.7647328 | L44: =L41*L42*L43 -> 7.1592522 | M44: =M41*M42*M43 -> 7.5769482 | N44: =N41*N42*N43 -> 7.5682136 | ... BN44: =BN41*BN42*BN43 -> 7.583309
B46: Partnerships
B47: Active Partnerships | D47: 2 | G47: =D47 -> 2 | H47: =G47 -> 2 | I47: =H47 -> 2 | J47: =I47 -> 2 | K47: =J47 -> 2 | L47: =K47 -> 2 | M47: =L47 -> 2 | N47: =M47 -> 2 | O47: =N47 -> 2 | ... BN47: =BM47 -> 2
B48: New Monthly Leads per Partnership | D48: 100 | G48: =D48 -> 100 | H48: =G48 -> 100 | I48: =H48 -> 100 | J48: =I48 -> 100 | K48: =J48 -> 100 | L48: =K48 -> 100 | M48: =L48 -> 100 | N48: =M48 -> 100 | O48: =N48 -> 100 | ... BN48: =BM48 -> 100
B49: Conversion Rate | D49: 0.05 | G49: =D49 -> 0.05 | H49: =G49 -> 0.05 | I49: =H49 -> 0.05 | J49: =I49 -> 0.05 | K49: =J49 -> 0.05 | L49: =K49 -> 0.05 | M49: =L49 -> 0.05 | N49: =M49 -> 0.05 | O49: =N49 -> 0.05 | ... BN49: =BM49 -> 0.05
B50: New Customers | G50: =G47*G48*G49 -> 10 | H50: =H47*H48*H49 -> 10 | I50: =I47*I48*I49 -> 10 | J50: =J47*J48*J49 -> 10 | K50: =K47*K48*K49 -> 10 | L50: =L47*L48*L49 -> 10 | M50: =M47*M48*M49 -> 10 | N50: =N47*N48*N49 -> 10 | ... BN50: =BN47*BN48*BN49 -> 10
B52: Email Marketing
B53: Mailing List Size | D53: 2000 | G53: =D53 -> 2000 | H53: =G53 -> 2000 | I53: =H53 -> 2000 | J53: =I53 -> 2000 | K53: =J53 -> 2000 | L53: =K53 -> 2000 | M53: =L53 -> 2000 | N53: =M53 -> 2000 | O53: =N53 -> 2000 | ... BN53: =BM53 -> 2000
B54: Average Number of Emails Sent a Month | D54: 2 | G54: =D54 -> 2 | H54: =G54 -> 2 | I54: =H54 -> 2 | J54: =I54 -> 2 | K54: =J54 -> 2 | L54: =K54 -> 2 | M54: =L54 -> 2 | N54: =M54 -> 2 | O54: =N54 -> 2 | ... BN54: =BM54 -> 2
B55: Response Rate per Email | D55: 0.05 | G55: =D55 -> 0.05 | H55: =G55 -> 0.05 | I55: =H55 -> 0.05 | J55: =I55 -> 0.05 | K55: =J55 -> 0.05 | L55: =K55 -> 0.05 | M55: =L55 -> 0.05 | N55: =M55 -> 0.05 | O55: =N55 -> 0.05 | ... BN55: =BM55 -> 0.05
B56: Conversion Rate | D56: 0.05 | G56: =D56 -> 0.05 | H56: =G56 -> 0.05 | I56: =H56 -> 0.05 | J56: =I56 -> 0.05 | K56: =J56 -> 0.05 | L56: =K56 -> 0.05 | M56: =L56 -> 0.05 | N56: =M56 -> 0.05 | O56: =N56 -> 0.05 | ... BN56: =BM56 -> 0.05
B57: New Customers | G57: =G53*G54*G55*G56 -> 10 | H57: =H53*H54*H55*H56 -> 10 | I57: =I53*I54*I55*I56 -> 10 | J57: =J53*J54*J55*J56 -> 10 | K57: =K53*K54*K55*K56 -> 10 | L57: =L53*L54*L55*L56 -> 10 | M57: =M53*M54*M55*M56 -> 10 | N57: =N53*N54*N55*N56 -> 10 | ... BN57: =BN53*BN54*BN55*BN56 -> 10
B59: Content Marketing
B60: New Pieces of Content | D60: 3 | G60: =D60 -> 3 | H60: =G60 -> 3 | I60: =H60 -> 3 | J60: =I60 -> 3 | K60: =J60 -> 3 | L60: =K60 -> 3 | M60: =L60 -> 3 | N60: =M60 -> 3 | O60: =N60 -> 3 | ... BN60: =BM60 -> 3
B61: New Leads per Piece of Content | D61: 50 | G61: =D61 -> 50 | H61: =G61 -> 50 | I61: =H61 -> 50 | J61: =I61 -> 50 | K61: =J61 -> 50 | L61: =K61 -> 50 | M61: =L61 -> 50 | N61: =M61 -> 50 | O61: =N61 -> 50 | ... BN61: =BM61 -> 50
B62: Conversion Rate | D62: 0.05 | G62: =D62 -> 0.05 | H62: =G62 -> 0.05 | I62: =H62 -> 0.05 | J62: =I62 -> 0.05 | K62: =J62 -> 0.05 | L62: =K62 -> 0.05 | M62: =L62 -> 0.05 | N62: =M62 -> 0.05 | O62: =N62 -> 0.05 | ... BN62: =BM62 -> 0.05
B63: New Customers | G63: =G60*G61*G62 -> 7.5 | H63: =H60*H61*H62 -> 7.5 | I63: =I60*I61*I62 -> 7.5 | J63: =J60*J61*J62 -> 7.5 | K63: =K60*K61*K62 -> 7.5 | L63: =L60*L61*L62 -> 7.5 | M63: =M60*M61*M62 -> 7.5 | N63: =N60*N61*N62 -> 7.5 | ... BN63: =BN60*BN61*BN62 -> 7.5
B65: Direct Sales Team
B66: Leads | D66: 25 | G66: =D66 -> 25 | H66: =G66 -> 25 | I66: =H66 -> 25 | J66: =I66 -> 25 | K66: =J66 -> 25 | L66: =K66 -> 25 | M66: =L66 -> 25 | N66: =M66 -> 25 | O66: =N66 -> 25 | ... BN66: =BM66 -> 25
B67: Sales Cycle | D67: 2 | G67: =D67 -> 2 | H67: =G67 -> 2 | I67: =H67 -> 2 | J67: =I67 -> 2 | K67: =J67 -> 2 | L67: =K67 -> 2 | M67: =L67 -> 2 | N67: =M67 -> 2 | O67: =N67 -> 2 | ... BN67: =BM67 -> 2
B68: Conversion Rate | D68: 0.2 | G68: =D68 -> 0.2 | H68: =G68 -> 0.2 | I68: =H68 -> 0.2 | J68: =I68 -> 0.2 | K68: =J68 -> 0.2 | L68: =K68 -> 0.2 | M68: =L68 -> 0.2 | N68: =M68 -> 0.2 | O68: =N68 -> 0.2 | ... BN68: =BM68 -> 0.2
B69: New Customers | G69: =IFERROR(offset(G66,,-G67+1)*G68,0) -> 0 | H69: =IFERROR(offset(H66,,-H67+1)*H68,0) -> 5 | I69: =IFERROR(offset(I66,,-I67+1)*I68,0) -> 5 | J69: =IFERROR(offset(J66,,-J67+1)*J68,0) -> 5 | K69: =IFERROR(offset(K66,,-K67+1)*K68,0) -> 5 | L69: =IFERROR(offset(L66,,-L67+1)*L68,0) -> 5 | M69: =IFERROR(offset(M66,,-M67+1)*M68,0) -> 5 | N69: =IFERROR(offset(N66,,-N67+1)*N68,0) -> 5 | ... BN69: =IFERROR(offset(BN66,,-BN67+1)*BN68,0) -> 5
B71: Total New Customers | G71: =G13+G19+G25+G31+G38+G44+G50+G57+G63+G69 -> 378.5 | H71: =H13+H19+H25+H31+H38+H44+H50+H57+H63+H69 -> 406.9275 | I71: =I13+I19+I25+I31+I38+I44+I50+I57+I63+I69 -> 427.97891 | J71: =J13+J19+J25+J31+J38+J44+J50+J57+J63+J69 -> 450.98218 | K71: =K13+K19+K25+K31+K38+K44+K50+K57+K63+K69 -> 477.28348 | L71: =L13+L19+L25+L31+L38+L44+L50+L57+L63+L69 -> 505.12988 | M71: =M13+M19+M25+M31+M38+M44+M50+M57+M63+M69 -> 504.54757 | N71: =N13+N19+N25+N31+N38+N44+N50+N57+N63+N69 -> 504.53884 | ... BN71: =BN13+BN19+BN25+BN31+BN38+BN44+BN50+BN57+BN63+BN69 -> 505.55393
B73: Revenue - Monthly SaaS:
B75: Monthly SaaS Stream 1
B76: % of Total New Customers | D76: 0.5 | G76: =D76 -> 0.5 | H76: =G76 -> 0.5 | I76: =H76 -> 0.5 | J76: =I76 -> 0.5 | K76: =J76 -> 0.5 | L76: =K76 -> 0.5 | M76: =L76 -> 0.5 | N76: =M76 -> 0.5 | O76: =N76 -> 0.5 | ... BN76: =BM76 -> 0.5
B77: New Customers | G77: =G76*G$71 -> 189.25 | H77: =H76*H$71 -> 203.46375 | I77: =I76*I$71 -> 213.98946 | J77: =J76*J$71 -> 225.49109 | K77: =K76*K$71 -> 238.64174 | L77: =L76*L$71 -> 252.56494 | M77: =M76*M$71 -> 252.27379 | N77: =N76*N$71 -> 252.26942 | ... BN77: =BN76*BN$71 -> 252.77697
B78: Churn Rate | D78: 0.025 | G78: =D78 -> 0.025 | H78: =G78 -> 0.025 | I78: =H78 -> 0.025 | J78: =I78 -> 0.025 | K78: =J78 -> 0.025 | L78: =K78 -> 0.025 | M78: =L78 -> 0.025 | N78: =M78 -> 0.025 | O78: =N78 -> 0.025 | ... BN78: =BM78 -> 0.025
B79: Churned Subscriptions | G79: =G82*G78 -> 0 | H79: =H82*H78 -> 4.73125 | I79: =I82*I78 -> 9.6995625 | J79: =J82*J78 -> 14.80681 | K79: =K82*K78 -> 20.073917 | L79: =L82*L78 -> 25.538113 | M79: =M82*M78 -> 31.213783 | N79: =N82*N78 -> 36.740283 | ... BN79: =BN82*BN78 -> 194.85431
B80: Retained Subscriptions | G80: =G82-G79 -> 0 | H80: =H82-H79 -> 184.51875 | I80: =I82-I79 -> 378.28294 | J80: =J82-J79 -> 577.46558 | K80: =K82-K79 -> 782.88276 | L80: =L82-L79 -> 995.98639 | M80: =M82-M79 -> 1217.3375 | N80: =N82-N79 -> 1432.871 | ... BN80: =BN82-BN79 -> 7599.3182
B81: Active Subscriptions | G81: =G77+G80 -> 189.25 | H81: =H77+H80 -> 387.9825 | I81: =I77+I80 -> 592.27239 | J81: =J77+J80 -> 802.95668 | K81: =K77+K80 -> 1021.5245 | L81: =L77+L80 -> 1248.5513 | M81: =M77+M80 -> 1469.6113 | N81: =N77+N80 -> 1685.1405 | ... BN81: =BN77+BN80 -> 7852.0951
B82: Previous Months Active Subsciptions | G82: =E81 | H82: =G81 -> 189.25 | I82: =H81 -> 387.9825 | J82: =I81 -> 592.27239 | K82: =J81 -> 802.95668 | L82: =K81 -> 1021.5245 | M82: =L81 -> 1248.5513 | N82: =M81 -> 1469.6113 | O82: =N81 -> 1685.1405 | ... BN82: =BM81 -> 7794.1725
B83: Price | D83: 10 | G83: =D83 -> 10 | H83: =G83 -> 10 | I83: =H83 -> 10 | J83: =I83 -> 10 | K83: =J83 -> 10 | L83: =K83 -> 10 | M83: =L83 -> 10 | N83: =M83 -> 10 | O83: =N83 -> 10 | ... BN83: =BM83 -> 10
B84: Revenue | G84: =G81*G83 -> 1892.5 | H84: =H81*H83 -> 3879.825 | I84: =I81*I83 -> 5922.7239 | J84: =J81*J83 -> 8029.5668 | K84: =K81*K83 -> 10215.245 | L84: =L81*L83 -> 12485.513 | M84: =M81*M83 -> 14696.113 | N84: =N81*N83 -> 16851.405 | ... BN84: =BN81*BN83 -> 78520.951
B86: Monthly SaaS Stream 2
B87: % of Total New Customers | D87: 0.3 | G87: =D87 -> 0.3 | H87: =G87 -> 0.3 | I87: =H87 -> 0.3 | J87: =I87 -> 0.3 | K87: =J87 -> 0.3 | L87: =K87 -> 0.3 | M87: =L87 -> 0.3 | N87: =M87 -> 0.3 | O87: =N87 -> 0.3 | ... BN87: =BM87 -> 0.3
B88: New Customers | G88: =G87*G$71 -> 113.55 | H88: =H87*H$71 -> 122.07825 | I88: =I87*I$71 -> 128.39367 | J88: =J87*J$71 -> 135.29466 | K88: =K87*K$71 -> 143.18504 | L88: =L87*L$71 -> 151.53896 | M88: =M87*M$71 -> 151.36427 | N88: =N87*N$71 -> 151.36165 | ... BN88: =BN87*BN$71 -> 151.66618
B89: Churn Rate | D89: 0 | G89: =D89 -> 0 | H89: =G89 -> 0 | I89: =H89 -> 0 | J89: =I89 -> 0 | K89: =J89 -> 0 | L89: =K89 -> 0 | M89: =L89 -> 0 | N89: =M89 -> 0 | O89: =N89 -> 0 | ... BN89: =BM89 -> 0
B90: Churned Subscriptions | G90: =G93*G89 -> 0 | H90: =H93*H89 -> 0 | I90: =I93*I89 -> 0 | J90: =J93*J89 -> 0 | K90: =K93*K89 -> 0 | L90: =L93*L89 -> 0 | M90: =M93*M89 -> 0 | N90: =N93*N89 -> 0 | ... BN90: =BN93*BN89 -> 0
B91: Retained Subscriptions | G91: =G93-G90 -> 0 | H91: =H93-H90 -> 113.55 | I91: =I93-I90 -> 235.62825 | J91: =J93-J90 -> 364.02192 | K91: =K93-K90 -> 499.31658 | L91: =L93-L90 -> 642.50162 | M91: =M93-M90 -> 794.04059 | N91: =N93-N90 -> 945.40486 | ... BN91: =BN93-BN90 -> 8831.1279
B92: Active Subscriptions | G92: =G88+G91 -> 113.55 | H92: =H88+H91 -> 235.62825 | I92: =I88+I91 -> 364.02192 | J92: =J88+J91 -> 499.31658 | K92: =K88+K91 -> 642.50162 | L92: =L88+L91 -> 794.04059 | M92: =M88+M91 -> 945.40486 | N92: =N88+N91 -> 1096.7665 | ... BN92: =BN88+BN91 -> 8982.7941
B93: Previous Months Active Subsciptions | G93: =E92 | H93: =G92 -> 113.55 | I93: =H92 -> 235.62825 | J93: =I92 -> 364.02192 | K93: =J92 -> 499.31658 | L93: =K92 -> 642.50162 | M93: =L92 -> 794.04059 | N93: =M92 -> 945.40486 | O93: =N92 -> 1096.7665 | ... BN93: =BM92 -> 8831.1279
B94: Price | D94: 25 | G94: =D94 -> 25 | H94: =G94 -> 25 | I94: =H94 -> 25 | J94: =I94 -> 25 | K94: =J94 -> 25 | L94: =K94 -> 25 | M94: =L94 -> 25 | N94: =M94 -> 25 | O94: =N94 -> 25 | ... BN94: =BM94 -> 25
B95: Revenue | G95: =G92*G94 -> 2838.75 | H95: =H92*H94 -> 5890.7063 | I95: =I92*I94 -> 9100.5481 | J95: =J92*J94 -> 12482.914 | K95: =K92*K94 -> 16062.541 | L95: =L92*L94 -> 19851.015 | M95: =M92*M94 -> 23635.121 | N95: =N92*N94 -> 27419.163 | ... BN95: =BN92*BN94 -> 224569.85
B97: Monthly SaaS Stream 3
B98: % of Total New Customers | D98: 0.2 | G98: =D98 -> 0.2 | H98: =G98 -> 0.2 | I98: =H98 -> 0.2 | J98: =I98 -> 0.2 | K98: =J98 -> 0.2 | L98: =K98 -> 0.2 | M98: =L98 -> 0.2 | N98: =M98 -> 0.2 | O98: =N98 -> 0.2 | ... BN98: =BM98 -> 0.2
B99: New Customers | G99: =G98*G$71 -> 75.7 | H99: =H98*H$71 -> 81.3855 | I99: =I98*I$71 -> 85.595782 | J99: =J98*J$71 -> 90.196437 | K99: =K98*K$71 -> 95.456697 | L99: =L98*L$71 -> 101.02598 | M99: =M98*M$71 -> 100.90951 | N99: =N98*N$71 -> 100.90777 | ... BN99: =BN98*BN$71 -> 101.11079
B100: Churn Rate | D100: 0 | G100: =D100 -> 0 | H100: =G100 -> 0 | I100: =H100 -> 0 | J100: =I100 -> 0 | K100: =J100 -> 0 | L100: =K100 -> 0 | M100: =L100 -> 0 | N100: =M100 -> 0 | O100: =N100 -> 0 | ... BN100: =BM100 -> 0
B101: Churned Subscriptions | G101: =G104*G100 -> 0 | H101: =H104*H100 -> 0 | I101: =I104*I100 -> 0 | J101: =J104*J100 -> 0 | K101: =K104*K100 -> 0 | L101: =L104*L100 -> 0 | M101: =M104*M100 -> 0 | N101: =N104*N100 -> 0 | ... BN101: =BN104*BN100 -> 0
B102: Retained Subscriptions | G102: =G104-G101 -> 0 | H102: =H104-H101 -> 75.7 | I102: =I104-I101 -> 157.0855 | J102: =J104-J101 -> 242.68128 | K102: =K104-K101 -> 332.87772 | L102: =L104-L101 -> 428.33442 | M102: =M104-M101 -> 529.36039 | N102: =N104-N101 -> 630.26991 | ... BN102: =BN104-BN101 -> 5887.4186
B103: Active Subscriptions | G103: =G99+G102 -> 75.7 | H103: =H99+H102 -> 157.0855 | I103: =I99+I102 -> 242.68128 | J103: =J99+J102 -> 332.87772 | K103: =K99+K102 -> 428.33442 | L103: =L99+L102 -> 529.36039 | M103: =M99+M102 -> 630.26991 | N103: =N99+N102 -> 731.17767 | ... BN103: =BN99+BN102 -> 5988.5294
B104: Previous Months Active Subsciptions | G104: =E103 | H104: =G103 -> 75.7 | I104: =H103 -> 157.0855 | J104: =I103 -> 242.68128 | K104: =J103 -> 332.87772 | L104: =K103 -> 428.33442 | M104: =L103 -> 529.36039 | N104: =M103 -> 630.26991 | O104: =N103 -> 731.17767 | ... BN104: =BM103 -> 5887.4186
B105: Price | D105: 50 | G105: =D105 -> 50 | H105: =G105 -> 50 | I105: =H105 -> 50 | J105: =I105 -> 50 | K105: =J105 -> 50 | L105: =K105 -> 50 | M105: =L105 -> 50 | N105: =M105 -> 50 | O105: =N105 -> 50 | ... BN105: =BM105 -> 50
B106: Revenue | G106: =G103*G105 -> 3785 | H106: =H103*H105 -> 7854.275 | I106: =I103*I105 -> 12134.064 | J106: =J103*J105 -> 16643.886 | K106: =K103*K105 -> 21416.721 | L106: =L103*L105 -> 26468.02 | M106: =M103*M105 -> 31513.495 | N106: =N103*N105 -> 36558.884 | ... BN106: =BN103*BN105 -> 299426.47
B108: + ADD MORE
B110: People:
B112: Name | C112: Salary | D112: Benefits | E112: Start Date
B113: CEO | C113: 100000 | D113: 0.2 | E113: 45658 | G113: =IF(G$4>=$E113,($C113/12)*(1+$D113),0) -> 10000 | H113: =IF(H$4>=$E113,($C113/12)*(1+$D113),0) -> 10000 | I113: =IF(I$4>=$E113,($C113/12)*(1+$D113),0) -> 10000 | J113: =IF(J$4>=$E113,($C113/12)*(1+$D113),0) -> 10000 | K113: =IF(K$4>=$E113,($C113/12)*(1+$D113),0) -> 10000 | L113: =IF(L$4>=$E113,($C113/12)*(1+$D113),0) -> 10000 | M113: =IF(M$4>=$E113,($C113/12)*(1+$D113),0) -> 10000 | N113: =IF(N$4>=$E113,($C113/12)*(1+$D113),0) -> 10000 | ... BB113: =IF(BB$4>=$E113,($C113/12)*(1+$D113),0) -> 10000 | BC113: 10000 | BD113: 10000 | BE113: 10000 | BF113: 10000 | BG113: 10000 | BH113: 10000 | BI113: 10000 | BJ113: 10000 | BK113: 10000 | BL113: 10000 | BM113: 10000 | BN113: 10000
B114: Person 2 | C114: 100000 | D114: 0.2 | E114: 43831 | G114: =IF(G$4>=$E114,($C114/12)*(1+$D114),0) -> 10000 | H114: =IF(H$4>=$E114,($C114/12)*(1+$D114),0) -> 10000 | I114: =IF(I$4>=$E114,($C114/12)*(1+$D114),0) -> 10000 | J114: =IF(J$4>=$E114,($C114/12)*(1+$D114),0) -> 10000 | K114: =IF(K$4>=$E114,($C114/12)*(1+$D114),0) -> 10000 | L114: =IF(L$4>=$E114,($C114/12)*(1+$D114),0) -> 10000 | M114: =IF(M$4>=$E114,($C114/12)*(1+$D114),0) -> 10000 | N114: =IF(N$4>=$E114,($C114/12)*(1+$D114),0) -> 10000 | ... BB114: =IF(BB$4>=$E114,($C114/12)*(1+$D114),0) -> 10000 | BC114: 10000 | BD114: 10000 | BE114: 10000 | BF114: 10000 | BG114: 10000 | BH114: 10000 | BI114: 10000 | BJ114: 10000 | BK114: 10000 | BL114: 10000 | BM114: 10000 | BN114: 10000
B115: Person 3 | C115: 100000 | D115: 0.2 | E115: 44075 | G115: =IF(G$4>=$E115,($C115/12)*(1+$D115),0) -> 10000 | H115: =IF(H$4>=$E115,($C115/12)*(1+$D115),0) -> 10000 | I115: =IF(I$4>=$E115,($C115/12)*(1+$D115),0) -> 10000 | J115: =IF(J$4>=$E115,($C115/12)*(1+$D115),0) -> 10000 | K115: =IF(K$4>=$E115,($C115/12)*(1+$D115),0) -> 10000 | L115: =IF(L$4>=$E115,($C115/12)*(1+$D115),0) -> 10000 | M115: =IF(M$4>=$E115,($C115/12)*(1+$D115),0) -> 10000 | N115: =IF(N$4>=$E115,($C115/12)*(1+$D115),0) -> 10000 | ... BB115: =IF(BB$4>=$E115,($C115/12)*(1+$D115),0) -> 10000 | BC115: 10000 | BD115: 10000 | BE115: 10000 | BF115: 10000 | BG115: 10000 | BH115: 10000 | BI115: 10000 | BJ115: 10000 | BK115: 10000 | BL115: 10000 | BM115: 10000 | BN115: 10000
B116: Person 4 | C116: 100000 | D116: 0.2 | E116: 43831 | G116: =IF(G$4>=$E116,($C116/12)*(1+$D116),0) -> 10000 | H116: =IF(H$4>=$E116,($C116/12)*(1+$D116),0) -> 10000 | I116: =IF(I$4>=$E116,($C116/12)*(1+$D116),0) -> 10000 | J116: =IF(J$4>=$E116,($C116/12)*(1+$D116),0) -> 10000 | K116: =IF(K$4>=$E116,($C116/12)*(1+$D116),0) -> 10000 | L116: =IF(L$4>=$E116,($C116/12)*(1+$D116),0) -> 10000 | M116: =IF(M$4>=$E116,($C116/12)*(1+$D116),0) -> 10000 | N116: =IF(N$4>=$E116,($C116/12)*(1+$D116),0) -> 10000 | ... BB116: =IF(BB$4>=$E116,($C116/12)*(1+$D116),0) -> 10000 | BC116: 10000 | BD116: 10000 | BE116: 10000 | BF116: 10000 | BG116: 10000 | BH116: 10000 | BI116: 10000 | BJ116: 10000 | BK116: 10000 | BL116: 10000 | BM116: 10000 | BN116: 10000
B117: Person 5 | C117: 100000 | D117: 0.2 | E117: 43891 | G117: =IF(G$4>=$E117,($C117/12)*(1+$D117),0) -> 10000 | H117: =IF(H$4>=$E117,($C117/12)*(1+$D117),0) -> 10000 | I117: =IF(I$4>=$E117,($C117/12)*(1+$D117),0) -> 10000 | J117: =IF(J$4>=$E117,($C117/12)*(1+$D117),0) -> 10000 | K117: =IF(K$4>=$E117,($C117/12)*(1+$D117),0) -> 10000 | L117: =IF(L$4>=$E117,($C117/12)*(1+$D117),0) -> 10000 | M117: =IF(M$4>=$E117,($C117/12)*(1+$D117),0) -> 10000 | N117: =IF(N$4>=$E117,($C117/12)*(1+$D117),0) -> 10000 | ... BB117: =IF(BB$4>=$E117,($C117/12)*(1+$D117),0) -> 10000 | BC117: 10000 | BD117: 10000 | BE117: 10000 | BF117: 10000 | BG117: 10000 | BH117: 10000 | BI117: 10000 | BJ117: 10000 | BK117: 10000 | BL117: 10000 | BM117: 10000 | BN117: 10000
B118: Person 6 | C118: 75000 | D118: 0.2 | E118: 43983 | G118: =IF(G$4>=$E118,($C118/12)*(1+$D118),0) -> 7500 | H118: =IF(H$4>=$E118,($C118/12)*(1+$D118),0) -> 7500 | I118: =IF(I$4>=$E118,($C118/12)*(1+$D118),0) -> 7500 | J118: =IF(J$4>=$E118,($C118/12)*(1+$D118),0) -> 7500 | K118: =IF(K$4>=$E118,($C118/12)*(1+$D118),0) -> 7500 | L118: =IF(L$4>=$E118,($C118/12)*(1+$D118),0) -> 7500 | M118: =IF(M$4>=$E118,($C118/12)*(1+$D118),0) -> 7500 | N118: =IF(N$4>=$E118,($C118/12)*(1+$D118),0) -> 7500 | ... BB118: =IF(BB$4>=$E118,($C118/12)*(1+$D118),0) -> 7500 | BC118: 7500 | BD118: 7500 | BE118: 7500 | BF118: 7500 | BG118: 7500 | BH118: 7500 | BI118: 7500 | BJ118: 7500 | BK118: 7500 | BL118: 7500 | BM118: 7500 | BN118: 7500
B119: Person 7 | C119: 50000 | D119: 0.2 | E119: 44075 | G119: =IF(G$4>=$E119,($C119/12)*(1+$D119),0) -> 5000 | H119: =IF(H$4>=$E119,($C119/12)*(1+$D119),0) -> 5000 | I119: =IF(I$4>=$E119,($C119/12)*(1+$D119),0) -> 5000 | J119: =IF(J$4>=$E119,($C119/12)*(1+$D119),0) -> 5000 | K119: =IF(K$4>=$E119,($C119/12)*(1+$D119),0) -> 5000 | L119: =IF(L$4>=$E119,($C119/12)*(1+$D119),0) -> 5000 | M119: =IF(M$4>=$E119,($C119/12)*(1+$D119),0) -> 5000 | N119: =IF(N$4>=$E119,($C119/12)*(1+$D119),0) -> 5000 | ... BB119: =IF(BB$4>=$E119,($C119/12)*(1+$D119),0) -> 5000 | BC119: 5000 | BD119: 5000 | BE119: 5000 | BF119: 5000 | BG119: 5000 | BH119: 5000 | BI119: 5000 | BJ119: 5000 | BK119: 5000 | BL119: 5000 | BM119: 5000 | BN119: 5000
B120: Person 8 | C120: 80000 | D120: 0.2 | E120: 44166 | G120: =IF(G$4>=$E120,($C120/12)*(1+$D120),0) -> 8000 | H120: =IF(H$4>=$E120,($C120/12)*(1+$D120),0) -> 8000 | I120: =IF(I$4>=$E120,($C120/12)*(1+$D120),0) -> 8000 | J120: =IF(J$4>=$E120,($C120/12)*(1+$D120),0) -> 8000 | K120: =IF(K$4>=$E120,($C120/12)*(1+$D120),0) -> 8000 | L120: =IF(L$4>=$E120,($C120/12)*(1+$D120),0) -> 8000 | M120: =IF(M$4>=$E120,($C120/12)*(1+$D120),0) -> 8000 | N120: =IF(N$4>=$E120,($C120/12)*(1+$D120),0) -> 8000 | ... BB120: =IF(BB$4>=$E120,($C120/12)*(1+$D120),0) -> 8000 | BC120: 8000 | BD120: 8000 | BE120: 8000 | BF120: 8000 | BG120: 8000 | BH120: 8000 | BI120: 8000 | BJ120: 8000 | BK120: 8000 | BL120: 8000 | BM120: 8000 | BN120: 8000
...

Sheet Financials
B1: Year Counter | F1: 1 | G1: 1 | H1: 1 | I1: 1 | J1: 1 | K1: 1 | L1: 1 | M1: 1 | N1: 1 | O1: 1 | P1: 1 | Q1: 1 | R1: =F1+1 -> 2 | S1: =G1+1 -> 2 | T1: =H1+1 -> 2 | U1: =I1+1 -> 2 | V1: =J1+1 -> 2 | W1: =K1+1 -> 2 | X1: =L1+1 -> 2 | Y1: =M1+1 -> 2 | ... BM1: =BA1+1 -> 5
B2: Year | F2: =YEAR(F4) -> 2026 | G2: =YEAR(G4) -> 2026 | H2: =YEAR(H4) -> 2026 | I2: =YEAR(I4) -> 2026 | J2: =YEAR(J4) -> 2026 | K2: =YEAR(K4) -> 2026 | L2: =YEAR(L4) -> 2026 | M2: =YEAR(M4) -> 2026 | ... BM2: =YEAR(BM4) -> 2031
B3: Month Counter | F3: 1 | G3: =F3+1 -> 2 | H3: =G3+1 -> 3 | I3: =H3+1 -> 4 | J3: =I3+1 -> 5 | K3: =J3+1 -> 6 | L3: =K3+1 -> 7 | M3: =L3+1 -> 8 | N3: =M3+1 -> 9 | ... BM3: =BL3+1 -> 60
B4: Date | F4: =Assumptions!G4 -> 46081 | G4: =EOMONTH(F4,1) -> 46112 | H4: =EOMONTH(G4,1) -> 46142 | I4: =EOMONTH(H4,1) -> 46173 | J4: =EOMONTH(I4,1) -> 46203 | K4: =EOMONTH(J4,1) -> 46234 | L4: =EOMONTH(K4,1) -> 46265 | M4: =EOMONTH(L4,1) -> 46295 | N4: =EOMONTH(M4,1) -> 46326 | ... BM4: =EOMONTH(BL4,1) -> 47879
B6: Income Statement:
B8: Revenue | F8: =SUM(F9:F11) -> 8516.25 | G8: =SUM(G9:G11) -> 17624.806 | H8: =SUM(H9:H11) -> 27157.336 | I8: =SUM(I9:I11) -> 37156.367 | J8: =SUM(J9:J11) -> 47694.506 | K8: =SUM(K9:K11) -> 58804.548 | L8: =SUM(L9:L11) -> 69844.73 | M8: =SUM(M9:M11) -> 80829.451 | ... BM8: =SUM(BM9:BM11) -> 602517.27
B9: =Assumptions!B75 -> Monthly SaaS Stream 1 | F9: =Assumptions!G84 -> 1892.5 | G9: =Assumptions!H84 -> 3879.825 | H9: =Assumptions!I84 -> 5922.7239 | I9: =Assumptions!J84 -> 8029.5668 | J9: =Assumptions!K84 -> 10215.245 | K9: =Assumptions!L84 -> 12485.513 | L9: =Assumptions!M84 -> 14696.113 | M9: =Assumptions!N84 -> 16851.405 | ... BM9: =Assumptions!BN84 -> 78520.951
B10: =Assumptions!B86 -> Monthly SaaS Stream 2 | F10: =Assumptions!G95 -> 2838.75 | G10: =Assumptions!H95 -> 5890.7063 | H10: =Assumptions!I95 -> 9100.5481 | I10: =Assumptions!J95 -> 12482.914 | J10: =Assumptions!K95 -> 16062.541 | K10: =Assumptions!L95 -> 19851.015 | L10: =Assumptions!M95 -> 23635.121 | M10: =Assumptions!N95 -> 27419.163 | ... BM10: =Assumptions!BN95 -> 224569.85
B11: =Assumptions!B97 -> Monthly SaaS Stream 3 | F11: =Assumptions!G106 -> 3785 | G11: =Assumptions!H106 -> 7854.275 | H11: =Assumptions!I106 -> 12134.064 | I11: =Assumptions!J106 -> 16643.886 | J11: =Assumptions!K106 -> 21416.721 | K11: =Assumptions!L106 -> 26468.02 | L11: =Assumptions!M106 -> 31513.495 | M11: =Assumptions!N106 -> 36558.884 | ... BM11: =Assumptions!BN106 -> 299426.47
B13: COGS | F13: =Assumptions!G150 -> 2980.6875 | G13: =Assumptions!H150 -> 6168.6822 | H13: =Assumptions!I150 -> 9505.0677 | I13: =Assumptions!J150 -> 13004.729 | J13: =Assumptions!K150 -> 16693.077 | K13: =Assumptions!L150 -> 20581.592 | L13: =Assumptions!M150 -> 24445.656 | M13: =Assumptions!N150 -> 28290.308 | ... BM13: =Assumptions!BN150 -> 210881.05
B15: Gross Profit | F15: =F8-F13 -> 5535.5625 | G15: =G8-G13 -> 11456.124 | H15: =H8-H13 -> 17652.268 | I15: =I8-I13 -> 24151.639 | J15: =J8-J13 -> 31001.429 | K15: =K8-K13 -> 38222.956 | L15: =L8-L13 -> 45399.075 | M15: =M8-M13 -> 52539.143 | ... BM15: =BM8-BM13 -> 391636.23
B16: Gross Margin | F16: =F15/F8 -> 0.65 | G16: =G15/G8 -> 0.65 | H16: =H15/H8 -> 0.65 | I16: =I15/I8 -> 0.65 | J16: =J15/J8 -> 0.65 | K16: =K15/K8 -> 0.65 | L16: =L15/L8 -> 0.65 | M16: =M15/M8 -> 0.65 | ... BM16: =BM15/BM8 -> 0.65
B18: Operating Expenses
B19: Salaries & Benefits | F19: =SUM(Assumptions!G113:G137) -> 218000 | G19: =SUM(Assumptions!H113:H137) -> 218000 | H19: =SUM(Assumptions!I113:I137) -> 218000 | I19: =SUM(Assumptions!J113:J137) -> 218000 | J19: =SUM(Assumptions!K113:K137) -> 218000 | K19: =SUM(Assumptions!L113:L137) -> 218000 | L19: =SUM(Assumptions!M113:M137) -> 218000 | M19: =SUM(Assumptions!N113:N137) -> 218000 | ... BM19: =SUM(Assumptions!BN113:BN137) -> 218000
B20: =Assumptions!B152 -> General & Admin | F20: 35000 | G20: =sum(Assumptions!H153:H163) -> 27500 | H20: =sum(Assumptions!I153:I163) -> 27500 | I20: =sum(Assumptions!J153:J163) -> 27500 | J20: =sum(Assumptions!K153:K163) -> 27500 | K20: =sum(Assumptions!L153:L163) -> 27500 | L20: =sum(Assumptions!M153:M163) -> 27500 | M20: =sum(Assumptions!N153:N163) -> 27500 | N20: =sum(Assumptions!O153:O163) -> 27500 | ... BM20: =sum(Assumptions!BN153:BN163) -> 27500
B21: =Assumptions!B166 -> Sales & Marketing | F21: =sum(Assumptions!G167:G168) -> 10681.3 | G21: =sum(Assumptions!H167:H168) -> 11409.985 | H21: =sum(Assumptions!I167:I168) -> 12172.587 | I21: =sum(Assumptions!J167:J168) -> 12972.509 | J21: =sum(Assumptions!K167:K168) -> 13815.561 | K21: =sum(Assumptions!L167:L168) -> 14704.364 | L21: =sum(Assumptions!M167:M168) -> 15587.578 | M21: =sum(Assumptions!N167:N168) -> 16466.356 | ... BM21: =sum(Assumptions!BN167:BN168) -> 58201.382
B22: =Assumptions!B171 -> Professional Fees | F22: 0 | G22: =SUM(Assumptions!H172:H174) -> 5000 | H22: =SUM(Assumptions!I172:I174) -> 5000 | I22: =SUM(Assumptions!J172:J174) -> 5000 | J22: =SUM(Assumptions!K172:K174) -> 5000 | K22: =SUM(Assumptions!L172:L174) -> 5000 | L22: =SUM(Assumptions!M172:M174) -> 5000 | M22: =SUM(Assumptions!N172:N174) -> 5000 | N22: =SUM(Assumptions!O172:O174) -> 5000 | ... BM22: =SUM(Assumptions!BN172:BN174) -> 5000
B23: =Assumptions!B177 -> Other | F23: =Assumptions!G178 -> 851.625 | G23: =Assumptions!H178 -> 1762.4806 | H23: =Assumptions!I178 -> 2715.7336 | I23: =Assumptions!J178 -> 3715.6367 | J23: =Assumptions!K178 -> 4769.4506 | K23: =Assumptions!L178 -> 5880.4547 | L23: =Assumptions!M178 -> 6984.473 | M23: =Assumptions!N178 -> 8082.9451 | ... BM23: =Assumptions!BN178 -> 60251.727
B24: Total Operating Expenses | F24: =SUM(F19:F23) -> 264532.92 | G24: =SUM(G19:G23) -> 263672.47 | H24: =SUM(H19:H23) -> 265388.32 | I24: =SUM(I19:I23) -> 267188.15 | J24: =SUM(J19:J23) -> 269085.01 | K24: =SUM(K19:K23) -> 271084.82 | L24: =SUM(L19:L23) -> 273072.05 | M24: =SUM(M19:M23) -> 275049.3 | ... BM24: =SUM(BM19:BM23) -> 368953.11
B26: EBITDA | F26: =F15-F24 -> -258997.36 | G26: =G15-G24 -> -252216.34 | H26: =H15-H24 -> -247736.05 | I26: =I15-I24 -> -243036.51 | J26: =J15-J24 -> -238083.58 | K26: =K15-K24 -> -232861.86 | L26: =L15-L24 -> -227672.98 | M26: =M15-M24 -> -222510.16 | ... BM26: =BM15-BM24 -> 22683.119
B27: Depreciation | F27: =SUM(Assumptions!G199:G202)-sum(Assumptions!E199:E202) -> 0 | G27: =SUM(Assumptions!H199:H202)-sum(Assumptions!G199:G202) -> 0 | H27: =SUM(Assumptions!I199:I202)-sum(Assumptions!H199:H202) -> 0 | I27: =SUM(Assumptions!J199:J202)-sum(Assumptions!I199:I202) -> 0 | J27: =SUM(Assumptions!K199:K202)-sum(Assumptions!J199:J202) -> 0 | K27: =SUM(Assumptions!L199:L202)-sum(Assumptions!K199:K202) -> 0 | L27: =SUM(Assumptions!M199:M202)-sum(Assumptions!L199:L202) -> 0 | M27: =SUM(Assumptions!N199:N202)-sum(Assumptions!M199:M202) -> 0 | N27: =SUM(Assumptions!O199:O202)-sum(Assumptions!N199:N202) -> 0 | ... BM27: =SUM(Assumptions!BN199:BN202)-sum(Assumptions!BM199:BM202) -> 0
B28: EBIT | F28: =F26-F27 -> -258997.36 | G28: =G26-G27 -> -252216.34 | H28: =H26-H27 -> -247736.05 | I28: =I26-I27 -> -243036.51 | J28: =J26-J27 -> -238083.58 | K28: =K26-K27 -> -232861.86 | L28: =L26-L27 -> -227672.98 | M28: =M26-M27 -> -222510.16 | ... BM28: =BM26-BM27 -> 22683.119
B29: Taxes | F29: =IF(F28>0,F28*Assumptions!$C$180,0) -> 0 | G29: =IF(G28>0,G28*Assumptions!$C$180,0) -> 0 | H29: =IF(H28>0,H28*Assumptions!$C$180,0) -> 0 | I29: =IF(I28>0,I28*Assumptions!$C$180,0) -> 0 | J29: =IF(J28>0,J28*Assumptions!$C$180,0) -> 0 | K29: =IF(K28>0,K28*Assumptions!$C$180,0) -> 0 | L29: =IF(L28>0,L28*Assumptions!$C$180,0) -> 0 | M29: =IF(M28>0,M28*Assumptions!$C$180,0) -> 0 | ... BM29: =IF(BM28>0,BM28*Assumptions!$C$180,0) -> 6124.4421
B30: Net Income | F30: =F28-F29 -> -258997.36 | G30: =G28-G29 -> -252216.34 | H30: =H28-H29 -> -247736.05 | I30: =I28-I29 -> -243036.51 | J30: =J28-J29 -> -238083.58 | K30: =K28-K29 -> -232861.86 | L30: =L28-L29 -> -227672.98 | M30: =M28-M29 -> -222510.16 | ... BM30: =BM28-BM29 -> 16558.677
B31: Net Margin | F31: =F30/F8 -> -30.412137 | G31: =G30/G8 -> -14.310304 | H31: =H30/H8 -> -9.1222516 | I31: =I30/I8 -> -6.5409114 | J31: =J30/J8 -> -4.991845 | K31: =K30/K8 -> -3.9599295 | L31: =L30/L8 -> -3.2597016 | M31: =M30/M8 -> -2.7528352 | ... BM31: =BM30/BM8 -> 0.027482493
B33: Balance Sheet:
B35: Assets
B36: Current Assets
B37: Cash | F37: =F80 -> 260251.32 | G37: =G80 -> 5894.467 | H37: =H80 -> -244081.73 | I37: =I80 -> -489468.01 | J37: =J80 -> -730028.05 | K37: =K80 -> -965500.78 | L37: =L80 -> -1195768.2 | M37: =M80 -> -1420859.8 | ... BM37: =BM80 -> -6474938.3
B38: Accounts Receivable | F38: =Assumptions!G190 -> 4258.125 | G38: =Assumptions!H190 -> 8812.4031 | H38: =Assumptions!I190 -> 13578.668 | I38: =Assumptions!J190 -> 18578.184 | J38: =Assumptions!K190 -> 23847.253 | K38: =Assumptions!L190 -> 29402.274 | L38: =Assumptions!M190 -> 34922.365 | M38: =Assumptions!N190 -> 40414.726 | ... BM38: =Assumptions!BN190 -> 301258.64
B39: Total Current Assets | F39: =SUM(F37:F38) -> 264509.44 | G39: =SUM(G37:G38) -> 14706.87 | H39: =SUM(H37:H38) -> -230503.06 | I39: =SUM(I37:I38) -> -470889.83 | J39: =SUM(J37:J38) -> -706180.8 | K39: =SUM(K37:K38) -> -936098.5 | L39: =SUM(L37:L38) -> -1160845.8 | M39: =SUM(M37:M38) -> -1380445 | ... BM39: =SUM(BM37:BM38) -> -6173679.7
B41: Fixed Assets | F41: =SUM(Assumptions!G192:G196) -> 0 | G41: =SUM(Assumptions!H192:H196) -> 0 | H41: =SUM(Assumptions!I192:I196) -> 0 | I41: =SUM(Assumptions!J192:J196) -> 0 | J41: =SUM(Assumptions!K192:K196) -> 0 | K41: =SUM(Assumptions!L192:L196) -> 0 | L41: =SUM(Assumptions!M192:M196) -> 0 | M41: =SUM(Assumptions!N192:N196) -> 0 | ... BM41: =SUM(Assumptions!BN192:BN196) -> 0
B42: Accumulated Depreciation | F42: =-SUM(Assumptions!G199:G202) -> 0 | G42: =-SUM(Assumptions!H199:H202) -> 0 | H42: =-SUM(Assumptions!I199:I202) -> 0 | I42: =-SUM(Assumptions!J199:J202) -> 0 | J42: =-SUM(Assumptions!K199:K202) -> 0 | K42: =-SUM(Assumptions!L199:L202) -> 0 | L42: =-SUM(Assumptions!M199:M202) -> 0 | M42: =-SUM(Assumptions!N199:N202) -> 0 | ... BM42: =-SUM(Assumptions!BN199:BN202) -> 0
B43: Total Assets | F43: =SUM(F39:F42) -> 264509.44 | G43: =SUM(G39:G42) -> 14706.87 | H43: =SUM(H39:H42) -> -230503.06 | I43: =SUM(I39:I42) -> -470889.83 | J43: =SUM(J39:J42) -> -706180.8 | K43: =SUM(K39:K42) -> -936098.5 | L43: =SUM(L39:L42) -> -1160845.8 | M43: =SUM(M39:M42) -> -1380445 | ... BM43: =SUM(BM39:BM42) -> -6173679.7
B45: Liabilities & Owner's Equity
B46: Liabilities
B47: Accounts payable | F47: =Assumptions!G206 -> 23506.806 | G47: =Assumptions!H206 -> 25920.574 | H47: =Assumptions!I206 -> 28446.694 | I47: =Assumptions!J206 -> 31096.437 | J47: =Assumptions!K206 -> 33889.044 | K47: =Assumptions!L206 -> 36833.205 | L47: =Assumptions!M206 -> 39758.853 | M47: =Assumptions!N206 -> 42669.805 | ... BM47: =Assumptions!BN206 -> 180917.08
B48: Total Liabilities | F48: =F47 -> 23506.806 | G48: =G47 -> 25920.574 | H48: =H47 -> 28446.694 | I48: =I47 -> 31096.437 | J48: =J47 -> 33889.044 | K48: =K47 -> 36833.205 | L48: =L47 -> 39758.853 | M48: =M47 -> 42669.805 | ... BM48: =BM47 -> 180917.08
B50: Equity | E50: Prev Cash
B51: Paid In Capital | E51: =Assumptions!C188 -> 500000 | F51: =E51 -> 500000 | G51: =Assumptions!H220+$E51 -> 500000 | H51: =Assumptions!I220+$E51 -> 500000 | I51: =Assumptions!J220+$E51 -> 500000 | J51: =Assumptions!K220+$E51 -> 500000 | K51: =Assumptions!L220+$E51 -> 500000 | L51: =Assumptions!M220+$E51 -> 500000 | M51: =Assumptions!N220+$E51 -> 500000 | N51: =Assumptions!O220+$E51 -> 500000 | ... BM51: =Assumptions!BN220+$E51 -> 500000
B52: Accumulated Retained Earnings | F52: =E52+F30 -> -258997.36 | G52: =F52+G30 -> -511213.7 | H52: =G52+H30 -> -758949.76 | I52: =H52+I30 -> -1001986.3 | J52: =I52+J30 -> -1240069.8 | K52: =J52+K30 -> -1472931.7 | L52: =K52+L30 -> -1700604.7 | M52: =L52+M30 -> -1923114.8 | ... BM52: =BL52+BM30 -> -6854596.8
B53: Total Equity | F53: =SUM(F51:F52) -> 241002.64 | G53: =SUM(G51:G52) -> -11213.704 | H53: =SUM(H51:H52) -> -258949.76 | I53: =SUM(I51:I52) -> -501986.26 | J53: =SUM(J51:J52) -> -740069.84 | K53: =SUM(K51:K52) -> -972931.71 | L53: =SUM(L51:L52) -> -1200604.7 | M53: =SUM(M51:M52) -> -1423114.8 | ... BM53: =SUM(BM51:BM52) -> -6354596.8
B55: Total Liabilities & Owner's Equity | F55: =F53+F48 -> 264509.44 | G55: =G53+G48 -> 14706.87 | H55: =H53+H48 -> -230503.06 | I55: =I53+I48 -> -470889.83 | J55: =J53+J48 -> -706180.8 | K55: =K53+K48 -> -936098.5 | L55: =L53+L48 -> -1160845.8 | M55: =M53+M48 -> -1380445 | ... BM55: =BM53+BM48 -> -6173679.7
B57: Balance Check | F57: =IF(ABS(F55-F43)>0.001,"ERROR","OK") -> OK | G57: =IF(ABS(G55-G43)>0.001,"ERROR","OK") -> OK | H57: =IF(ABS(H55-H43)>0.001,"ERROR","OK") -> OK | I57: =IF(ABS(I55-I43)>0.001,"ERROR","OK") -> OK | J57: =IF(ABS(J55-J43)>0.001,"ERROR","OK") -> OK | K57: =IF(ABS(K55-K43)>0.001,"ERROR","OK") -> OK | L57: =IF(ABS(L55-L43)>0.001,"ERROR","OK") -> OK | M57: =IF(ABS(M55-M43)>0.001,"ERROR","OK") -> OK | ... BM57: =IF(ABS(BM55-BM43)>0.001,"ERROR","OK") -> OK
B59: Statement of Cash Flows:
B61: Operating Cash Flows
B62: Net Income | F62: =F52-E52 -> -258997.36 | G62: =G52-F52 -> -252216.34 | H62: =H52-G52 -> -247736.05 | I62: =I52-H52 -> -243036.51 | J62: =J52-I52 -> -238083.58 | K62: =K52-J52 -> -232861.86 | L62: =L52-K52 -> -227672.98 | M62: =M52-L52 -> -222510.16 | ... BM62: =BM52-BL52 -> 16558.677
B63: Depreciation | F63: =E42-F42 -> 0 | G63: =F42-G42 -> 0 | H63: =G42-H42 -> 0 | I63: =H42-I42 -> 0 | J63: =I42-J42 -> 0 | K63: =J42-K42 -> 0 | L63: =K42-L42 -> 0 | M63: =L42-M42 -> 0 | ... BM63: =BL42-BM42 -> 0
B64: Change in Accounts Receivable | F64: =E38-F38 -> -4258.125 | G64: =F38-G38 -> -4554.2781 | H64: =G38-H38 -> -4766.265 | I64: =H38-I38 -> -4999.5155 | J64: =I38-J38 -> -5269.0696 | K64: =J38-K38 -> -5555.0206 | L64: =K38-L38 -> -5520.0913 | M64: =L38-M38 -> -5492.3605 | ... BM64: =BL38-BM38 -> -4713.2102
B65: Change in Accounts Payable | F65: =F47-E47 -> 23506.806 | G65: =G47-F47 -> 2413.7674 | H65: =H47-G47 -> 2526.1204 | I65: =I47-H47 -> 2649.7432 | J65: =J47-I47 -> 2792.6069 | K65: =K47-J47 -> 2944.1609 | L65: =L47-K47 -> 2925.6484 | M65: =M47-L47 -> 2910.9511 | ... BM65: =BM47-BL47 -> 2498.0014
B66: Total Operating Cash Flows | F66: =SUM(F62:F65) -> -239748.68 | G66: =SUM(G62:G65) -> -254356.85 | H66: =SUM(H62:H65) -> -249976.2 | I66: =SUM(I62:I65) -> -245386.28 | J66: =SUM(J62:J65) -> -240560.04 | K66: =SUM(K62:K65) -> -235472.72 | L66: =SUM(L62:L65) -> -230267.42 | M66: =SUM(M62:M65) -> -225091.57 | ... BM66: =SUM(BM62:BM65) -> 14343.468
B68: Investing Cash Flows
B69: Changes in Fixed Assets | F69: =E41-F41 -> 0 | G69: =F41-G41 -> 0 | H69: =G41-H41 -> 0 | I69: =H41-I41 -> 0 | J69: =I41-J41 -> 0 | K69: =J41-K41 -> 0 | L69: =K41-L41 -> 0 | M69: =L41-M41 -> 0 | ... BM69: =BL41-BM41 -> 0
B70: Total Investing Cash Flows | F70: =F69 -> 0 | G70: =G69 -> 0 | H70: =H69 -> 0 | I70: =I69 -> 0 | J70: =J69 -> 0 | K70: =K69 -> 0 | L70: =L69 -> 0 | M70: =M69 -> 0 | ... BM70: =BM69 -> 0
B72: Financing Cash Flows
B73: Changes in Paid in Capital | F73: =F51-E51 -> 0 | G73: =G51-F51 -> 0 | H73: =H51-G51 -> 0 | I73: =I51-H51 -> 0 | J73: =J51-I51 -> 0 | K73: =K51-J51 -> 0 | L73: =L51-K51 -> 0 | M73: =M51-L51 -> 0 | ... BM73: =BM51-BL51 -> 0
B74: Total Financing Cash Flows | F74: =F73 -> 0 | G74: =G73 -> 0 | H74: =H73 -> 0 | I74: =I73 -> 0 | J74: =J73 -> 0 | K74: =K73 -> 0 | L74: =L73 -> 0 | M74: =M73 -> 0 | ... BM74: =BM73 -> 0
B76: Beginning Cash | F76: =Assumptions!C188 -> 500000 | G76: =F80 -> 260251.32 | H76: =G80 -> 5894.467 | I76: =H80 -> -244081.73 | J76: =I80 -> -489468.01 | K76: =J80 -> -730028.05 | L76: =K80 -> -965500.78 | M76: =L80 -> -1195768.2 | N76: =M80 -> -1420859.8 | ... BM76: =BL80 -> -6489281.8
B78: Change in Cash | F78: =F74+F70+F66 -> -239748.68 | G78: =G74+G70+G66 -> -254356.85 | H78: =H74+H70+H66 -> -249976.2 | I78: =I74+I70+I66 -> -245386.28 | J78: =J74+J70+J66 -> -240560.04 | K78: =K74+K70+K66 -> -235472.72 | L78: =L74+L70+L66 -> -230267.42 | M78: =M74+M70+M66 -> -225091.57 | ... BM78: =BM74+BM70+BM66 -> 14343.468
B80: Ending Cash | F80: =F76+F78 -> 260251.32 | G80: =G76+G78 -> 5894.467 | H80: =H76+H78 -> -244081.73 | I80: =I76+I78 -> -489468.01 | J80: =J76+J78 -> -730028.05 | K80: =K76+K78 -> -965500.78 | L80: =L76+L78 -> -1195768.2 | M80: =M76+M78 -> -1420859.8 | ... BM80: =BM76+BM78 -> -6474938.3
C1006: Forecastr Template
