Workbook

Sheet Overview
C2: YOUR LOGO HERE
C4: Financial Model
G5: Welcome! This template was created by Forecastr's team of Financial Analysts and Fractional CFOs to help our fellow founders create better financial models for their startups and small businesses. Forecastr is an out-of-the-box finance function for your business. We provide the tools and support you need to create an investor-grade financial model. Our analysts work with you every step of the way to build a model that's customized to fit your business, keep it up to date, and generate insightful reports to share with your investors and other stakeholders. ✔ Impress your investors ✔ Hit your growth targets ✔ Never run out of cash
C7: Your Website Link Here
C10: Table of Contents
C12: Assumptions
C14: Financials
I18: SCHEDULE A MODELING SESSION WITH A MEMBER OF OUR TEAM

Sheet Assumptions
B1: Year Counter | G1: 1 | H1: 1 | I1: 1 | J1: 1 | K1: 1 | L1: 1 | M1: 1 | N1: 1 | O1: 1 | P1: 1 | Q1: 1 | R1: 1 | S1: =G1+1 -> 2 | T1: =H1+1 -> 2 | U1: =I1+1 -> 2 | V1: =J1+1 -> 2 | W1: =K1+1 -> 2 | X1: =L1+1 -> 2 | Y1: =M1+1 -> 2 | Z1: =N1+1 -> 2 | ... BN1: =BB1+1 -> 5
B2: Year | G2: =YEAR(G4) -> 2026 | H2: =YEAR(H4) -> 2026 | I2: =YEAR(I4) -> 2026 | J2: =YEAR(J4) -> 2026 | K2: =YEAR(K4) -> 2026 | L2: =YEAR(L4) -> 2026 | M2: =YEAR(M4) -> 2026 | N2: =YEAR(N4) -> 2026 | ... BN2: =YEAR(BN4) -> 2031
B3: Month Counter | G3: 1 | H3: =G3+1 -> 2 | I3: =H3+1 -> 3 | J3: =I3+1 -> 4 | K3: =J3+1 -> 5 | L3: =K3+1 -> 6 | M3: =L3+1 -> 7 | N3: =M3+1 -> 8 | O3: =N3+1 -> 9 | ... BN3: =BM3+1 -> 60
B4: Date | G4: =eomonth(today(),0) -> 46081 | H4: =EOMONTH(G4,1) -> 46112 | I4: =EOMONTH(H4,1) -> 46142 | J4: =EOMONTH(I4,1) -> 46173 | K4: =EOMONTH(J4,1) -> 46203 | L4: =EOMONTH(K4,1) -> 46234 | M4: =EOMONTH(L4,1) -> 46265 | N4: =EOMONTH(M4,1) -> 46295 | O4: =EOMONTH(N4,1) -> 46326 | ... BN4: =EOMONTH(BM4,1) -> 47879
B6: Customer Acquisition:
B8: Build Customer Acquisition Channels
B10: Organic / Word of Mouth
B11: App Traffic | D11: 1000 | G11: =D11 -> 1000 | H11: =G11 -> 1000 | I11: =H11 -> 1000 | J11: =I11 -> 1000 | K11: =J11 -> 1000 | L11: =K11 -> 1000 | M11: =L11 -> 1000 | N11: =M11 -> 1000 | O11: =N11 -> 1000 | ... BN11: =BM11 -> 1000
B12: Conversion Rate | D12: 0.05 | G12: =D12 -> 0.05 | H12: =G12 -> 0.05 | I12: =H12 -> 0.05 | J12: =I12 -> 0.05 | K12: =J12 -> 0.05 | L12: =K12 -> 0.05 | M12: =L12 -> 0.05 | N12: =M12 -> 0.05 | O12: =N12 -> 0.05 | ... BN12: =BM12 -> 0.05
B13: New Customers | G13: =G11*G12 -> 50 | H13: =H11*H12 -> 50 | I13: =I11*I12 -> 50 | J13: =J11*J12 -> 50 | K13: =K11*K12 -> 50 | L13: =L11*L12 -> 50 | M13: =M11*M12 -> 50 | N13: =N11*N12 -> 50 | ... BN13: =BN11*BN12 -> 50
B15: Paid Advertising
B16: Budget per Month | D16: 5000 | G16: =D16 -> 5000 | H16: =G16 -> 5000 | I16: =H16 -> 5000 | J16: =I16 -> 5000 | K16: =J16 -> 5000 | L16: =K16 -> 5000 | M16: =L16 -> 5000 | N16: =M16 -> 5000 | O16: =N16 -> 5000 | ... BN16: =BM16 -> 5000
B17: Average CPC | D17: 2 | G17: =D17 -> 2 | H17: =G17 -> 2 | I17: =H17 -> 2 | J17: =I17 -> 2 | K17: =J17 -> 2 | L17: =K17 -> 2 | M17: =L17 -> 2 | N17: =M17 -> 2 | O17: =N17 -> 2 | ... BN17: =BM17 -> 2
B18: Conversion Rate | D18: 0.05 | G18: =D18 -> 0.05 | H18: =G18 -> 0.05 | I18: =H18 -> 0.05 | J18: =I18 -> 0.05 | K18: =J18 -> 0.05 | L18: =K18 -> 0.05 | M18: =L18 -> 0.05 | N18: =M18 -> 0.05 | O18: =N18 -> 0.05 | ... BN18: =BM18 -> 0.05
B19: New Customers | G19: =(G16/G17)*G18 -> 125 | H19: =(H16/H17)*H18 -> 125 | I19: =(I16/I17)*I18 -> 125 | J19: =(J16/J17)*J18 -> 125 | K19: =(K16/K17)*K18 -> 125 | L19: =(L16/L17)*L18 -> 125 | M19: =(M16/M17)*M18 -> 125 | N19: =(N16/N17)*N18 -> 125 | ... BN19: =(BN16/BN17)*BN18 -> 125
B21: Affiliates
B22: Number of Affiliates | D22: 5 | G22: =D22 -> 5 | H22: =G22 -> 5 | I22: =H22 -> 5 | J22: =I22 -> 5 | K22: =J22 -> 5 | L22: =K22 -> 5 | M22: =L22 -> 5 | N22: =M22 -> 5 | O22: =N22 -> 5 | ... BN22: =BM22 -> 5
B23: New Monthly Leads per Affiliate | D23: 50 | G23: =D23 -> 50 | H23: =G23 -> 50 | I23: =H23 -> 50 | J23: =I23 -> 50 | K23: =J23 -> 50 | L23: =K23 -> 50 | M23: =L23 -> 50 | N23: =M23 -> 50 | O23: =N23 -> 50 | ... BN23: =BM23 -> 50
B24: Conversion Rate | D24: 0.05 | G24: =D24 -> 0.05 | H24: =G24 -> 0.05 | I24: =H24 -> 0.05 | J24: =I24 -> 0.05 | K24: =J24 -> 0.05 | L24: =K24 -> 0.05 | M24: =L24 -> 0.05 | N24: =M24 -> 0.05 | O24: =N24 -> 0.05 | ... BN24: =BM24 -> 0.05
B25: New Customers | G25: =G22*G23*G24 -> 12.5 | H25: =H22*H23*H24 -> 12.5 | I25: =I22*I23*I24 -> 12.5 | J25: =J22*J23*J24 -> 12.5 | K25: =K22*K23*K24 -> 12.5 | L25: =L22*L23*L24 -> 12.5 | M25: =M22*M23*M24 -> 12.5 | N25: =N22*N23*N24 -> 12.5 | ... BN25: =BN22*BN23*BN24 -> 12.5
B27: Transactional
B28: Days Selling | D28: 1 | G28: 1 | H28: 0 | I28: 0 | J28: 0 | K28: 0 | L28: 0 | M28: 0 | N28: 0 | O28: 0 | P28: 0 | Q28: 0 | R28: 0 | S28: 0 | T28: 0 | U28: 0 | V28: 0 | W28: 0 | X28: 0 | Y28: 0 | Z28: 0 | AA28: 0 | AB28: 0 | AC28: 0 | AD28: 0 | AE28: 0 | AF28: 0 | AG28: 0 | AH28: 0 | AI28: 0 | AJ28: 0 | AK28: 0 | AL28: 0 | AM28: 0 | AN28: 0 | AO28: 0 | AP28: 0 | AQ28: 0 | AR28: 0 | AS28: 0 | AT28: 0 | AU28: 0 | AV28: 0 | AW28: 0 | AX28: 0 | AY28: 0 | AZ28: 0 | BA28: 0 | BB28: 0 | BC28: 0 | BD28: 0 | BE28: 0 | BF28: 0 | BG28: 0 | BH28: 0 | BI28: 0 | BJ28: 0 | BK28: 0 | BL28: 0 | BM28: 0 | BN28: 0
B29: New Leads per Day | D29: 10 | G29: =D29 -> 10 | H29: =G29 -> 10 | I29: =H29 -> 10 | J29: =I29 -> 10 | K29: =J29 -> 10 | L29: =K29 -> 10 | M29: =L29 -> 10 | N29: =M29 -> 10 | O29: =N29 -> 10 | ... BN29: =BM29 -> 10
B30: Conversion Rate | D30: 0.05 | G30: =D30 -> 0.05 | H30: =G30 -> 0.05 | I30: =H30 -> 0.05 | J30: =I30 -> 0.05 | K30: =J30 -> 0.05 | L30: =K30 -> 0.05 | M30: =L30 -> 0.05 | N30: =M30 -> 0.05 | O30: =N30 -> 0.05 | ... BN30: =BM30 -> 0.05
B31: New Customers | G31: =G28*G29*G30 -> 0.5 | H31: =H28*H29*H30 -> 0 | I31: =I28*I29*I30 -> 0 | J31: =J28*J29*J30 -> 0 | K31: =K28*K29*K30 -> 0 | L31: =L28*L29*L30 -> 0 | M31: =M28*M29*M30 -> 0 | N31: =N28*N29*N30 -> 0 | ... BN31: =BN28*BN29*BN30 -> 0
B33: Influencers
B34: Number of Influencers | D34: 2 | G34: =D34 -> 2 | H34: =G34 -> 2 | I34: =H34 -> 2 | J34: =I34 -> 2 | K34: =J34 -> 2 | L34: =K34 -> 2 | M34: =L34 -> 2 | N34: =M34 -> 2 | O34: =N34 -> 2 | ... BN34: =BM34 -> 2
B35: New Monthly Posts per Influencer | D35: 100 | G35: =D35 -> 100 | H35: =G35 -> 100 | I35: =H35 -> 100 | J35: =I35 -> 100 | K35: =J35 -> 100 | L35: =K35 -> 100 | M35: =L35 -> 100 | N35: =M35 -> 100 | O35: =N35 -> 100 | ... BN35: =BM35 -> 100
B36: New Monthly Leads per Post | D36: 5 | G36: =D36 -> 5 | H36: =G36 -> 5 | I36: =H36 -> 5 | J36: =I36 -> 5 | K36: =J36 -> 5 | L36: =K36 -> 5 | M36: =L36 -> 5 | N36: =M36 -> 5 | O36: =N36 -> 5 | ... BN36: =BM36 -> 5
B37: Conversion Rate | D37: 0.05 | G37: =D37 -> 0.05 | H37: =G37 -> 0.05 | I37: =H37 -> 0.05 | J37: =I37 -> 0.05 | K37: =J37 -> 0.05 | L37: =K37 -> 0.05 | M37: =L37 -> 0.05 | N37: =M37 -> 0.05 | O37: =N37 -> 0.05 | ... BN37: =BM37 -> 0.05
B38: New Customers | G38: =G34*G35*G36*G37 -> 50 | H38: =H34*H35*H36*H37 -> 50 | I38: =I34*I35*I36*I37 -> 50 | J38: =J34*J35*J36*J37 -> 50 | K38: =K34*K35*K36*K37 -> 50 | L38: =L34*L35*L36*L37 -> 50 | M38: =M34*M35*M36*M37 -> 50 | N38: =N34*N35*N36*N37 -> 50 | ... BN38: =BN34*BN35*BN36*BN37 -> 50
B40: Customer Referrals
B41: Previous Months New Customers | D41: =C71 | G41: =F71 | H41: =G71 -> 265.5 | I41: =H71 -> 273.9825 | J41: =I71 -> 274.10974 | K41: =J71 -> 274.11165 | L41: =K71 -> 274.11167 | M41: =L71 -> 274.11168 | N41: =M71 -> 274.11168 | ... BN41: =BM71 -> 274.11168
B42: Referral Percentage | D42: 0.3 | G42: =D42 -> 0.3 | H42: =G42 -> 0.3 | I42: =H42 -> 0.3 | J42: =I42 -> 0.3 | K42: =J42 -> 0.3 | L42: =K42 -> 0.3 | M42: =L42 -> 0.3 | N42: =M42 -> 0.3 | O42: =N42 -> 0.3 | ... BN42: =BM42 -> 0.3
B43: Conversion Rate | D43: 0.05 | G43: =D43 -> 0.05 | H43: =G43 -> 0.05 | I43: =H43 -> 0.05 | J43: =I43 -> 0.05 | K43: =J43 -> 0.05 | L43: =K43 -> 0.05 | M43: =L43 -> 0.05 | N43: =M43 -> 0.05 | O43: =N43 -> 0.05 | ... BN43: =BM43 -> 0.05
B44: New Customers | G44: =G41*G42*G43 -> 0 | H44: =H41*H42*H43 -> 3.9825 | I44: =I41*I42*I43 -> 4.1097375 | J44: =J41*J42*J43 -> 4.1116461 | K44: =K41*K42*K43 -> 4.1116747 | L44: =L41*L42*L43 -> 4.1116751 | M44: =M41*M42*M43 -> 4.1116751 | N44: =N41*N42*N43 -> 4.1116751 | ... BN44: =BN41*BN42*BN43 -> 4.1116751
B46: Partnerships
B47: Active Partnerships | D47: 2 | G47: =D47 -> 2 | H47: =G47 -> 2 | I47: =H47 -> 2 | J47: =I47 -> 2 | K47: =J47 -> 2 | L47: =K47 -> 2 | M47: =L47 -> 2 | N47: =M47 -> 2 | O47: =N47 -> 2 | ... BN47: =BM47 -> 2
B48: New Monthly Leads per Partnership | D48: 100 | G48: =D48 -> 100 | H48: =G48 -> 100 | I48: =H48 -> 100 | J48: =I48 -> 100 | K48: =J48 -> 100 | L48: =K48 -> 100 | M48: =L48 -> 100 | N48: =M48 -> 100 | O48: =N48 -> 100 | ... BN48: =BM48 -> 100
B49: Conversion Rate | D49: 0.05 | G49: =D49 -> 0.05 | H49: =G49 -> 0.05 | I49: =H49 -> 0.05 | J49: =I49 -> 0.05 | K49: =J49 -> 0.05 | L49: =K49 -> 0.05 | M49: =L49 -> 0.05 | N49: =M49 -> 0.05 | O49: =N49 -> 0.05 | ... BN49: =BM49 -> 0.05
B50: New Customers | G50: =G47*G48*G49 -> 10 | H50: =H47*H48*H49 -> 10 | I50: =I47*I48*I49 -> 10 | J50: =J47*J48*J49 -> 10 | K50: =K47*K48*K49 -> 10 | L50: =L47*L48*L49 -> 10 | M50: =M47*M48*M49 -> 10 | N50: =N47*N48*N49 -> 10 | ... BN50: =BN47*BN48*BN49 -> 10
B52: Email Marketing
B53: Mailing List Size | D53: 2000 | G53: =D53 -> 2000 | H53: =G53 -> 2000 | I53: =H53 -> 2000 | J53: =I53 -> 2000 | K53: =J53 -> 2000 | L53: =K53 -> 2000 | M53: =L53 -> 2000 | N53: =M53 -> 2000 | O53: =N53 -> 2000 | ... BN53: =BM53 -> 2000
B54: Average Number of Emails Sent a Month | D54: 2 | G54: =D54 -> 2 | H54: =G54 -> 2 | I54: =H54 -> 2 | J54: =I54 -> 2 | K54: =J54 -> 2 | L54: =K54 -> 2 | M54: =L54 -> 2 | N54: =M54 -> 2 | O54: =N54 -> 2 | ... BN54: =BM54 -> 2
B55: Response Rate per Email | D55: 0.05 | G55: =D55 -> 0.05 | H55: =G55 -> 0.05 | I55: =H55 -> 0.05 | J55: =I55 -> 0.05 | K55: =J55 -> 0.05 | L55: =K55 -> 0.05 | M55: =L55 -> 0.05 | N55: =M55 -> 0.05 | O55: =N55 -> 0.05 | ... BN55: =BM55 -> 0.05
B56: Conversion Rate | D56: 0.05 | G56: =D56 -> 0.05 | H56: =G56 -> 0.05 | I56: =H56 -> 0.05 | J56: =I56 -> 0.05 | K56: =J56 -> 0.05 | L56: =K56 -> 0.05 | M56: =L56 -> 0.05 | N56: =M56 -> 0.05 | O56: =N56 -> 0.05 | ... BN56: =BM56 -> 0.05
B57: New Customers | G57: =G53*G54*G55*G56 -> 10 | H57: =H53*H54*H55*H56 -> 10 | I57: =I53*I54*I55*I56 -> 10 | J57: =J53*J54*J55*J56 -> 10 | K57: =K53*K54*K55*K56 -> 10 | L57: =L53*L54*L55*L56 -> 10 | M57: =M53*M54*M55*M56 -> 10 | N57: =N53*N54*N55*N56 -> 10 | ... BN57: =BN53*BN54*BN55*BN56 -> 10
B59: Content Marketing
B60: New Pieces of Content | D60: 3 | G60: =D60 -> 3 | H60: =G60 -> 3 | I60: =H60 -> 3 | J60: =I60 -> 3 | K60: =J60 -> 3 | L60: =K60 -> 3 | M60: =L60 -> 3 | N60: =M60 -> 3 | O60: =N60 -> 3 | ... BN60: =BM60 -> 3
B61: New Leads per Piece of Content | D61: 50 | G61: =D61 -> 50 | H61: =G61 -> 50 | I61: =H61 -> 50 | J61: =I61 -> 50 | K61: =J61 -> 50 | L61: =K61 -> 50 | M61: =L61 -> 50 | N61: =M61 -> 50 | O61: =N61 -> 50 | ... BN61: =BM61 -> 50
B62: Conversion Rate | D62: 0.05 | G62: =D62 -> 0.05 | H62: =G62 -> 0.05 | I62: =H62 -> 0.05 | J62: =I62 -> 0.05 | K62: =J62 -> 0.05 | L62: =K62 -> 0.05 | M62: =L62 -> 0.05 | N62: =M62 -> 0.05 | O62: =N62 -> 0.05 | ... BN62: =BM62 -> 0.05
B63: New Customers | G63: =G60*G61*G62 -> 7.5 | H63: =H60*H61*H62 -> 7.5 | I63: =I60*I61*I62 -> 7.5 | J63: =J60*J61*J62 -> 7.5 | K63: =K60*K61*K62 -> 7.5 | L63: =L60*L61*L62 -> 7.5 | M63: =M60*M61*M62 -> 7.5 | N63: =N60*N61*N62 -> 7.5 | ... BN63: =BN60*BN61*BN62 -> 7.5
B65: Direct Sales Team
B66: Leads | D66: 25 | G66: =D66 -> 25 | H66: =G66 -> 25 | I66: =H66 -> 25 | J66: =I66 -> 25 | K66: =J66 -> 25 | L66: =K66 -> 25 | M66: =L66 -> 25 | N66: =M66 -> 25 | O66: =N66 -> 25 | ... BN66: =BM66 -> 25
B67: Sales Cycle | D67: 2 | G67: =D67 -> 2 | H67: =G67 -> 2 | I67: =H67 -> 2 | J67: =I67 -> 2 | K67: =J67 -> 2 | L67: =K67 -> 2 | M67: =L67 -> 2 | N67: =M67 -> 2 | O67: =N67 -> 2 | ... BN67: =BM67 -> 2
B68: Conversion Rate | D68: 0.2 | G68: =D68 -> 0.2 | H68: =G68 -> 0.2 | I68: =H68 -> 0.2 | J68: =I68 -> 0.2 | K68: =J68 -> 0.2 | L68: =K68 -> 0.2 | M68: =L68 -> 0.2 | N68: =M68 -> 0.2 | O68: =N68 -> 0.2 | ... BN68: =BM68 -> 0.2
B69: New Customers | G69: =IFERROR(offset(G66,,-G67+1)*G68,0) -> 0 | H69: =IFERROR(offset(H66,,-H67+1)*H68,0) -> 5 | I69: =IFERROR(offset(I66,,-I67+1)*I68,0) -> 5 | J69: =IFERROR(offset(J66,,-J67+1)*J68,0) -> 5 | K69: =IFERROR(offset(K66,,-K67+1)*K68,0) -> 5 | L69: =IFERROR(offset(L66,,-L67+1)*L68,0) -> 5 | M69: =IFERROR(offset(M66,,-M67+1)*M68,0) -> 5 | N69: =IFERROR(offset(N66,,-N67+1)*N68,0) -> 5 | ... BN69: =IFERROR(offset(BN66,,-BN67+1)*BN68,0) -> 5
B71: Total New Customers | G71: =G13+G19+G25+G31+G38+G44+G50+G57+G63+G69 -> 265.5 | H71: =H13+H19+H25+H31+H38+H44+H50+H57+H63+H69 -> 273.9825 | I71: =I13+I19+I25+I31+I38+I44+I50+I57+I63+I69 -> 274.10974 | J71: =J13+J19+J25+J31+J38+J44+J50+J57+J63+J69 -> 274.11165 | K71: =K13+K19+K25+K31+K38+K44+K50+K57+K63+K69 -> 274.11167 | L71: =L13+L19+L25+L31+L38+L44+L50+L57+L63+L69 -> 274.11168 | M71: =M13+M19+M25+M31+M38+M44+M50+M57+M63+M69 -> 274.11168 | N71: =N13+N19+N25+N31+N38+N44+N50+N57+N63+N69 -> 274.11168 | ... BN71: =BN13+BN19+BN25+BN31+BN38+BN44+BN50+BN57+BN63+BN69 -> 274.11168
B73: Revenue - E-Commerce:
B75: Product Purchases #1
B76: % of Total New Customers | D76: 0.5 | G76: =D76 -> 0.5 | H76: =G76 -> 0.5 | I76: =H76 -> 0.5 | J76: =I76 -> 0.5 | K76: =J76 -> 0.5 | L76: =K76 -> 0.5 | M76: =L76 -> 0.5 | N76: =M76 -> 0.5 | O76: =N76 -> 0.5 | ... BN76: =BM76 -> 0.5
B77: New Customers | G77: =G76*G$71 -> 132.75 | H77: =H76*H$71 -> 136.99125 | I77: =I76*I$71 -> 137.05487 | J77: =J76*J$71 -> 137.05582 | K77: =K76*K$71 -> 137.05584 | L77: =L76*L$71 -> 137.05584 | M77: =M76*M$71 -> 137.05584 | N77: =N76*N$71 -> 137.05584 | ... BN77: =BN76*BN$71 -> 137.05584
B78: Returning Customer Rate | D78: 0.5 | G78: =D78 -> 0.5 | H78: =G78 -> 0.5 | I78: =H78 -> 0.5 | J78: =I78 -> 0.5 | K78: =J78 -> 0.5 | L78: =K78 -> 0.5 | M78: =L78 -> 0.5 | N78: =M78 -> 0.5 | O78: =N78 -> 0.5 | ... BN78: =BM78 -> 0.5
B79: Returning Customers | G79: =G81*G78 -> 0 | H79: =H81*H78 -> 66.375 | I79: =I81*I78 -> 101.68313 | J79: =J81*J78 -> 119.369 | K79: =K81*K78 -> 128.21241 | L79: =L81*L78 -> 132.63412 | M79: =M81*M78 -> 134.84498 | N79: =N81*N78 -> 135.95041 | ... BN79: =BN81*BN78 -> 137.05584
B80: Total Customers | G80: =G79+G77 -> 132.75 | H80: =H79+H77 -> 203.36625 | I80: =I79+I77 -> 238.73799 | J80: =J79+J77 -> 256.42482 | K80: =K79+K77 -> 265.26825 | L80: =L79+L77 -> 269.68996 | M80: =M79+M77 -> 271.90082 | N80: =N79+N77 -> 273.00625 | ... BN80: =BN79+BN77 -> 274.11168
B81: Previous Months Customers | G81: =F80 | H81: =G80 -> 132.75 | I81: =H80 -> 203.36625 | J81: =I80 -> 238.73799 | K81: =J80 -> 256.42482 | L81: =K80 -> 265.26825 | M81: =L80 -> 269.68996 | N81: =M80 -> 271.90082 | ... BN81: =BM80 -> 274.11168
B82: Average Monthly Orders per Customer | D82: 3 | G82: =D82 -> 3 | H82: =G82 -> 3 | I82: =H82 -> 3 | J82: =I82 -> 3 | K82: =J82 -> 3 | L82: =K82 -> 3 | M82: =L82 -> 3 | N82: =M82 -> 3 | O82: =N82 -> 3 | ... BN82: =BM82 -> 3
B83: Total Orders | G83: =G82*G80 -> 398.25 | H83: =H82*H80 -> 610.09875 | I83: =I82*I80 -> 716.21398 | J83: =J82*J80 -> 769.27446 | K83: =K82*K80 -> 795.80474 | L83: =L82*L80 -> 809.06988 | M83: =M82*M80 -> 815.70245 | N83: =N82*N80 -> 819.01874 | ... BN83: =BN82*BN80 -> 822.33503
B84: Average Order Value | D84: 50 | G84: =D84 -> 50 | H84: =G84 -> 50 | I84: =H84 -> 50 | J84: =I84 -> 50 | K84: =J84 -> 50 | L84: =K84 -> 50 | M84: =L84 -> 50 | N84: =M84 -> 50 | O84: =N84 -> 50 | ... BN84: =BM84 -> 50
B85: Revenue | G85: =G84*G83 -> 19912.5 | H85: =H84*H83 -> 30504.938 | I85: =I84*I83 -> 35810.699 | J85: =J84*J83 -> 38463.723 | K85: =K84*K83 -> 39790.237 | L85: =L84*L83 -> 40453.494 | M85: =M84*M83 -> 40785.123 | N85: =N84*N83 -> 40950.937 | ... BN85: =BN84*BN83 -> 41116.751
B87: Product Purchases #2
B88: % of Total New Customers | D88: 0.3 | G88: =D88 -> 0.3 | H88: =G88 -> 0.3 | I88: =H88 -> 0.3 | J88: =I88 -> 0.3 | K88: =J88 -> 0.3 | L88: =K88 -> 0.3 | M88: =L88 -> 0.3 | N88: =M88 -> 0.3 | O88: =N88 -> 0.3 | ... BN88: =BM88 -> 0.3
B89: New Customers | G89: =G88*G$71 -> 79.65 | H89: =H88*H$71 -> 82.19475 | I89: =I88*I$71 -> 82.232921 | J89: =J88*J$71 -> 82.233494 | K89: =K88*K$71 -> 82.233502 | L89: =L88*L$71 -> 82.233503 | M89: =M88*M$71 -> 82.233503 | N89: =N88*N$71 -> 82.233503 | ... BN89: =BN88*BN$71 -> 82.233503
B90: Returning Customer Rate | D90: 0.5 | G90: =D90 -> 0.5 | H90: =G90 -> 0.5 | I90: =H90 -> 0.5 | J90: =I90 -> 0.5 | K90: =J90 -> 0.5 | L90: =K90 -> 0.5 | M90: =L90 -> 0.5 | N90: =M90 -> 0.5 | O90: =N90 -> 0.5 | ... BN90: =BM90 -> 0.5
B91: Returning Customers | G91: =G93*G90 -> 0 | H91: =H93*H90 -> 39.825 | I91: =I93*I90 -> 61.009875 | J91: =J93*J90 -> 71.621398 | K91: =K93*K90 -> 76.927446 | L91: =L93*L90 -> 79.580474 | M91: =M93*M90 -> 80.906988 | N91: =N93*N90 -> 81.570245 | ... BN91: =BN93*BN90 -> 82.233503
B92: Total Customers | G92: =G91+G89 -> 79.65 | H92: =H91+H89 -> 122.01975 | I92: =I91+I89 -> 143.2428 | J92: =J91+J89 -> 153.85489 | K92: =K91+K89 -> 159.16095 | L92: =L91+L89 -> 161.81398 | M92: =M91+M89 -> 163.14049 | N92: =N91+N89 -> 163.80375 | ... BN92: =BN91+BN89 -> 164.46701
B93: Previous Months Customers | G93: =F92 | H93: =G92 -> 79.65 | I93: =H92 -> 122.01975 | J93: =I92 -> 143.2428 | K93: =J92 -> 153.85489 | L93: =K92 -> 159.16095 | M93: =L92 -> 161.81398 | N93: =M92 -> 163.14049 | ... BN93: =BM92 -> 164.46701
B94: Average Monthly Orders per Customer | D94: 2 | G94: =D94 -> 2 | H94: =G94 -> 2 | I94: =H94 -> 2 | J94: =I94 -> 2 | K94: =J94 -> 2 | L94: =K94 -> 2 | M94: =L94 -> 2 | N94: =M94 -> 2 | O94: =N94 -> 2 | ... BN94: =BM94 -> 2
B95: Total Orders | G95: =G94*G92 -> 159.3 | H95: =H94*H92 -> 244.0395 | I95: =I94*I92 -> 286.48559 | J95: =J94*J92 -> 307.70978 | K95: =K94*K92 -> 318.3219 | L95: =L94*L92 -> 323.62795 | M95: =M94*M92 -> 326.28098 | N95: =N94*N92 -> 327.6075 | ... BN95: =BN94*BN92 -> 328.93401
B96: Average Order Value | D96: 250 | G96: =D96 -> 250 | H96: =G96 -> 250 | I96: =H96 -> 250 | J96: =I96 -> 250 | K96: =J96 -> 250 | L96: =K96 -> 250 | M96: =L96 -> 250 | N96: =M96 -> 250 | O96: =N96 -> 250 | ... BN96: =BM96 -> 250
B97: Revenue | G97: =G96*G95 -> 39825 | H97: =H96*H95 -> 61009.875 | I97: =I96*I95 -> 71621.398 | J97: =J96*J95 -> 76927.446 | K97: =K96*K95 -> 79580.474 | L97: =L96*L95 -> 80906.988 | M97: =M96*M95 -> 81570.245 | N97: =N96*N95 -> 81901.874 | ... BN97: =BN96*BN95 -> 82233.503
B99: Monthly Subscription Purchases
B100: % of Total New Customers | D100: 0.2 | G100: =D100 -> 0.2 | H100: =G100 -> 0.2 | I100: =H100 -> 0.2 | J100: =I100 -> 0.2 | K100: =J100 -> 0.2 | L100: =K100 -> 0.2 | M100: =L100 -> 0.2 | N100: =M100 -> 0.2 | O100: =N100 -> 0.2 | ... BN100: =BM100 -> 0.2
B101: New Customers | G101: =G100*G$71 -> 53.1 | H101: =H100*H$71 -> 54.7965 | I101: =I100*I$71 -> 54.821948 | J101: =J100*J$71 -> 54.822329 | K101: =K100*K$71 -> 54.822335 | L101: =L100*L$71 -> 54.822335 | M101: =M100*M$71 -> 54.822335 | N101: =N100*N$71 -> 54.822335 | ... BN101: =BN100*BN$71 -> 54.822335
B102: Churn Rate | D102: 0.5 | G102: =D102 -> 0.5 | H102: =G102 -> 0.5 | I102: =H102 -> 0.5 | J102: =I102 -> 0.5 | K102: =J102 -> 0.5 | L102: =K102 -> 0.5 | M102: =L102 -> 0.5 | N102: =M102 -> 0.5 | O102: =N102 -> 0.5 | ... BN102: =BM102 -> 0.5
B103: Churned Subscriptions | G103: =G104*G102 -> 0 | H103: =H104*H102 -> 26.55 | I103: =I104*I102 -> 40.67325 | J103: =J104*J102 -> 47.747599 | K103: =K104*K102 -> 51.284964 | L103: =L104*L102 -> 53.053649 | M103: =M104*M102 -> 53.937992 | N103: =N104*N102 -> 54.380164 | ... BN103: =BN104*BN102 -> 54.822335
B104: Previous Months Active Subsciptions | G104: =E106 | H104: =G106 -> 53.1 | I104: =H106 -> 81.3465 | J104: =I106 -> 95.495198 | K104: =J106 -> 102.56993 | L104: =K106 -> 106.1073 | M104: =L106 -> 107.87598 | N104: =M106 -> 108.76033 | O104: =N106 -> 109.2025 | ... BN104: =BM106 -> 109.64467
B105: Retained Subscriptions | G105: =G104-G103 -> 0 | H105: =H104-H103 -> 26.55 | I105: =I104-I103 -> 40.67325 | J105: =J104-J103 -> 47.747599 | K105: =K104-K103 -> 51.284964 | L105: =L104-L103 -> 53.053649 | M105: =M104-M103 -> 53.937992 | N105: =N104-N103 -> 54.380164 | ... BN105: =BN104-BN103 -> 54.822335
B106: Active Subscriptions | G106: =G101+G105 -> 53.1 | H106: =H101+H105 -> 81.3465 | I106: =I101+I105 -> 95.495198 | J106: =J101+J105 -> 102.56993 | K106: =K101+K105 -> 106.1073 | L106: =L101+L105 -> 107.87598 | M106: =M101+M105 -> 108.76033 | N106: =N101+N105 -> 109.2025 | ... BN106: =BN101+BN105 -> 109.64467
B107: Price | D107: 10 | G107: =D107 -> 10 | H107: =G107 -> 10 | I107: =H107 -> 10 | J107: =I107 -> 10 | K107: =J107 -> 10 | L107: =K107 -> 10 | M107: =L107 -> 10 | N107: =M107 -> 10 | O107: =N107 -> 10 | ... BN107: =BM107 -> 10
B108: Revenue | G108: =G106*G107 -> 531 | H108: =H106*H107 -> 813.465 | I108: =I106*I107 -> 954.95197 | J108: =J106*J107 -> 1025.6993 | K108: =K106*K107 -> 1061.073 | L108: =L106*L107 -> 1078.7598 | M108: =M106*M107 -> 1087.6033 | N108: =N106*N107 -> 1092.025 | ... BN108: =BN106*BN107 -> 1096.4467
B110: + ADD MORE
B113: People:
B115: Name | C115: Salary | D115: Benefits | E115: Start Date
B116: Person 1 | C116: 100000 | D116: 0.2 | E116: 43831 | G116: =IF(G$4>=$E116,($C116/12)*(1+$D116),0) -> 10000 | H116: =IF(H$4>=$E116,($C116/12)*(1+$D116),0) -> 10000 | I116: =IF(I$4>=$E116,($C116/12)*(1+$D116),0) -> 10000 | J116: =IF(J$4>=$E116,($C116/12)*(1+$D116),0) -> 10000 | K116: =IF(K$4>=$E116,($C116/12)*(1+$D116),0) -> 10000 | L116: =IF(L$4>=$E116,($C116/12)*(1+$D116),0) -> 10000 | M116: =IF(M$4>=$E116,($C116/12)*(1+$D116),0) -> 10000 | N116: =IF(N$4>=$E116,($C116/12)*(1+$D116),0) -> 10000 | ... BN116: =IF(BN$4>=$E116,($C116/12)*(1+$D116),0) -> 10000
B117: Person 2 | C117: 100000 | D117: 0.2 | E117: 43831 | G117: =IF(G$4>=$E117,($C117/12)*(1+$D117),0) -> 10000 | H117: =IF(H$4>=$E117,($C117/12)*(1+$D117),0) -> 10000 | I117: =IF(I$4>=$E117,($C117/12)*(1+$D117),0) -> 10000 | J117: =IF(J$4>=$E117,($C117/12)*(1+$D117),0) -> 10000 | K117: =IF(K$4>=$E117,($C117/12)*(1+$D117),0) -> 10000 | L117: =IF(L$4>=$E117,($C117/12)*(1+$D117),0) -> 10000 | M117: =IF(M$4>=$E117,($C117/12)*(1+$D117),0) -> 10000 | N117: =IF(N$4>=$E117,($C117/12)*(1+$D117),0) -> 10000 | ... BN117: =IF(BN$4>=$E117,($C117/12)*(1+$D117),0) -> 10000
B118: Person 3 | C118: 100000 | D118: 0.2 | E118: 44075 | G118: =IF(G$4>=$E118,($C118/12)*(1+$D118),0) -> 10000 | H118: =IF(H$4>=$E118,($C118/12)*(1+$D118),0) -> 10000 | I118: =IF(I$4>=$E118,($C118/12)*(1+$D118),0) -> 10000 | J118: =IF(J$4>=$E118,($C118/12)*(1+$D118),0) -> 10000 | K118: =IF(K$4>=$E118,($C118/12)*(1+$D118),0) -> 10000 | L118: =IF(L$4>=$E118,($C118/12)*(1+$D118),0) -> 10000 | M118: =IF(M$4>=$E118,($C118/12)*(1+$D118),0) -> 10000 | N118: =IF(N$4>=$E118,($C118/12)*(1+$D118),0) -> 10000 | ... BN118: =IF(BN$4>=$E118,($C118/12)*(1+$D118),0) -> 10000
B119: Person 4 | C119: 100000 | D119: 0.2 | E119: 43831 | G119: =IF(G$4>=$E119,($C119/12)*(1+$D119),0) -> 10000 | H119: =IF(H$4>=$E119,($C119/12)*(1+$D119),0) -> 10000 | I119: =IF(I$4>=$E119,($C119/12)*(1+$D119),0) -> 10000 | J119: =IF(J$4>=$E119,($C119/12)*(1+$D119),0) -> 10000 | K119: =IF(K$4>=$E119,($C119/12)*(1+$D119),0) -> 10000 | L119: =IF(L$4>=$E119,($C119/12)*(1+$D119),0) -> 10000 | M119: =IF(M$4>=$E119,($C119/12)*(1+$D119),0) -> 10000 | N119: =IF(N$4>=$E119,($C119/12)*(1+$D119),0) -> 10000 | ... BN119: =IF(BN$4>=$E119,($C119/12)*(1+$D119),0) -> 10000
B120: Person 5 | C120: 100000 | D120: 0.2 | E120: 43891 | G120: =IF(G$4>=$E120,($C120/12)*(1+$D120),0) -> 10000 | H120: =IF(H$4>=$E120,($C120/12)*(1+$D120),0) -> 10000 | I120: =IF(I$4>=$E120,($C120/12)*(1+$D120),0) -> 10000 | J120: =IF(J$4>=$E120,($C120/12)*(1+$D120),0) -> 10000 | K120: =IF(K$4>=$E120,($C120/12)*(1+$D120),0) -> 10000 | L120: =IF(L$4>=$E120,($C120/12)*(1+$D120),0) -> 10000 | M120: =IF(M$4>=$E120,($C120/12)*(1+$D120),0) -> 10000 | N120: =IF(N$4>=$E120,($C120/12)*(1+$D120),0) -> 10000 | ... BN120: =IF(BN$4>=$E120,($C120/12)*(1+$D120),0) -> 10000
B121: Person 6 | C121: 75000 | D121: 0.2 | E121: 43983 | G121: =IF(G$4>=$E121,($C121/12)*(1+$D121),0) -> 7500 | H121: =IF(H$4>=$E121,($C121/12)*(1+$D121),0) -> 7500 | I121: =IF(I$4>=$E121,($C121/12)*(1+$D121),0) -> 7500 | J121: =IF(J$4>=$E121,($C121/12)*(1+$D121),0) -> 7500 | K121: =IF(K$4>=$E121,($C121/12)*(1+$D121),0) -> 7500 | L121: =IF(L$4>=$E121,($C121/12)*(1+$D121),0) -> 7500 | M121: =IF(M$4>=$E121,($C121/12)*(1+$D121),0) -> 7500 | N121: =IF(N$4>=$E121,($C121/12)*(1+$D121),0) -> 7500 | ... BN121: =IF(BN$4>=$E121,($C121/12)*(1+$D121),0) -> 7500
...

Sheet Financials
B1: Year Counter | F1: 1 | G1: 1 | H1: 1 | I1: 1 | J1: 1 | K1: 1 | L1: 1 | M1: 1 | N1: 1 | O1: 1 | P1: 1 | Q1: 1 | R1: =F1+1 -> 2 | S1: =G1+1 -> 2 | T1: =H1+1 -> 2 | U1: =I1+1 -> 2 | V1: =J1+1 -> 2 | W1: =K1+1 -> 2 | X1: =L1+1 -> 2 | Y1: =M1+1 -> 2 | ... BM1: =BA1+1 -> 5
B2: Year | F2: =YEAR(F4) -> 2026 | G2: =YEAR(G4) -> 2026 | H2: =YEAR(H4) -> 2026 | I2: =YEAR(I4) -> 2026 | J2: =YEAR(J4) -> 2026 | K2: =YEAR(K4) -> 2026 | L2: =YEAR(L4) -> 2026 | M2: =YEAR(M4) -> 2026 | ... BM2: =YEAR(BM4) -> 2031
B3: Month Counter | F3: 1 | G3: =F3+1 -> 2 | H3: =G3+1 -> 3 | I3: =H3+1 -> 4 | J3: =I3+1 -> 5 | K3: =J3+1 -> 6 | L3: =K3+1 -> 7 | M3: =L3+1 -> 8 | N3: =M3+1 -> 9 | ... BM3: =BL3+1 -> 60
B4: Date | F4: =Assumptions!G4 -> 46081 | G4: =EOMONTH(F4,1) -> 46112 | H4: =EOMONTH(G4,1) -> 46142 | I4: =EOMONTH(H4,1) -> 46173 | J4: =EOMONTH(I4,1) -> 46203 | K4: =EOMONTH(J4,1) -> 46234 | L4: =EOMONTH(K4,1) -> 46265 | M4: =EOMONTH(L4,1) -> 46295 | N4: =EOMONTH(M4,1) -> 46326 | ... BM4: =EOMONTH(BL4,1) -> 47879
B6: Income Statement:
B8: Revenue | F8: =sum(F9:F11) -> 60268.5 | G8: =sum(G9:G11) -> 92328.277 | H8: =sum(H9:H11) -> 108387.05 | I8: =sum(I9:I11) -> 116416.87 | J8: =sum(J9:J11) -> 120431.78 | K8: =sum(K9:K11) -> 122439.24 | L8: =sum(L9:L11) -> 123442.97 | M8: =sum(M9:M11) -> 123944.84 | ... BM8: =sum(BM9:BM11) -> 124446.7
B9: =Assumptions!B75 -> Product Purchases #1 | F9: =Assumptions!G85 -> 19912.5 | G9: =Assumptions!H85 -> 30504.938 | H9: =Assumptions!I85 -> 35810.699 | I9: =Assumptions!J85 -> 38463.723 | J9: =Assumptions!K85 -> 39790.237 | K9: =Assumptions!L85 -> 40453.494 | L9: =Assumptions!M85 -> 40785.123 | M9: =Assumptions!N85 -> 40950.937 | ... BN9: =Assumptions!BO85
B10: =Assumptions!B87 -> Product Purchases #2 | F10: =Assumptions!G97 -> 39825 | G10: =Assumptions!H97 -> 61009.875 | H10: =Assumptions!I97 -> 71621.398 | I10: =Assumptions!J97 -> 76927.446 | J10: =Assumptions!K97 -> 79580.474 | K10: =Assumptions!L97 -> 80906.988 | L10: =Assumptions!M97 -> 81570.245 | M10: =Assumptions!N97 -> 81901.874 | ... BN10: =Assumptions!BO97
B11: =Assumptions!B99 -> Monthly Subscription Purchases | F11: =Assumptions!G108 -> 531 | G11: =Assumptions!H108 -> 813.465 | H11: =Assumptions!I108 -> 954.95197 | I11: =Assumptions!J108 -> 1025.6993 | J11: =Assumptions!K108 -> 1061.073 | K11: =Assumptions!L108 -> 1078.7598 | L11: =Assumptions!M108 -> 1087.6033 | M11: =Assumptions!N108 -> 1092.025 | ... BM11: =Assumptions!BN108 -> 1096.4467
B13: COGS | F13: =Assumptions!G153 -> 24107.4 | G13: =Assumptions!H153 -> 36931.311 | H13: =Assumptions!I153 -> 43354.82 | I13: =Assumptions!J153 -> 46566.747 | J13: =Assumptions!K153 -> 48172.714 | K13: =Assumptions!L153 -> 48975.697 | L13: =Assumptions!M153 -> 49377.189 | M13: =Assumptions!N153 -> 49577.934 | ... BM13: =Assumptions!BN153 -> 49778.68
B15: Gross Profit | F15: =F8-F13 -> 36161.1 | G15: =G8-G13 -> 55396.967 | H15: =H8-H13 -> 65032.23 | I15: =I8-I13 -> 69850.121 | J15: =J8-J13 -> 72259.071 | K15: =K8-K13 -> 73463.545 | L15: =L8-L13 -> 74065.783 | M15: =M8-M13 -> 74366.902 | ... BM15: =BM8-BM13 -> 74668.02
B16: Gross Margin | F16: =F15/F8 -> 0.6 | G16: =G15/G8 -> 0.6 | H16: =H15/H8 -> 0.6 | I16: =I15/I8 -> 0.6 | J16: =J15/J8 -> 0.6 | K16: =K15/K8 -> 0.6 | L16: =L15/L8 -> 0.6 | M16: =M15/M8 -> 0.6 | ... BM16: =BM15/BM8 -> 0.6
B18: Operating Expenses
B19: Salaries & Benefits | F19: =SUM(Assumptions!G116:G140) -> 202000 | G19: =SUM(Assumptions!H116:H140) -> 202000 | H19: =SUM(Assumptions!I116:I140) -> 202000 | I19: =SUM(Assumptions!J116:J140) -> 202000 | J19: =SUM(Assumptions!K116:K140) -> 202000 | K19: =SUM(Assumptions!L116:L140) -> 202000 | L19: =SUM(Assumptions!M116:M140) -> 202000 | M19: =SUM(Assumptions!N116:N140) -> 202000 | ... BM19: =SUM(Assumptions!BN116:BN140) -> 202000
B20: =Assumptions!B155 -> General & Admin | F20: =sum(Assumptions!G156:G163) -> 20000 | G20: =sum(Assumptions!H156:H163) -> 20000 | H20: =sum(Assumptions!I156:I163) -> 20000 | I20: =sum(Assumptions!J156:J163) -> 20000 | J20: =sum(Assumptions!K156:K163) -> 20000 | K20: =sum(Assumptions!L156:L163) -> 20000 | L20: =sum(Assumptions!M156:M163) -> 20000 | M20: =sum(Assumptions!N156:N163) -> 20000 | ... BM20: =sum(Assumptions!BN156:BN163) -> 20000
B21: =Assumptions!B166 -> Sales & Marketing | F21: =sum(Assumptions!G167:G168) -> 14821.48 | G21: =sum(Assumptions!H167:H168) -> 17386.262 | H21: =sum(Assumptions!I167:I168) -> 18670.964 | I21: =sum(Assumptions!J167:J168) -> 19313.349 | J21: =sum(Assumptions!K167:K168) -> 19634.543 | K21: =sum(Assumptions!L167:L168) -> 19795.139 | L21: =sum(Assumptions!M167:M168) -> 19875.438 | M21: =sum(Assumptions!N167:N168) -> 19915.587 | ... BM21: =sum(Assumptions!BN167:BN168) -> 19955.736
B22: =Assumptions!B171 -> Professional Fees | F22: =SUM(Assumptions!G172:G174) -> 5000 | G22: =SUM(Assumptions!H172:H174) -> 5000 | H22: =SUM(Assumptions!I172:I174) -> 5000 | I22: =SUM(Assumptions!J172:J174) -> 5000 | J22: =SUM(Assumptions!K172:K174) -> 5000 | K22: =SUM(Assumptions!L172:L174) -> 5000 | L22: =SUM(Assumptions!M172:M174) -> 5000 | M22: =SUM(Assumptions!N172:N174) -> 5000 | ... BM22: =SUM(Assumptions!BN172:BN174) -> 5000
B23: =Assumptions!B177 -> Other | F23: =Assumptions!G178 -> 6026.85 | G23: =Assumptions!H178 -> 9232.8278 | H23: =Assumptions!I178 -> 10838.705 | I23: =Assumptions!J178 -> 11641.687 | J23: =Assumptions!K178 -> 12043.178 | K23: =Assumptions!L178 -> 12243.924 | L23: =Assumptions!M178 -> 12344.297 | M23: =Assumptions!N178 -> 12394.484 | ... BM23: =Assumptions!BN178 -> 12444.67
B24: Total Operating Expenses | F24: =SUM(F19:F23) -> 247848.33 | G24: =SUM(G19:G23) -> 253619.09 | H24: =SUM(H19:H23) -> 256509.67 | I24: =SUM(I19:I23) -> 257955.04 | J24: =SUM(J19:J23) -> 258677.72 | K24: =SUM(K19:K23) -> 259039.06 | L24: =SUM(L19:L23) -> 259219.73 | M24: =SUM(M19:M23) -> 259310.07 | ... BM24: =SUM(BM19:BM23) -> 259400.41
B26: EBITDA | F26: =F15-F24 -> -211687.23 | G26: =G15-G24 -> -198222.12 | H26: =H15-H24 -> -191477.44 | I26: =I15-I24 -> -188104.92 | J26: =J15-J24 -> -186418.65 | K26: =K15-K24 -> -185575.52 | L26: =L15-L24 -> -185153.95 | M26: =M15-M24 -> -184943.17 | ... BM26: =BM15-BM24 -> -184732.39
B27: Depreciation | F27: =SUM(Assumptions!G201:G204)-sum(Assumptions!E201:E204) -> 0 | G27: =SUM(Assumptions!H201:H204)-sum(Assumptions!G201:G204) -> 0 | H27: =SUM(Assumptions!I201:I204)-sum(Assumptions!H201:H204) -> 0 | I27: =SUM(Assumptions!J201:J204)-sum(Assumptions!I201:I204) -> 0 | J27: =SUM(Assumptions!K201:K204)-sum(Assumptions!J201:J204) -> 0 | K27: =SUM(Assumptions!L201:L204)-sum(Assumptions!K201:K204) -> 0 | L27: =SUM(Assumptions!M201:M204)-sum(Assumptions!L201:L204) -> 0 | M27: =SUM(Assumptions!N201:N204)-sum(Assumptions!M201:M204) -> 0 | N27: =SUM(Assumptions!O201:O204)-sum(Assumptions!N201:N204) -> 0 | ... BM27: =SUM(Assumptions!BN201:BN204)-sum(Assumptions!BM201:BM204) -> 0
B28: EBIT | F28: =F26-F27 -> -211687.23 | G28: =G26-G27 -> -198222.12 | H28: =H26-H27 -> -191477.44 | I28: =I26-I27 -> -188104.92 | J28: =J26-J27 -> -186418.65 | K28: =K26-K27 -> -185575.52 | L28: =L26-L27 -> -185153.95 | M28: =M26-M27 -> -184943.17 | ... BM28: =BM26-BM27 -> -184732.39
B29: Taxes | F29: =IF(F28>0,F28*Assumptions!$C$180,0) -> 0 | G29: =IF(G28>0,G28*Assumptions!$C$180,0) -> 0 | H29: =IF(H28>0,H28*Assumptions!$C$180,0) -> 0 | I29: =IF(I28>0,I28*Assumptions!$C$180,0) -> 0 | J29: =IF(J28>0,J28*Assumptions!$C$180,0) -> 0 | K29: =IF(K28>0,K28*Assumptions!$C$180,0) -> 0 | L29: =IF(L28>0,L28*Assumptions!$C$180,0) -> 0 | M29: =IF(M28>0,M28*Assumptions!$C$180,0) -> 0 | ... BM29: =IF(BM28>0,BM28*Assumptions!$C$180,0) -> 0
B30: Net Income | F30: =F28-F29 -> -211687.23 | G30: =G28-G29 -> -198222.12 | H30: =H28-H29 -> -191477.44 | I30: =I28-I29 -> -188104.92 | J30: =J28-J29 -> -186418.65 | K30: =K28-K29 -> -185575.52 | L30: =L28-L29 -> -185153.95 | M30: =M28-M29 -> -184943.17 | ... BM30: =BM28-BM29 -> -184732.39
B31: Net Margin | F31: =F30/F8 -> -3.5124025 | G31: =G30/G8 -> -2.1469276 | H31: =H30/H8 -> -1.7666081 | I31: =I30/I8 -> -1.6157875 | J31: =J30/J8 -> -1.547919 | K31: =K30/K8 -> -1.5156539 | L31: =L30/L8 -> -1.4999149 | M31: =M30/M8 -> -1.492141 | ... BM31: =BM30/BM8 -> -1.4844298
B33: Balance Sheet:
B35: Assets
B36: Current Assets
B37: Cash | F37: =F82 -> 269048.98 | G37: =G82 -> 51270.397 | H37: =H82 -> -150002.89 | I37: =I82 -> -343006 | J37: =J82 -> -531873.75 | K37: =K82 -> -718673.81 | L37: =L82 -> -904440.04 | M37: =M82 -> -1089689.3 | ... BM37: =BM82 -> -10696290
B38: Accounts Receivable | F38: =Assumptions!G190 -> 30134.25 | G38: =Assumptions!H190 -> 46164.139 | H38: =Assumptions!I190 -> 54193.525 | I38: =Assumptions!J190 -> 58208.434 | J38: =Assumptions!K190 -> 60215.892 | K38: =Assumptions!L190 -> 61219.621 | L38: =Assumptions!M190 -> 61721.486 | M38: =Assumptions!N190 -> 61972.418 | ... BM38: =Assumptions!BN190 -> 62223.35
B39: Inventory | F39: =Assumptions!G192 -> 24107.4 | G39: =Assumptions!H192 -> 36931.311 | H39: =Assumptions!I192 -> 43354.82 | I39: =Assumptions!J192 -> 46566.747 | J39: =Assumptions!K192 -> 48172.714 | K39: =Assumptions!L192 -> 48975.697 | L39: =Assumptions!M192 -> 49377.189 | M39: =Assumptions!N192 -> 49577.934 | ... BN39: =Assumptions!BO192
B40: Total Current Assets | F40: =SUM(F37:F39) -> 323290.64 | G40: =SUM(G37:G39) -> 134365.85 | H40: =SUM(H37:H39) -> -52454.549 | I40: =SUM(I37:I39) -> -238230.82 | J40: =SUM(J37:J39) -> -423485.14 | K40: =SUM(K37:K39) -> -608478.5 | L40: =SUM(L37:L39) -> -793341.37 | M40: =SUM(M37:M39) -> -978139 | ... BM40: =SUM(BM37:BM39) -> -10584288
B42: Fixed Assets | F42: =SUM(Assumptions!G194:G198) -> 0 | G42: =SUM(Assumptions!H194:H198) -> 0 | H42: =SUM(Assumptions!I194:I198) -> 0 | I42: =SUM(Assumptions!J194:J198) -> 0 | J42: =SUM(Assumptions!K194:K198) -> 0 | K42: =SUM(Assumptions!L194:L198) -> 0 | L42: =SUM(Assumptions!M194:M198) -> 0 | M42: =SUM(Assumptions!N194:N198) -> 0 | ... BM42: =SUM(Assumptions!BN194:BN198) -> 0
B43: Accumulated Depreciation | F43: =-SUM(Assumptions!G201:G204) -> 0 | G43: =-SUM(Assumptions!H201:H204) -> 0 | H43: =-SUM(Assumptions!I201:I204) -> 0 | I43: =-SUM(Assumptions!J201:J204) -> 0 | J43: =-SUM(Assumptions!K201:K204) -> 0 | K43: =-SUM(Assumptions!L201:L204) -> 0 | L43: =-SUM(Assumptions!M201:M204) -> 0 | M43: =-SUM(Assumptions!N201:N204) -> 0 | ... BM43: =-SUM(Assumptions!BN201:BN204) -> 0
B44: Total Assets | F44: =SUM(F40:F43) -> 323290.64 | G44: =SUM(G40:G43) -> 134365.85 | H44: =SUM(H40:H43) -> -52454.549 | I44: =SUM(I40:I43) -> -238230.82 | J44: =SUM(J40:J43) -> -423485.14 | K44: =SUM(K40:K43) -> -608478.5 | L44: =SUM(L40:L43) -> -793341.37 | M44: =SUM(M40:M43) -> -978139 | ... BM44: =SUM(BM40:BM43) -> -10584288
B46: Liabilities & Owner's Equity
B47: Liabilities
B48: Accounts payable | F48: =Assumptions!G208 -> 34977.865 | G48: =Assumptions!H208 -> 44275.2 | H48: =Assumptions!I208 -> 48932.244 | I48: =Assumptions!J208 -> 51260.892 | J48: =Assumptions!K208 -> 52425.217 | K48: =Assumptions!L208 -> 53007.38 | L48: =Assumptions!M208 -> 53298.462 | M48: =Assumptions!N208 -> 53444.002 | ... BM48: =Assumptions!BN208 -> 53589.543
B49: Total Liabilities | F49: =F48 -> 34977.865 | G49: =G48 -> 44275.2 | H49: =H48 -> 48932.244 | I49: =I48 -> 51260.892 | J49: =J48 -> 52425.217 | K49: =K48 -> 53007.38 | L49: =L48 -> 53298.462 | M49: =M48 -> 53444.002 | ... BM49: =BM48 -> 53589.543
B51: Equity | E51: Prev Cash
B52: Paid In Capital | E52: =Assumptions!C188 -> 500000 | F52: =E52 -> 500000 | G52: =Assumptions!H222+$E52 -> 500000 | H52: =Assumptions!I222+$E52 -> 500000 | I52: =Assumptions!J222+$E52 -> 500000 | J52: =Assumptions!K222+$E52 -> 500000 | K52: =Assumptions!L222+$E52 -> 500000 | L52: =Assumptions!M222+$E52 -> 500000 | M52: =Assumptions!N222+$E52 -> 500000 | N52: =Assumptions!O222+$E52 -> 500000 | ... BM52: =Assumptions!BN222+$E52 -> 500000
B53: Accumulated Retained Earnings | F53: =E53+F30 -> -211687.23 | G53: =F53+G30 -> -409909.35 | H53: =G53+H30 -> -601386.79 | I53: =H53+I30 -> -789491.71 | J53: =I53+J30 -> -975910.36 | K53: =J53+K30 -> -1161485.9 | L53: =K53+L30 -> -1346639.8 | M53: =L53+M30 -> -1531583 | ... BM53: =BL53+BM30 -> -11137878
B54: Total Equity | F54: =SUM(F52:F53) -> 288312.77 | G54: =SUM(G52:G53) -> 90090.647 | H54: =SUM(H52:H53) -> -101386.79 | I54: =SUM(I52:I53) -> -289491.71 | J54: =SUM(J52:J53) -> -475910.36 | K54: =SUM(K52:K53) -> -661485.88 | L54: =SUM(L52:L53) -> -846639.83 | M54: =SUM(M52:M53) -> -1031583 | ... BM54: =SUM(BM52:BM53) -> -10637878
B56: Total Liabilities & Owner's Equity | F56: =F54+F49 -> 323290.64 | G56: =G54+G49 -> 134365.85 | H56: =H54+H49 -> -52454.549 | I56: =I54+I49 -> -238230.82 | J56: =J54+J49 -> -423485.14 | K56: =K54+K49 -> -608478.5 | L56: =L54+L49 -> -793341.37 | M56: =M54+M49 -> -978139 | ... BM56: =BM54+BM49 -> -10584288
B58: Balance Check | F58: =IF(ABS(F56-F44)>0.001,"ERROR","OK") -> OK | G58: =IF(ABS(G56-G44)>0.001,"ERROR","OK") -> OK | H58: =IF(ABS(H56-H44)>0.001,"ERROR","OK") -> OK | I58: =IF(ABS(I56-I44)>0.001,"ERROR","OK") -> OK | J58: =IF(ABS(J56-J44)>0.001,"ERROR","OK") -> OK | K58: =IF(ABS(K56-K44)>0.001,"ERROR","OK") -> OK | L58: =IF(ABS(L56-L44)>0.001,"ERROR","OK") -> OK | M58: =IF(ABS(M56-M44)>0.001,"ERROR","OK") -> OK | ... BM58: =IF(ABS(BM56-BM44)>0.001,"ERROR","OK") -> OK
B60: Statement of Cash Flows:
B62: Operating Cash Flows
B63: Net Income | F63: =F53-E53 -> -211687.23 | G63: =G53-F53 -> -198222.12 | H63: =H53-G53 -> -191477.44 | I63: =I53-H53 -> -188104.92 | J63: =J53-I53 -> -186418.65 | K63: =K53-J53 -> -185575.52 | L63: =L53-K53 -> -185153.95 | M63: =M53-L53 -> -184943.17 | ... BM63: =BM53-BL53 -> -184732.39
B64: Depreciation | F64: =E43-F43 -> 0 | G64: =F43-G43 -> 0 | H64: =G43-H43 -> 0 | I64: =H43-I43 -> 0 | J64: =I43-J43 -> 0 | K64: =J43-K43 -> 0 | L64: =K43-L43 -> 0 | M64: =L43-M43 -> 0 | ... BM64: =BL43-BM43 -> 0
B65: Change in Accounts Receivable | F65: =E38-F38 -> -30134.25 | G65: =F38-G38 -> -16029.889 | H65: =G38-H38 -> -8029.3858 | I65: =H38-I38 -> -4014.9095 | J65: =I38-J38 -> -2007.458 | K65: =J38-K38 -> -1003.7291 | L65: =K38-L38 -> -501.86453 | M65: =L38-M38 -> -250.93226 | ... BM65: =BL38-BM38 -> 0
B66: Change in Inventory | F66: =E39-F39 -> -24107.4 | G66: =F39-G39 -> -12823.911 | H66: =G39-H39 -> -6423.5087 | I66: =H39-I39 -> -3211.9276 | J66: =I39-J39 -> -1605.9664 | K66: =J39-K39 -> -802.98325 | L66: =K39-L39 -> -401.49162 | M66: =L39-M39 -> -200.74581 | ... BM66: =BL39-BM39 -> 0
B67: Change in Accounts Payable | F67: =F48-E48 -> 34977.865 | G67: =G48-F48 -> 9297.3355 | H67: =H48-G48 -> 4657.0438 | I67: =I48-H48 -> 2328.6475 | J67: =J48-I48 -> 1164.3256 | K67: =K48-J48 -> 582.16285 | L67: =L48-K48 -> 291.08143 | M67: =M48-L48 -> 145.54071 | ... BM67: =BM48-BL48 -> 0
B68: Total Operating Cash Flows | F68: =SUM(F63:F67) -> -230951.02 | G68: =SUM(G63:G67) -> -217778.59 | H68: =SUM(H63:H67) -> -201273.29 | I68: =SUM(I63:I67) -> -193003.11 | J68: =SUM(J63:J67) -> -188867.75 | K68: =SUM(K63:K67) -> -186800.07 | L68: =SUM(L63:L67) -> -185766.23 | M68: =SUM(M63:M67) -> -185249.31 | ... BM68: =SUM(BM63:BM67) -> -184732.39
B70: Investing Cash Flows
B71: Changes in Fixed Assets | F71: =E42-F42 -> 0 | G71: =F42-G42 -> 0 | H71: =G42-H42 -> 0 | I71: =H42-I42 -> 0 | J71: =I42-J42 -> 0 | K71: =J42-K42 -> 0 | L71: =K42-L42 -> 0 | M71: =L42-M42 -> 0 | ... BM71: =BL42-BM42 -> 0
B72: Total Investing Cash Flows | F72: =F71 -> 0 | G72: =G71 -> 0 | H72: =H71 -> 0 | I72: =I71 -> 0 | J72: =J71 -> 0 | K72: =K71 -> 0 | L72: =L71 -> 0 | M72: =M71 -> 0 | ... BM72: =BM71 -> 0
B74: Financing Cash Flows
B75: Changes in Paid in Capital | F75: =F52-E52 -> 0 | G75: =G52-F52 -> 0 | H75: =H52-G52 -> 0 | I75: =I52-H52 -> 0 | J75: =J52-I52 -> 0 | K75: =K52-J52 -> 0 | L75: =L52-K52 -> 0 | M75: =M52-L52 -> 0 | ... BM75: =BM52-BL52 -> 0
B76: Total Financing Cash Flows | F76: =F75 -> 0 | G76: =G75 -> 0 | H76: =H75 -> 0 | I76: =I75 -> 0 | J76: =J75 -> 0 | K76: =K75 -> 0 | L76: =L75 -> 0 | M76: =M75 -> 0 | ... BM76: =BM75 -> 0
B78: Beginning Cash | F78: =Assumptions!C188 -> 500000 | G78: =F82 -> 269048.98 | H78: =G82 -> 51270.397 | I78: =H82 -> -150002.89 | J78: =I82 -> -343006 | K78: =J82 -> -531873.75 | L78: =K82 -> -718673.81 | M78: =L82 -> -904440.04 | N78: =M82 -> -1089689.3 | ... BM78: =BL82 -> -10511558
B80: Change in Cash | F80: =F76+F72+F68 -> -230951.02 | G80: =G76+G72+G68 -> -217778.59 | H80: =H76+H72+H68 -> -201273.29 | I80: =I76+I72+I68 -> -193003.11 | J80: =J76+J72+J68 -> -188867.75 | K80: =K76+K72+K68 -> -186800.07 | L80: =L76+L72+L68 -> -185766.23 | M80: =M76+M72+M68 -> -185249.31 | ... BM80: =BM76+BM72+BM68 -> -184732.39
B82: Ending Cash | F82: =F78+F80 -> 269048.98 | G82: =G78+G80 -> 51270.397 | H82: =H78+H80 -> -150002.89 | I82: =I78+I80 -> -343006 | J82: =J78+J80 -> -531873.75 | K82: =K78+K80 -> -718673.81 | L82: =L78+L80 -> -904440.04 | M82: =M78+M80 -> -1089689.3 | ... BM82: =BM78+BM80 -> -10696290
