Workbook

Sheet Overview
C2: YOUR LOGO HERE
C4: Financial Model
G5: Welcome! This template was created by Forecastr's team of Financial Analysts and Fractional CFOs to help our fellow founders create better financial models for their startups and small businesses. Forecastr is an out-of-the-box finance function for your business. We provide the tools and support you need to create an investor-grade financial model. Our analysts work with you every step of the way to build a model that's customized to fit your business, keep it up to date, and generate insightful reports to share with your investors and other stakeholders. ✔ Impress your investors ✔ Hit your growth targets ✔ Never run out of cash
C7: Your Website Link Here
C10: Table of Contents
C12: Assumptions
C14: Financials
I18: SCHEDULE A MODELING SESSION WITH A MEMBER OF OUR TEAM

Sheet Assumptions
B1: Year Counter | R1: 1 | S1: 1 | T1: 1 | U1: 1 | V1: 1 | W1: 1 | X1: 1 | Y1: 1 | Z1: 1 | AA1: 1 | AB1: 1 | AC1: 1 | AD1: =R1+1 -> 2 | AE1: =S1+1 -> 2 | AF1: =T1+1 -> 2 | AG1: =U1+1 -> 2 | AH1: =V1+1 -> 2 | AI1: =W1+1 -> 2 | AJ1: =X1+1 -> 2 | AK1: =Y1+1 -> 2 | ... BY1: =BM1+1 -> 5
B2: Year | R2: =YEAR(R4) -> 2023 | S2: =YEAR(S4) -> 2023 | T2: =YEAR(T4) -> 2023 | U2: =YEAR(U4) -> 2023 | V2: =YEAR(V4) -> 2023 | W2: =YEAR(W4) -> 2023 | X2: =YEAR(X4) -> 2023 | Y2: =YEAR(Y4) -> 2023 | ... BY2: =YEAR(BY4) -> 2027
B3: Month Counter | R3: 1 | S3: =R3+1 -> 2 | T3: =S3+1 -> 3 | U3: =T3+1 -> 4 | V3: =U3+1 -> 5 | W3: =V3+1 -> 6 | X3: =W3+1 -> 7 | Y3: =X3+1 -> 8 | Z3: =Y3+1 -> 9 | ... BY3: =BX3+1 -> 60
B4: Date | R4: 44957 | S4: =EOMONTH(R4,1) -> 44985 | T4: =EOMONTH(S4,1) -> 45016 | U4: =EOMONTH(T4,1) -> 45046 | V4: =EOMONTH(U4,1) -> 45077 | W4: =EOMONTH(V4,1) -> 45107 | X4: =EOMONTH(W4,1) -> 45138 | Y4: =EOMONTH(X4,1) -> 45169 | Z4: =EOMONTH(Y4,1) -> 45199 | ... BY4: =EOMONTH(BX4,1) -> 46752
B6: Customer Acquisition:
B8: Build Customer Acquisition Channels
B10: Organic / Word of Mouth
B11: Web Traffic | D11: 5000 | R11: =D11 -> 5000 | S11: =R11 -> 5000 | T11: =S11 -> 5000 | U11: =T11 -> 5000 | V11: =U11 -> 5000 | W11: =V11 -> 5000 | X11: =W11 -> 5000 | Y11: =X11 -> 5000 | Z11: =Y11 -> 5000 | ... BY11: =BX11 -> 5000
B12: Conversion Rate | D12: 0.02 | R12: =D12 -> 0.02 | S12: =R12 -> 0.02 | T12: =S12 -> 0.02 | U12: =T12 -> 0.02 | V12: =U12 -> 0.02 | W12: =V12 -> 0.02 | X12: =W12 -> 0.02 | Y12: =X12 -> 0.02 | Z12: =Y12 -> 0.02 | ... BY12: =BX12 -> 0.02
B13: New Customers | R13: =R11*R12 -> 100 | S13: =S11*S12 -> 100 | T13: =T11*T12 -> 100 | U13: =U11*U12 -> 100 | V13: =V11*V12 -> 100 | W13: =W11*W12 -> 100 | X13: =X11*X12 -> 100 | Y13: =Y11*Y12 -> 100 | ... BY13: =BY11*BY12 -> 100
B15: Paid Advertising
B16: Budget per Month | D16: 5000 | R16: =D16 -> 5000 | S16: =R16 -> 5000 | T16: =S16 -> 5000 | U16: =T16 -> 5000 | V16: =U16 -> 5000 | W16: =V16 -> 5000 | X16: =W16 -> 5000 | Y16: =X16 -> 5000 | Z16: =Y16 -> 5000 | ... BY16: =BX16 -> 5000
B17: Average CPC | D17: 2 | R17: =D17 -> 2 | S17: =R17 -> 2 | T17: =S17 -> 2 | U17: =T17 -> 2 | V17: =U17 -> 2 | W17: =V17 -> 2 | X17: =W17 -> 2 | Y17: =X17 -> 2 | Z17: =Y17 -> 2 | ... BY17: =BX17 -> 2
B18: Conversion Rate | D18: 0.05 | R18: =D18 -> 0.05 | S18: =R18 -> 0.05 | T18: =S18 -> 0.05 | U18: =T18 -> 0.05 | V18: =U18 -> 0.05 | W18: =V18 -> 0.05 | X18: =W18 -> 0.05 | Y18: =X18 -> 0.05 | Z18: =Y18 -> 0.05 | ... BY18: =BX18 -> 0.05
B19: New Customers | R19: =(D16/D17)*D18 -> 125 | S19: =(S16/S17)*S18 -> 125 | T19: =(T16/T17)*T18 -> 125 | U19: =(U16/U17)*U18 -> 125 | V19: =(V16/V17)*V18 -> 125 | W19: =(W16/W17)*W18 -> 125 | X19: =(X16/X17)*X18 -> 125 | Y19: =(Y16/Y17)*Y18 -> 125 | Z19: =(Z16/Z17)*Z18 -> 125 | ... BY19: =(BY16/BY17)*BY18 -> 125
B21: Affiliates
B22: Number of Affiliates | D22: 5 | R22: =D22 -> 5 | S22: =R22 -> 5 | T22: =S22 -> 5 | U22: =T22 -> 5 | V22: =U22 -> 5 | W22: =V22 -> 5 | X22: =W22 -> 5 | Y22: =X22 -> 5 | Z22: =Y22 -> 5 | ... BY22: =BX22 -> 5
B23: New Monthly Leads per Affiliate | D23: 50 | R23: =D23 -> 50 | S23: =R23 -> 50 | T23: =S23 -> 50 | U23: =T23 -> 50 | V23: =U23 -> 50 | W23: =V23 -> 50 | X23: =W23 -> 50 | Y23: =X23 -> 50 | Z23: =Y23 -> 50 | ... BY23: =BX23 -> 50
B24: Conversion Rate | D24: 0.05 | R24: =D24 -> 0.05 | S24: =R24 -> 0.05 | T24: =S24 -> 0.05 | U24: =T24 -> 0.05 | V24: =U24 -> 0.05 | W24: =V24 -> 0.05 | X24: =W24 -> 0.05 | Y24: =X24 -> 0.05 | Z24: =Y24 -> 0.05 | ... BY24: =BX24 -> 0.05
B25: New Customers | R25: =R22*R23*R24 -> 12.5 | S25: =S22*S23*S24 -> 12.5 | T25: =T22*T23*T24 -> 12.5 | U25: =U22*U23*U24 -> 12.5 | V25: =V22*V23*V24 -> 12.5 | W25: =W22*W23*W24 -> 12.5 | X25: =X22*X23*X24 -> 12.5 | Y25: =Y22*Y23*Y24 -> 12.5 | ... BY25: =BY22*BY23*BY24 -> 12.5
B27: Conferences
B28: Conferences Atteneded | R28: 1 | S28: 0 | T28: 0 | U28: 0 | V28: 0 | W28: 0 | X28: 0 | Y28: 0 | Z28: 0 | AA28: 0 | AB28: 0 | AC28: 0 | AD28: 0 | AE28: 0 | AF28: 0 | AG28: 0 | AH28: 0 | AI28: 0 | AJ28: 0 | AK28: 0 | AL28: 0 | AM28: 0 | AN28: 0 | AO28: 0 | AP28: 0 | AQ28: 0 | AR28: 0 | AS28: 0 | AT28: 0 | AU28: 0 | AV28: 0 | AW28: 0 | AX28: 0 | AY28: 0 | AZ28: 0 | BA28: 0 | BB28: 0 | BC28: 0 | BD28: 0 | BE28: 0 | BF28: 0 | BG28: 0 | BH28: 0 | BI28: 0 | BJ28: 0 | BK28: 0 | BL28: 0 | BM28: 0 | BN28: 0 | BO28: 0 | BP28: 0 | BQ28: 0 | BR28: 0 | BS28: 0 | BT28: 0 | BU28: 0 | BV28: 0 | BW28: 0 | BX28: 0 | BY28: 0
B29: New Leads per Conference | D29: 50 | R29: =D29 -> 50 | S29: =R29 -> 50 | T29: =S29 -> 50 | U29: =T29 -> 50 | V29: =U29 -> 50 | W29: =V29 -> 50 | X29: =W29 -> 50 | Y29: =X29 -> 50 | Z29: =Y29 -> 50 | ... BY29: =BX29 -> 50
B30: Conversion Rate | D30: 0.05 | R30: =D30 -> 0.05 | S30: =R30 -> 0.05 | T30: =S30 -> 0.05 | U30: =T30 -> 0.05 | V30: =U30 -> 0.05 | W30: =V30 -> 0.05 | X30: =W30 -> 0.05 | Y30: =X30 -> 0.05 | Z30: =Y30 -> 0.05 | ... BY30: =BX30 -> 0.05
B31: New Customers | R31: =R28*R29*R30 -> 2.5 | S31: =S28*S29*S30 -> 0 | T31: =T28*T29*T30 -> 0 | U31: =U28*U29*U30 -> 0 | V31: =V28*V29*V30 -> 0 | W31: =W28*W29*W30 -> 0 | X31: =X28*X29*X30 -> 0 | Y31: =Y28*Y29*Y30 -> 0 | ... BY31: =BY28*BY29*BY30 -> 0
B33: Influencers
B34: Number of Influencers | D34: 2 | R34: =D34 -> 2 | S34: =R34 -> 2 | T34: =S34 -> 2 | U34: =T34 -> 2 | V34: =U34 -> 2 | W34: =V34 -> 2 | X34: =W34 -> 2 | Y34: =X34 -> 2 | Z34: =Y34 -> 2 | ... BY34: =BX34 -> 2
B35: New Monthly Posts per Influencer | D35: 100 | R35: =D35 -> 100 | S35: =R35 -> 100 | T35: =S35 -> 100 | U35: =T35 -> 100 | V35: =U35 -> 100 | W35: =V35 -> 100 | X35: =W35 -> 100 | Y35: =X35 -> 100 | Z35: =Y35 -> 100 | ... BY35: =BX35 -> 100
B36: New Monthly Leads per Post | D36: 5 | R36: =D36 -> 5 | S36: =R36 -> 5 | T36: =S36 -> 5 | U36: =T36 -> 5 | V36: =U36 -> 5 | W36: =V36 -> 5 | X36: =W36 -> 5 | Y36: =X36 -> 5 | Z36: =Y36 -> 5 | ... BY36: =BX36 -> 5
B37: Conversion Rate | D37: 0.05 | R37: =D37 -> 0.05 | S37: =R37 -> 0.05 | T37: =S37 -> 0.05 | U37: =T37 -> 0.05 | V37: =U37 -> 0.05 | W37: =V37 -> 0.05 | X37: =W37 -> 0.05 | Y37: =X37 -> 0.05 | Z37: =Y37 -> 0.05 | ... BY37: =BX37 -> 0.05
B38: New Customers | R38: =R34*R35*R36*R37 -> 50 | S38: =S34*S35*S36*S37 -> 50 | T38: =T34*T35*T36*T37 -> 50 | U38: =U34*U35*U36*U37 -> 50 | V38: =V34*V35*V36*V37 -> 50 | W38: =W34*W35*W36*W37 -> 50 | X38: =X34*X35*X36*X37 -> 50 | Y38: =Y34*Y35*Y36*Y37 -> 50 | ... BY38: =BY34*BY35*BY36*BY37 -> 50
B40: Customer Referrals
B41: Previous Months New Customers | R41: =Q71 | S41: =R71 -> 317.5 | T41: =S71 -> 324.7625 | U41: =T71 -> 324.87144 | V41: =U71 -> 324.87307 | W41: =V71 -> 324.8731 | X41: =W71 -> 324.8731 | Y41: =X71 -> 324.8731 | ... BY41: =BX71 -> 324.8731
B42: Referral Percentage | D42: 0.3 | R42: =D42 -> 0.3 | S42: =R42 -> 0.3 | T42: =S42 -> 0.3 | U42: =T42 -> 0.3 | V42: =U42 -> 0.3 | W42: =V42 -> 0.3 | X42: =W42 -> 0.3 | Y42: =X42 -> 0.3 | Z42: =Y42 -> 0.3 | ... BY42: =BX42 -> 0.3
B43: Conversion Rate | D43: 0.05 | R43: =D43 -> 0.05 | S43: =R43 -> 0.05 | T43: =S43 -> 0.05 | U43: =T43 -> 0.05 | V43: =U43 -> 0.05 | W43: =V43 -> 0.05 | X43: =W43 -> 0.05 | Y43: =X43 -> 0.05 | Z43: =Y43 -> 0.05 | ... BY43: =BX43 -> 0.05
B44: New Customers | R44: =R41*R42*R43 -> 0 | S44: =S41*S42*S43 -> 4.7625 | T44: =T41*T42*T43 -> 4.8714375 | U44: =U41*U42*U43 -> 4.8730716 | V44: =V41*V42*V43 -> 4.8730961 | W44: =W41*W42*W43 -> 4.8730964 | X44: =X41*X42*X43 -> 4.8730964 | Y44: =Y41*Y42*Y43 -> 4.8730964 | ... BY44: =BY41*BY42*BY43 -> 4.8730964
B46: Partnerships
B47: Active Partnerships | D47: 2 | R47: =D47 -> 2 | S47: =R47 -> 2 | T47: =S47 -> 2 | U47: =T47 -> 2 | V47: =U47 -> 2 | W47: =V47 -> 2 | X47: =W47 -> 2 | Y47: =X47 -> 2 | Z47: =Y47 -> 2 | ... BY47: =BX47 -> 2
B48: New Monthly Leads per Partnership | D48: 100 | R48: =D48 -> 100 | S48: =R48 -> 100 | T48: =S48 -> 100 | U48: =T48 -> 100 | V48: =U48 -> 100 | W48: =V48 -> 100 | X48: =W48 -> 100 | Y48: =X48 -> 100 | Z48: =Y48 -> 100 | ... BY48: =BX48 -> 100
B49: Conversion Rate | D49: 0.05 | R49: =D49 -> 0.05 | S49: =R49 -> 0.05 | T49: =S49 -> 0.05 | U49: =T49 -> 0.05 | V49: =U49 -> 0.05 | W49: =V49 -> 0.05 | X49: =W49 -> 0.05 | Y49: =X49 -> 0.05 | Z49: =Y49 -> 0.05 | ... BY49: =BX49 -> 0.05
B50: New Customers | R50: =R47*R48*R49 -> 10 | S50: =S47*S48*S49 -> 10 | T50: =T47*T48*T49 -> 10 | U50: =U47*U48*U49 -> 10 | V50: =V47*V48*V49 -> 10 | W50: =W47*W48*W49 -> 10 | X50: =X47*X48*X49 -> 10 | Y50: =Y47*Y48*Y49 -> 10 | ... BY50: =BY47*BY48*BY49 -> 10
B52: Email Marketing
B53: Mailing List Size | D53: 2000 | R53: =D53 -> 2000 | S53: =R53 -> 2000 | T53: =S53 -> 2000 | U53: =T53 -> 2000 | V53: =U53 -> 2000 | W53: =V53 -> 2000 | X53: =W53 -> 2000 | Y53: =X53 -> 2000 | Z53: =Y53 -> 2000 | ... BY53: =BX53 -> 2000
B54: Average Number of Emails Sent a Month | D54: 2 | R54: =D54 -> 2 | S54: =R54 -> 2 | T54: =S54 -> 2 | U54: =T54 -> 2 | V54: =U54 -> 2 | W54: =V54 -> 2 | X54: =W54 -> 2 | Y54: =X54 -> 2 | Z54: =Y54 -> 2 | ... BY54: =BX54 -> 2
B55: Response Rate per Email | D55: 0.05 | R55: =D55 -> 0.05 | S55: =R55 -> 0.05 | T55: =S55 -> 0.05 | U55: =T55 -> 0.05 | V55: =U55 -> 0.05 | W55: =V55 -> 0.05 | X55: =W55 -> 0.05 | Y55: =X55 -> 0.05 | Z55: =Y55 -> 0.05 | ... BY55: =BX55 -> 0.05
B56: Conversion Rate | D56: 0.05 | R56: =D56 -> 0.05 | S56: =R56 -> 0.05 | T56: =S56 -> 0.05 | U56: =T56 -> 0.05 | V56: =U56 -> 0.05 | W56: =V56 -> 0.05 | X56: =W56 -> 0.05 | Y56: =X56 -> 0.05 | Z56: =Y56 -> 0.05 | ... BY56: =BX56 -> 0.05
B57: New Customers | R57: =R53*R54*R55*R56 -> 10 | S57: =S53*S54*S55*S56 -> 10 | T57: =T53*T54*T55*T56 -> 10 | U57: =U53*U54*U55*U56 -> 10 | V57: =V53*V54*V55*V56 -> 10 | W57: =W53*W54*W55*W56 -> 10 | X57: =X53*X54*X55*X56 -> 10 | Y57: =Y53*Y54*Y55*Y56 -> 10 | ... BY57: =BY53*BY54*BY55*BY56 -> 10
B59: Content Marketing
B60: New Pieces of Content | D60: 3 | R60: =D60 -> 3 | S60: =R60 -> 3 | T60: =S60 -> 3 | U60: =T60 -> 3 | V60: =U60 -> 3 | W60: =V60 -> 3 | X60: =W60 -> 3 | Y60: =X60 -> 3 | Z60: =Y60 -> 3 | ... BY60: =BX60 -> 3
B61: New Leads per Piece of Content | D61: 50 | R61: =D61 -> 50 | S61: =R61 -> 50 | T61: =S61 -> 50 | U61: =T61 -> 50 | V61: =U61 -> 50 | W61: =V61 -> 50 | X61: =W61 -> 50 | Y61: =X61 -> 50 | Z61: =Y61 -> 50 | ... BY61: =BX61 -> 50
B62: Conversion Rate | D62: 0.05 | R62: =D62 -> 0.05 | S62: =R62 -> 0.05 | T62: =S62 -> 0.05 | U62: =T62 -> 0.05 | V62: =U62 -> 0.05 | W62: =V62 -> 0.05 | X62: =W62 -> 0.05 | Y62: =X62 -> 0.05 | Z62: =Y62 -> 0.05 | ... BY62: =BX62 -> 0.05
B63: New Customers | R63: =R60*R61*R62 -> 7.5 | S63: =S60*S61*S62 -> 7.5 | T63: =T60*T61*T62 -> 7.5 | U63: =U60*U61*U62 -> 7.5 | V63: =V60*V61*V62 -> 7.5 | W63: =W60*W61*W62 -> 7.5 | X63: =X60*X61*X62 -> 7.5 | Y63: =Y60*Y61*Y62 -> 7.5 | ... BY63: =BY60*BY61*BY62 -> 7.5
B65: Direct Sales Team
B66: Leads | D66: 25 | R66: =D66 -> 25 | S66: =R66 -> 25 | T66: =S66 -> 25 | U66: =T66 -> 25 | V66: =U66 -> 25 | W66: =V66 -> 25 | X66: =W66 -> 25 | Y66: =X66 -> 25 | Z66: =Y66 -> 25 | ... BY66: =BX66 -> 25
B67: Sales Cycle | D67: 2 | R67: =D67 -> 2 | S67: =R67 -> 2 | T67: =S67 -> 2 | U67: =T67 -> 2 | V67: =U67 -> 2 | W67: =V67 -> 2 | X67: =W67 -> 2 | Y67: =X67 -> 2 | Z67: =Y67 -> 2 | ... BY67: =BX67 -> 2
B68: Conversion Rate | D68: 0.2 | R68: =D68 -> 0.2 | S68: =R68 -> 0.2 | T68: =S68 -> 0.2 | U68: =T68 -> 0.2 | V68: =U68 -> 0.2 | W68: =V68 -> 0.2 | X68: =W68 -> 0.2 | Y68: =X68 -> 0.2 | Z68: =Y68 -> 0.2 | ... BY68: =BX68 -> 0.2
B69: New Customers | R69: =IFERROR(offset(R66,,-R67+1)*R68,0) -> 0 | S69: =IFERROR(offset(S66,,-S67+1)*S68,0) -> 5 | T69: =IFERROR(offset(T66,,-T67+1)*T68,0) -> 5 | U69: =IFERROR(offset(U66,,-U67+1)*U68,0) -> 5 | V69: =IFERROR(offset(V66,,-V67+1)*V68,0) -> 5 | W69: =IFERROR(offset(W66,,-W67+1)*W68,0) -> 5 | X69: =IFERROR(offset(X66,,-X67+1)*X68,0) -> 5 | Y69: =IFERROR(offset(Y66,,-Y67+1)*Y68,0) -> 5 | ... BY69: =IFERROR(offset(BY66,,-BY67+1)*BY68,0) -> 5
B71: Total New Customers | R71: =R13+R19+R25+R31+R38+R44+R50+R57+R63+R69 -> 317.5 | S71: =S13+S19+S25+S31+S38+S44+S50+S57+S63+S69 -> 324.7625 | T71: =T13+T19+T25+T31+T38+T44+T50+T57+T63+T69 -> 324.87144 | U71: =U13+U19+U25+U31+U38+U44+U50+U57+U63+U69 -> 324.87307 | V71: =V13+V19+V25+V31+V38+V44+V50+V57+V63+V69 -> 324.8731 | W71: =W13+W19+W25+W31+W38+W44+W50+W57+W63+W69 -> 324.8731 | X71: =X13+X19+X25+X31+X38+X44+X50+X57+X63+X69 -> 324.8731 | Y71: =Y13+Y19+Y25+Y31+Y38+Y44+Y50+Y57+Y63+Y69 -> 324.8731 | ... BY71: =BY13+BY19+BY25+BY31+BY38+BY44+BY50+BY57+BY63+BY69 -> 324.8731
B73: Revenue - Annual SaaS:
B75: Annual SaaS Tier 1
B76: % of Total New Customers | D76: 0.5 | R76: =D76 -> 0.5 | S76: =R76 -> 0.5 | T76: =S76 -> 0.5 | U76: =T76 -> 0.5 | V76: =U76 -> 0.5 | W76: =V76 -> 0.5 | X76: =W76 -> 0.5 | Y76: =X76 -> 0.5 | Z76: =Y76 -> 0.5 | ... BY76: =BX76 -> 0.5
B77: New Customers | R77: =R76*R$71 -> 158.75 | S77: =S76*S$71 -> 162.38125 | T77: =T76*T$71 -> 162.43572 | U77: =U76*U$71 -> 162.43654 | V77: =V76*V$71 -> 162.43655 | W77: =W76*W$71 -> 162.43655 | X77: =X76*X$71 -> 162.43655 | Y77: =Y76*Y$71 -> 162.43655 | ... BY77: =BY76*BY$71 -> 162.43655
B78: Billed Subscriptions | F78: 0 | G78: 0 | H78: 0 | I78: 0 | J78: 0 | K78: 0 | L78: 0 | M78: 0 | N78: 0 | O78: 0 | P78: 0 | Q78: 0 | R78: =R77+R83 -> 158.75 | S78: =S77+S83 -> 162.38125 | T78: =T77+T83 -> 162.43572 | U78: =U77+U83 -> 162.43654 | V78: =V77+V83 -> 162.43655 | W78: =W77+W83 -> 162.43655 | X78: =X77+X83 -> 162.43655 | Y78: =Y77+Y83 -> 162.43655 | ... BY78: =BY77+BY83 -> 546.0467
B79: Subscriptions Available for Renewal | R79: =F78 -> 0 | S79: =G78 -> 0 | T79: =H78 -> 0 | U79: =I78 -> 0 | V79: =J78 -> 0 | W79: =K78 -> 0 | X79: =L78 -> 0 | Y79: =M78 -> 0 | ... BY79: =BM78 -> 479.51269
B80: Subscriptions In-between Billing Cycles | R80: =R85-R79 -> 0 | S80: =S85-S79 -> 158.75 | T80: =T85-T79 -> 321.13125 | U80: =U85-U79 -> 483.56697 | V80: =V85-V79 -> 646.0035 | W80: =W85-W79 -> 808.44005 | X80: =X85-X79 -> 970.8766 | Y80: =Y85-Y79 -> 1133.3131 | ... BY80: =BY85-BY79 -> 6004.9807
B81: Annual Churn Rate | D81: 0.2 | R81: =D81 -> 0.2 | S81: =R81 -> 0.2 | T81: =S81 -> 0.2 | U81: =T81 -> 0.2 | V81: =U81 -> 0.2 | W81: =V81 -> 0.2 | X81: =W81 -> 0.2 | Y81: =X81 -> 0.2 | Z81: =Y81 -> 0.2 | ... BY81: =BX81 -> 0.2
B82: Churned Subscriptions | R82: =R79*R81 -> 0 | S82: =S79*S81 -> 0 | T82: =T79*T81 -> 0 | U82: =U79*U81 -> 0 | V82: =V79*V81 -> 0 | W82: =W79*W81 -> 0 | X82: =X79*X81 -> 0 | Y82: =Y79*Y81 -> 0 | ... BY82: =BY79*BY81 -> 95.902538
B83: Renewed Susbcriptions | R83: =R79-R82 -> 0 | S83: =S79-S82 -> 0 | T83: =T79-T82 -> 0 | U83: =U79-U82 -> 0 | V83: =V79-V82 -> 0 | W83: =W79-W82 -> 0 | X83: =X79-X82 -> 0 | Y83: =Y79-Y82 -> 0 | ... BY83: =BY79-BY82 -> 383.61015
B84: Active Subscriptions | R84: =R78+R80 -> 158.75 | S84: =S78+S80 -> 321.13125 | T84: =T78+T80 -> 483.56697 | U84: =U78+U80 -> 646.0035 | V84: =V78+V80 -> 808.44005 | W84: =W78+W80 -> 970.8766 | X84: =X78+X80 -> 1133.3131 | Y84: =Y78+Y80 -> 1295.7497 | ... BY84: =BY78+BY80 -> 6551.0274
B85: Previous Months Active Subsciptions | R85: =E84 | S85: =R84 -> 158.75 | T85: =S84 -> 321.13125 | U85: =T84 -> 483.56697 | V85: =U84 -> 646.0035 | W85: =V84 -> 808.44005 | X85: =W84 -> 970.8766 | Y85: =X84 -> 1133.3131 | Z85: =Y84 -> 1295.7497 | ... BY85: =BX84 -> 6484.4934
B86: Annual Price | D86: 100 | R86: =D86 -> 100 | S86: =R86 -> 100 | T86: =S86 -> 100 | U86: =T86 -> 100 | V86: =U86 -> 100 | W86: =V86 -> 100 | X86: =W86 -> 100 | Y86: =X86 -> 100 | Z86: =Y86 -> 100 | ... BY86: =BX86 -> 100
B87: Bookings | R87: =R78*R86 -> 15875 | S87: =S78*S86 -> 16238.125 | T87: =T78*T86 -> 16243.572 | U87: =U78*U86 -> 16243.654 | V87: =V78*V86 -> 16243.655 | W87: =W78*W86 -> 16243.655 | X87: =X78*X86 -> 16243.655 | Y87: =Y78*Y86 -> 16243.655 | ... BY87: =BY78*BY86 -> 54604.67
B88: Revenue | R88: =(R86/12)*R84 -> 1322.9167 | S88: =(S86/12)*S84 -> 2676.0938 | T88: =(T86/12)*T84 -> 4029.7247 | U88: =(U86/12)*U84 -> 5383.3625 | V88: =(V86/12)*V84 -> 6737.0004 | W88: =(W86/12)*W84 -> 8090.6383 | X88: =(X86/12)*X84 -> 9444.2762 | Y88: =(Y86/12)*Y84 -> 10797.914 | ... BY88: =(BY86/12)*BY84 -> 54591.895
B90: Annual SaaS Tier 2
B91: % of Total New Customers | D91: 0.3 | R91: =D91 -> 0.3 | S91: =R91 -> 0.3 | T91: =S91 -> 0.3 | U91: =T91 -> 0.3 | V91: =U91 -> 0.3 | W91: =V91 -> 0.3 | X91: =W91 -> 0.3 | Y91: =X91 -> 0.3 | Z91: =Y91 -> 0.3 | ... BY91: =BX91 -> 0.3
B92: New Customers | R92: =R91*R$71 -> 95.25 | S92: =S91*S$71 -> 97.42875 | T92: =T91*T$71 -> 97.461431 | U92: =U91*U$71 -> 97.461921 | V92: =V91*V$71 -> 97.461929 | W92: =W91*W$71 -> 97.461929 | X92: =X91*X$71 -> 97.461929 | Y92: =Y91*Y$71 -> 97.461929 | ... BY92: =BY91*BY$71 -> 97.461929
B93: Billed Subscriptions | F93: 0 | G93: 0 | H93: 0 | I93: 0 | J93: 0 | K93: 0 | L93: 0 | M93: 0 | N93: 0 | O93: 0 | P93: 0 | Q93: 0 | R93: =R92+R98 -> 95.25 | S93: =S92+S98 -> 97.42875 | T93: =T92+T98 -> 97.461431 | U93: =U92+U98 -> 97.461921 | V93: =V92+V98 -> 97.461929 | W93: =W92+W98 -> 97.461929 | X93: =X92+X98 -> 97.461929 | Y93: =Y92+Y98 -> 97.461929 | ... BY93: =BY92+BY98 -> 327.62802
B94: Subscriptions Available for Renewal | R94: =F93 -> 0 | S94: =G93 -> 0 | T94: =H93 -> 0 | U94: =I93 -> 0 | V94: =J93 -> 0 | W94: =K93 -> 0 | X94: =L93 -> 0 | Y94: =M93 -> 0 | ... BY94: =BM93 -> 287.70761
B95: Subscriptions In-between Billing Cycles | R95: =R100-R94 -> 0 | S95: =S100-S94 -> 95.25 | T95: =T100-T94 -> 192.67875 | U95: =U100-U94 -> 290.14018 | V95: =V100-V94 -> 387.6021 | W95: =W100-W94 -> 485.06403 | X95: =X100-X94 -> 582.52596 | Y95: =Y100-Y94 -> 679.98789 | ... BY95: =BY100-BY94 -> 3602.9884
B96: Annual Churn Rate | D96: 0.2 | R96: =D96 -> 0.2 | S96: =R96 -> 0.2 | T96: =S96 -> 0.2 | U96: =T96 -> 0.2 | V96: =U96 -> 0.2 | W96: =V96 -> 0.2 | X96: =W96 -> 0.2 | Y96: =X96 -> 0.2 | Z96: =Y96 -> 0.2 | ... BY96: =BX96 -> 0.2
B97: Churned Subscriptions | R97: =R94*R96 -> 0 | S97: =S94*S96 -> 0 | T97: =T94*T96 -> 0 | U97: =U94*U96 -> 0 | V97: =V94*V96 -> 0 | W97: =W94*W96 -> 0 | X97: =X94*X96 -> 0 | Y97: =Y94*Y96 -> 0 | ... BY97: =BY94*BY96 -> 57.541523
B98: Renewed Susbcriptions | R98: =R94-R97 -> 0 | S98: =S94-S97 -> 0 | T98: =T94-T97 -> 0 | U98: =U94-U97 -> 0 | V98: =V94-V97 -> 0 | W98: =W94-W97 -> 0 | X98: =X94-X97 -> 0 | Y98: =Y94-Y97 -> 0 | ... BY98: =BY94-BY97 -> 230.16609
B99: Active Subscriptions | R99: =R93+R95 -> 95.25 | S99: =S93+S95 -> 192.67875 | T99: =T93+T95 -> 290.14018 | U99: =U93+U95 -> 387.6021 | V99: =V93+V95 -> 485.06403 | W99: =W93+W95 -> 582.52596 | X99: =X93+X95 -> 679.98789 | Y99: =Y93+Y95 -> 777.44982 | ... BY99: =BY93+BY95 -> 3930.6164
B100: Previous Months Active Subsciptions | R100: =E99 | S100: =R99 -> 95.25 | T100: =S99 -> 192.67875 | U100: =T99 -> 290.14018 | V100: =U99 -> 387.6021 | W100: =V99 -> 485.06403 | X100: =W99 -> 582.52596 | Y100: =X99 -> 679.98789 | Z100: =Y99 -> 777.44982 | ... BY100: =BX99 -> 3890.696
B101: Annual Price | D101: 200 | R101: =D101 -> 200 | S101: =R101 -> 200 | T101: =S101 -> 200 | U101: =T101 -> 200 | V101: =U101 -> 200 | W101: =V101 -> 200 | X101: =W101 -> 200 | Y101: =X101 -> 200 | Z101: =Y101 -> 200 | ... BY101: =BX101 -> 200
B102: Bookings | R102: =R93*R101 -> 19050 | S102: =S93*S101 -> 19485.75 | T102: =T93*T101 -> 19492.286 | U102: =U93*U101 -> 19492.384 | V102: =V93*V101 -> 19492.386 | W102: =W93*W101 -> 19492.386 | X102: =X93*X101 -> 19492.386 | Y102: =Y93*Y101 -> 19492.386 | ... BY102: =BY93*BY101 -> 65525.604
B103: Revenue | R103: =(R101/12)*R99 -> 1587.5 | S103: =(S101/12)*S99 -> 3211.3125 | T103: =(T101/12)*T99 -> 4835.6697 | U103: =(U101/12)*U99 -> 6460.035 | V103: =(V101/12)*V99 -> 8084.4005 | W103: =(W101/12)*W99 -> 9708.766 | X103: =(X101/12)*X99 -> 11333.131 | Y103: =(Y101/12)*Y99 -> 12957.497 | ... BY103: =(BY101/12)*BY99 -> 65510.274
B105: Annual SaaS Tier 3
B106: % of Total New Customers | D106: 0.2 | R106: =D106 -> 0.2 | S106: =R106 -> 0.2 | T106: =S106 -> 0.2 | U106: =T106 -> 0.2 | V106: =U106 -> 0.2 | W106: =V106 -> 0.2 | X106: =W106 -> 0.2 | Y106: =X106 -> 0.2 | Z106: =Y106 -> 0.2 | ... BY106: =BX106 -> 0.2
B107: New Customers | R107: =R106*R$71 -> 63.5 | S107: =S106*S$71 -> 64.9525 | T107: =T106*T$71 -> 64.974288 | U107: =U106*U$71 -> 64.974614 | V107: =V106*V$71 -> 64.974619 | W107: =W106*W$71 -> 64.974619 | X107: =X106*X$71 -> 64.974619 | Y107: =Y106*Y$71 -> 64.974619 | ... BY107: =BY106*BY$71 -> 64.974619
B108: Billed Subscriptions | F108: 0 | G108: 0 | H108: 0 | I108: 0 | J108: 0 | K108: 0 | L108: 0 | M108: 0 | N108: 0 | O108: 0 | P108: 0 | Q108: 0 | R108: =R107+R113 -> 63.5 | S108: =S107+S113 -> 64.9525 | T108: =T107+T113 -> 64.974288 | U108: =U107+U113 -> 64.974614 | V108: =V107+V113 -> 64.974619 | W108: =W107+W113 -> 64.974619 | X108: =X107+X113 -> 64.974619 | Y108: =Y107+Y113 -> 64.974619 | ... BY108: =BY107+BY113 -> 218.41868
B109: Subscriptions Available for Renewal | R109: =F108 -> 0 | S109: =G108 -> 0 | T109: =H108 -> 0 | U109: =I108 -> 0 | V109: =J108 -> 0 | W109: =K108 -> 0 | X109: =L108 -> 0 | Y109: =M108 -> 0 | ... BY109: =BM108 -> 191.80508
B110: Subscriptions In-between Billing Cycles | R110: =R115-R109 -> 0 | S110: =S115-S109 -> 63.5 | T110: =T115-T109 -> 128.4525 | U110: =U115-U109 -> 193.42679 | V110: =V115-V109 -> 258.4014 | W110: =W115-W109 -> 323.37602 | X110: =X115-X109 -> 388.35064 | Y110: =Y115-Y109 -> 453.32526 | ... BY110: =BY115-BY109 -> 2401.9923
B111: Annual Churn Rate | D111: 0.2 | R111: =D111 -> 0.2 | S111: =R111 -> 0.2 | T111: =S111 -> 0.2 | U111: =T111 -> 0.2 | V111: =U111 -> 0.2 | W111: =V111 -> 0.2 | X111: =W111 -> 0.2 | Y111: =X111 -> 0.2 | Z111: =Y111 -> 0.2 | ... BY111: =BX111 -> 0.2
B112: Churned Subscriptions | R112: =R109*R111 -> 0 | S112: =S109*S111 -> 0 | T112: =T109*T111 -> 0 | U112: =U109*U111 -> 0 | V112: =V109*V111 -> 0 | W112: =W109*W111 -> 0 | X112: =X109*X111 -> 0 | Y112: =Y109*Y111 -> 0 | ... BY112: =BY109*BY111 -> 38.361015
B113: Renewed Susbcriptions | R113: =R109-R112 -> 0 | S113: =S109-S112 -> 0 | T113: =T109-T112 -> 0 | U113: =U109-U112 -> 0 | V113: =V109-V112 -> 0 | W113: =W109-W112 -> 0 | X113: =X109-X112 -> 0 | Y113: =Y109-Y112 -> 0 | ... BY113: =BY109-BY112 -> 153.44406
B114: Active Subscriptions | R114: =R108+R110 -> 63.5 | S114: =S108+S110 -> 128.4525 | T114: =T108+T110 -> 193.42679 | U114: =U108+U110 -> 258.4014 | V114: =V108+V110 -> 323.37602 | W114: =W108+W110 -> 388.35064 | X114: =X108+X110 -> 453.32526 | Y114: =Y108+Y110 -> 518.29988 | ... BY114: =BY108+BY110 -> 2620.411
B115: Previous Months Active Subsciptions | R115: =E114 | S115: =R114 -> 63.5 | T115: =S114 -> 128.4525 | U115: =T114 -> 193.42679 | V115: =U114 -> 258.4014 | W115: =V114 -> 323.37602 | X115: =W114 -> 388.35064 | Y115: =X114 -> 453.32526 | Z115: =Y114 -> 518.29988 | ... BY115: =BX114 -> 2593.7974
B116: Annual Price | D116: 350 | R116: =D116 -> 350 | S116: =R116 -> 350 | T116: =S116 -> 350 | U116: =T116 -> 350 | V116: =U116 -> 350 | W116: =V116 -> 350 | X116: =W116 -> 350 | Y116: =X116 -> 350 | Z116: =Y116 -> 350 | ... BY116: =BX116 -> 350
B117: Bookings | R117: =R108*R116 -> 22225 | S117: =S108*S116 -> 22733.375 | T117: =T108*T116 -> 22741.001 | U117: =U108*U116 -> 22741.115 | V117: =V108*V116 -> 22741.117 | W117: =W108*W116 -> 22741.117 | X117: =X108*X116 -> 22741.117 | Y117: =Y108*Y116 -> 22741.117 | ... BY117: =BY108*BY116 -> 76446.538
...

Sheet Financials
B1: Year Counter | F1: 1 | G1: 1 | H1: 1 | I1: 1 | J1: 1 | K1: 1 | L1: 1 | M1: 1 | N1: 1 | O1: 1 | P1: 1 | Q1: 1 | R1: =F1+1 -> 2 | S1: =G1+1 -> 2 | T1: =H1+1 -> 2 | U1: =I1+1 -> 2 | V1: =J1+1 -> 2 | W1: =K1+1 -> 2 | X1: =L1+1 -> 2 | Y1: =M1+1 -> 2 | ... BM1: =BA1+1 -> 5
B2: Year | F2: =YEAR(F4) -> 2023 | G2: =YEAR(G4) -> 2023 | H2: =YEAR(H4) -> 2023 | I2: =YEAR(I4) -> 2023 | J2: =YEAR(J4) -> 2023 | K2: =YEAR(K4) -> 2023 | L2: =YEAR(L4) -> 2023 | M2: =YEAR(M4) -> 2023 | ... BM2: =YEAR(BM4) -> 2027
B3: Month Counter | F3: 1 | G3: =F3+1 -> 2 | H3: =G3+1 -> 3 | I3: =H3+1 -> 4 | J3: =I3+1 -> 5 | K3: =J3+1 -> 6 | L3: =K3+1 -> 7 | M3: =L3+1 -> 8 | N3: =M3+1 -> 9 | ... BM3: =BL3+1 -> 60
B4: Date | F4: =Assumptions!R4 -> 44957 | G4: =EOMONTH(F4,1) -> 44985 | H4: =EOMONTH(G4,1) -> 45016 | I4: =EOMONTH(H4,1) -> 45046 | J4: =EOMONTH(I4,1) -> 45077 | K4: =EOMONTH(J4,1) -> 45107 | L4: =EOMONTH(K4,1) -> 45138 | M4: =EOMONTH(L4,1) -> 45169 | N4: =EOMONTH(M4,1) -> 45199 | ... BM4: =EOMONTH(BL4,1) -> 46752
B6: Income Statement:
B8: Revenue | F8: =sum(F9:F11) -> 4762.5 | G8: =sum(G9:G11) -> 9633.9375 | H8: =sum(H9:H11) -> 14507.009 | I8: =sum(I9:I11) -> 19380.105 | J8: =sum(J9:J11) -> 24253.202 | K8: =sum(K9:K11) -> 29126.298 | L8: =sum(L9:L11) -> 33999.394 | M8: =sum(M9:M11) -> 38872.491 | ... BM8: =sum(BM9:BM11) -> 196530.82
B9: =Assumptions!B75 -> Annual SaaS Tier 1 | F9: =Assumptions!R88 -> 1322.9167 | G9: =Assumptions!S88 -> 2676.0938 | H9: =Assumptions!T88 -> 4029.7247 | I9: =Assumptions!U88 -> 5383.3625 | J9: =Assumptions!V88 -> 6737.0004 | K9: =Assumptions!W88 -> 8090.6383 | L9: =Assumptions!X88 -> 9444.2762 | M9: =Assumptions!Y88 -> 10797.914 | ... BN9: =Assumptions!BZ88
B10: =Assumptions!B90 -> Annual SaaS Tier 2 | F10: =Assumptions!R103 -> 1587.5 | G10: =Assumptions!S103 -> 3211.3125 | H10: =Assumptions!T103 -> 4835.6697 | I10: =Assumptions!U103 -> 6460.035 | J10: =Assumptions!V103 -> 8084.4005 | K10: =Assumptions!W103 -> 9708.766 | L10: =Assumptions!X103 -> 11333.131 | M10: =Assumptions!Y103 -> 12957.497 | ... BN10: =Assumptions!BZ103
B11: =Assumptions!B105 -> Annual SaaS Tier 3 | F11: =Assumptions!R118 -> 1852.0833 | G11: =Assumptions!S118 -> 3746.5312 | H11: =Assumptions!T118 -> 5641.6146 | I11: =Assumptions!U118 -> 7536.7076 | J11: =Assumptions!V118 -> 9431.8006 | K11: =Assumptions!W118 -> 11326.894 | L11: =Assumptions!X118 -> 13221.987 | M11: =Assumptions!Y118 -> 15117.08 | ... BN11: =Assumptions!BZ118
B13: COGS | F13: =Assumptions!R163 -> 1666.875 | G13: =Assumptions!S163 -> 3371.8781 | H13: =Assumptions!T163 -> 5077.4532 | I13: =Assumptions!U163 -> 6783.0368 | J13: =Assumptions!V163 -> 8488.6206 | K13: =Assumptions!W163 -> 10194.204 | L13: =Assumptions!X163 -> 11899.788 | M13: =Assumptions!Y163 -> 13605.372 | ... BM13: =Assumptions!BY163 -> 68785.788
B15: Gross Profit | F15: =F8-F13 -> 3095.625 | G15: =G8-G13 -> 6262.0594 | H15: =H8-H13 -> 9429.5559 | I15: =I8-I13 -> 12597.068 | J15: =J8-J13 -> 15764.581 | K15: =K8-K13 -> 18932.094 | L15: =L8-L13 -> 22099.606 | M15: =M8-M13 -> 25267.119 | ... BM15: =BM8-BM13 -> 127745.03
B16: Gross Margin | F16: =F15/F8 -> 0.65 | G16: =G15/G8 -> 0.65 | H16: =H15/H8 -> 0.65 | I16: =I15/I8 -> 0.65 | J16: =J15/J8 -> 0.65 | K16: =K15/K8 -> 0.65 | L16: =L15/L8 -> 0.65 | M16: =M15/M8 -> 0.65 | ... BM16: =BM15/BM8 -> 0.65
B18: Operating Expenses
B19: Salaries & Benefits | F19: =SUM(Assumptions!R126:R150) -> 202000 | G19: =SUM(Assumptions!S126:S150) -> 202000 | H19: =SUM(Assumptions!T126:T150) -> 202000 | I19: =SUM(Assumptions!U126:U150) -> 202000 | J19: =SUM(Assumptions!V126:V150) -> 202000 | K19: =SUM(Assumptions!W126:W150) -> 202000 | L19: =SUM(Assumptions!X126:X150) -> 202000 | M19: =SUM(Assumptions!Y126:Y150) -> 202000 | ... BM19: =SUM(Assumptions!BY126:BY150) -> 202000
B20: =Assumptions!B165 -> General & Admin | F20: =sum(Assumptions!R166:R173) -> 20000 | G20: =sum(Assumptions!S166:S173) -> 20000 | H20: =sum(Assumptions!T166:T173) -> 20000 | I20: =sum(Assumptions!U166:U173) -> 20000 | J20: =sum(Assumptions!V166:V173) -> 20000 | K20: =sum(Assumptions!W166:W173) -> 20000 | L20: =sum(Assumptions!X166:X173) -> 20000 | M20: =sum(Assumptions!Y166:Y173) -> 20000 | ... BM20: =sum(Assumptions!BY166:BY173) -> 20000
B21: =Assumptions!B176 -> Sales & Marketing | F21: =sum(Assumptions!R177:R178) -> 10381 | G21: =sum(Assumptions!S177:S178) -> 10770.715 | H21: =sum(Assumptions!T177:T178) -> 11160.561 | I21: =sum(Assumptions!U177:U178) -> 11550.408 | J21: =sum(Assumptions!V177:V178) -> 11940.256 | K21: =sum(Assumptions!W177:W178) -> 12330.104 | L21: =sum(Assumptions!X177:X178) -> 12719.952 | M21: =sum(Assumptions!Y177:Y178) -> 13109.799 | ... BM21: =sum(Assumptions!BY177:BY178) -> 25722.466
B22: =Assumptions!B181 -> Professional Fees | F22: =SUM(Assumptions!R182:R184) -> 5500 | G22: =SUM(Assumptions!S182:S184) -> 5500 | H22: =SUM(Assumptions!T182:T184) -> 5500 | I22: =SUM(Assumptions!U182:U184) -> 5500 | J22: =SUM(Assumptions!V182:V184) -> 5500 | K22: =SUM(Assumptions!W182:W184) -> 5500 | L22: =SUM(Assumptions!X182:X184) -> 5500 | M22: =SUM(Assumptions!Y182:Y184) -> 5500 | ... BM22: =SUM(Assumptions!BY182:BY184) -> 5500
B23: =Assumptions!B187 -> Other | F23: =Assumptions!R188 -> 476.25 | G23: =Assumptions!S188 -> 963.39375 | H23: =Assumptions!T188 -> 1450.7009 | I23: =Assumptions!U188 -> 1938.0105 | J23: =Assumptions!V188 -> 2425.3202 | K23: =Assumptions!W188 -> 2912.6298 | L23: =Assumptions!X188 -> 3399.9394 | M23: =Assumptions!Y188 -> 3887.2491 | ... BM23: =Assumptions!BY188 -> 19653.082
B24: Total Operating Expenses | F24: =SUM(F19:F23) -> 238357.25 | G24: =SUM(G19:G23) -> 239234.11 | H24: =SUM(H19:H23) -> 240111.26 | I24: =SUM(I19:I23) -> 240988.42 | J24: =SUM(J19:J23) -> 241865.58 | K24: =SUM(K19:K23) -> 242742.73 | L24: =SUM(L19:L23) -> 243619.89 | M24: =SUM(M19:M23) -> 244497.05 | ... BM24: =SUM(BM19:BM23) -> 272875.55
B26: EBITDA | F26: =F15-F24 -> -235261.62 | G26: =G15-G24 -> -232972.05 | H26: =H15-H24 -> -230681.71 | I26: =I15-I24 -> -228391.35 | J26: =J15-J24 -> -226101 | K26: =K15-K24 -> -223810.64 | L26: =L15-L24 -> -221520.28 | M26: =M15-M24 -> -219229.93 | ... BM26: =BM15-BM24 -> -145130.51
B27: Depreciation | F27: =SUM(Assumptions!R209:R212)-sum(Assumptions!E209:E212) -> 0 | G27: =SUM(Assumptions!S209:S212)-sum(Assumptions!R209:R212) -> 0 | H27: =SUM(Assumptions!T209:T212)-sum(Assumptions!S209:S212) -> 0 | I27: =SUM(Assumptions!U209:U212)-sum(Assumptions!T209:T212) -> 0 | J27: =SUM(Assumptions!V209:V212)-sum(Assumptions!U209:U212) -> 0 | K27: =SUM(Assumptions!W209:W212)-sum(Assumptions!V209:V212) -> 0 | L27: =SUM(Assumptions!X209:X212)-sum(Assumptions!W209:W212) -> 0 | M27: =SUM(Assumptions!Y209:Y212)-sum(Assumptions!X209:X212) -> 0 | N27: =SUM(Assumptions!Z209:Z212)-sum(Assumptions!Y209:Y212) -> 0 | ... BM27: =SUM(Assumptions!BY209:BY212)-sum(Assumptions!BX209:BX212) -> 0
B28: EBIT | F28: =F26-F27 -> -235261.62 | G28: =G26-G27 -> -232972.05 | H28: =H26-H27 -> -230681.71 | I28: =I26-I27 -> -228391.35 | J28: =J26-J27 -> -226101 | K28: =K26-K27 -> -223810.64 | L28: =L26-L27 -> -221520.28 | M28: =M26-M27 -> -219229.93 | ... BM28: =BM26-BM27 -> -145130.51
B29: Taxes | F29: =IF(F28>0,F28*Assumptions!$C$190,0) -> 0 | G29: =IF(G28>0,G28*Assumptions!$C$190,0) -> 0 | H29: =IF(H28>0,H28*Assumptions!$C$190,0) -> 0 | I29: =IF(I28>0,I28*Assumptions!$C$190,0) -> 0 | J29: =IF(J28>0,J28*Assumptions!$C$190,0) -> 0 | K29: =IF(K28>0,K28*Assumptions!$C$190,0) -> 0 | L29: =IF(L28>0,L28*Assumptions!$C$190,0) -> 0 | M29: =IF(M28>0,M28*Assumptions!$C$190,0) -> 0 | ... BM29: =IF(BM28>0,BM28*Assumptions!$C$190,0) -> 0
B30: Net Income | F30: =F28-F29 -> -235261.62 | G30: =G28-G29 -> -232972.05 | H30: =H28-H29 -> -230681.71 | I30: =I28-I29 -> -228391.35 | J30: =J28-J29 -> -226101 | K30: =K28-K29 -> -223810.64 | L30: =L28-L29 -> -221520.28 | M30: =M28-M29 -> -219229.93 | ... BM30: =BM28-BM29 -> -145130.51
B31: Net Margin | F31: =F30/F8 -> -49.398766 | G31: =G30/G8 -> -24.182433 | H31: =H30/H8 -> -15.901397 | I31: =I30/I8 -> -11.784835 | J31: =J30/J8 -> -9.3225216 | K31: =K30/K8 -> -7.684143 | L31: =L30/L8 -> -6.5154185 | M31: =M30/M8 -> -5.6397191 | ... BM31: =BM30/BM8 -> -0.73846185
B33: Balance Sheet:
B35: Assets
B36: Current Assets
B37: Cash | F37: =F82 -> 333756.69 | G37: =G82 -> 148463.16 | H37: =H82 -> -39393.865 | I37: =I82 -> -229833.35 | J37: =J82 -> -422855.56 | K37: =K82 -> -618460.52 | L37: =L82 -> -816648.22 | M37: =M82 -> -1017418.7 | ... BM37: =BM82 -> -9397036.2
B38: Accounts Receivable | F38: =Assumptions!R200 -> 2381.25 | G38: =Assumptions!S200 -> 4816.9688 | H38: =Assumptions!T200 -> 7253.5045 | I38: =Assumptions!U200 -> 9690.0526 | J38: =Assumptions!V200 -> 12126.601 | K38: =Assumptions!W200 -> 14563.149 | L38: =Assumptions!X200 -> 16999.697 | M38: =Assumptions!Y200 -> 19436.245 | ... BM38: =Assumptions!BY200 -> 98265.411
B39: Total Current Assets | F39: =SUM(F37:F38) -> 336137.94 | G39: =SUM(G37:G38) -> 153280.13 | H39: =SUM(H37:H38) -> -32140.361 | I39: =SUM(I37:I38) -> -220143.29 | J39: =SUM(J37:J38) -> -410728.96 | K39: =SUM(K37:K38) -> -603897.37 | L39: =SUM(L37:L38) -> -799648.52 | M39: =SUM(M37:M38) -> -997982.42 | ... BM39: =SUM(BM37:BM38) -> -9298770.8
B41: Fixed Assets | F41: =SUM(Assumptions!R202:R206) -> 0 | G41: =SUM(Assumptions!S202:S206) -> 0 | H41: =SUM(Assumptions!T202:T206) -> 0 | I41: =SUM(Assumptions!U202:U206) -> 0 | J41: =SUM(Assumptions!V202:V206) -> 0 | K41: =SUM(Assumptions!W202:W206) -> 0 | L41: =SUM(Assumptions!X202:X206) -> 0 | M41: =SUM(Assumptions!Y202:Y206) -> 0 | ... BM41: =SUM(Assumptions!BY202:BY206) -> 0
B42: Accumulated Depreciation | F42: =-SUM(Assumptions!R209:R212) -> 0 | G42: =-SUM(Assumptions!S209:S212) -> 0 | H42: =-SUM(Assumptions!T209:T212) -> 0 | I42: =-SUM(Assumptions!U209:U212) -> 0 | J42: =-SUM(Assumptions!V209:V212) -> 0 | K42: =-SUM(Assumptions!W209:W212) -> 0 | L42: =-SUM(Assumptions!X209:X212) -> 0 | M42: =-SUM(Assumptions!Y209:Y212) -> 0 | ... BM42: =-SUM(Assumptions!BY209:BY212) -> 0
B43: Total Assets | F43: =SUM(F39:F42) -> 336137.94 | G43: =SUM(G39:G42) -> 153280.13 | H43: =SUM(H39:H42) -> -32140.361 | I43: =SUM(I39:I42) -> -220143.29 | J43: =SUM(J39:J42) -> -410728.96 | K43: =SUM(K39:K42) -> -603897.37 | L43: =SUM(L39:L42) -> -799648.52 | M43: =SUM(M39:M42) -> -997982.42 | ... BM43: =SUM(BM39:BM42) -> -9298770.8
B45: Liabilities & Owner's Equity
B46: Liabilities
B47: Accounts payable | F47: =Assumptions!R216 -> 19012.062 | G47: =Assumptions!S216 -> 20302.993 | H47: =Assumptions!T216 -> 21594.357 | I47: =Assumptions!U216 -> 22885.728 | J47: =Assumptions!V216 -> 24177.098 | K47: =Assumptions!W216 -> 25468.469 | L47: =Assumptions!X216 -> 26759.84 | M47: =Assumptions!Y216 -> 28051.21 | ... BM47: =Assumptions!BY216 -> 69830.668
B48: Deferred Revenue | F48: =Assumptions!R218 -> 52387.5 | G48: =Assumptions!S218 -> 101210.81 | H48: =Assumptions!T218 -> 145180.66 | I48: =Assumptions!U218 -> 184277.71 | J48: =Assumptions!V218 -> 218501.67 | K48: =Assumptions!W218 -> 247852.52 | L48: =Assumptions!X218 -> 272330.29 | M48: =Assumptions!Y218 -> 291934.95 | ... BN48: =Assumptions!BZ218
B49: Total Liabilities | F49: =SUM(F47:F48) -> 71399.562 | G49: =SUM(G47:G48) -> 121513.81 | H49: =SUM(H47:H48) -> 166775.02 | I49: =SUM(I47:I48) -> 207163.44 | J49: =SUM(J47:J48) -> 242678.76 | K49: =SUM(K47:K48) -> 273320.99 | L49: =SUM(L47:L48) -> 299090.13 | M49: =SUM(M47:M48) -> 319986.16 | ... BM49: =SUM(BM47:BM48) -> 1151002.4
B51: Equity | E51: Prev Cash
B52: Paid In Capital | E52: =Assumptions!C198 -> 500000 | F52: =E52 -> 500000 | G52: =Assumptions!S232+$E52 -> 500000 | H52: =Assumptions!T232+$E52 -> 500000 | I52: =Assumptions!U232+$E52 -> 500000 | J52: =Assumptions!V232+$E52 -> 500000 | K52: =Assumptions!W232+$E52 -> 500000 | L52: =Assumptions!X232+$E52 -> 500000 | M52: =Assumptions!Y232+$E52 -> 500000 | N52: =Assumptions!Z232+$E52 -> 500000 | ... BM52: =Assumptions!BY232+$E52 -> 500000
B53: Accumulated Retained Earnings | F53: =E53+F30 -> -235261.62 | G53: =F53+G30 -> -468233.67 | H53: =G53+H30 -> -698915.38 | I53: =H53+I30 -> -927306.73 | J53: =I53+J30 -> -1153407.7 | K53: =J53+K30 -> -1377218.4 | L53: =K53+L30 -> -1598738.6 | M53: =L53+M30 -> -1817968.6 | ... BM53: =BL53+BM30 -> -10949773
B54: Total Equity | F54: =SUM(F52:F53) -> 264738.38 | G54: =SUM(G52:G53) -> 31766.326 | H54: =SUM(H52:H53) -> -198915.38 | I54: =SUM(I52:I53) -> -427306.73 | J54: =SUM(J52:J53) -> -653407.73 | K54: =SUM(K52:K53) -> -877218.37 | L54: =SUM(L52:L53) -> -1098738.6 | M54: =SUM(M52:M53) -> -1317968.6 | ... BM54: =SUM(BM52:BM53) -> -10449773
B56: Total Liabilities & Owner's Equity | F56: =F54+F49 -> 336137.94 | G56: =G54+G49 -> 153280.13 | H56: =H54+H49 -> -32140.361 | I56: =I54+I49 -> -220143.29 | J56: =J54+J49 -> -410728.96 | K56: =K54+K49 -> -603897.37 | L56: =L54+L49 -> -799648.52 | M56: =M54+M49 -> -997982.42 | ... BM56: =BM54+BM49 -> -9298770.8
B58: Balance Check | F58: =IF(ABS(F56-F43)>0.001,"ERROR","OK") -> OK | G58: =IF(ABS(G56-G43)>0.001,"ERROR","OK") -> OK | H58: =IF(ABS(H56-H43)>0.001,"ERROR","OK") -> OK | I58: =IF(ABS(I56-I43)>0.001,"ERROR","OK") -> OK | J58: =IF(ABS(J56-J43)>0.001,"ERROR","OK") -> OK | K58: =IF(ABS(K56-K43)>0.001,"ERROR","OK") -> OK | L58: =IF(ABS(L56-L43)>0.001,"ERROR","OK") -> OK | M58: =IF(ABS(M56-M43)>0.001,"ERROR","OK") -> OK | ... BM58: =IF(ABS(BM56-BM43)>0.001,"ERROR","OK") -> OK
B60: Statement of Cash Flows:
B62: Operating Cash Flows
B63: Net Income | F63: =F53-E53 -> -235261.62 | G63: =G53-F53 -> -232972.05 | H63: =H53-G53 -> -230681.71 | I63: =I53-H53 -> -228391.35 | J63: =J53-I53 -> -226101 | K63: =K53-J53 -> -223810.64 | L63: =L53-K53 -> -221520.28 | M63: =M53-L53 -> -219229.93 | ... BM63: =BM53-BL53 -> -145130.51
B64: Depreciation | F64: =E42-F42 -> 0 | G64: =F42-G42 -> 0 | H64: =G42-H42 -> 0 | I64: =H42-I42 -> 0 | J64: =I42-J42 -> 0 | K64: =J42-K42 -> 0 | L64: =K42-L42 -> 0 | M64: =L42-M42 -> 0 | ... BM64: =BL42-BM42 -> 0
B65: Change in Accounts Receivable | F65: =E38-F38 -> -2381.25 | G65: =F38-G38 -> -2435.7188 | H65: =G38-H38 -> -2436.5358 | I65: =H38-I38 -> -2436.548 | J65: =I38-J38 -> -2436.5482 | K65: =J38-K38 -> -2436.5482 | L65: =K38-L38 -> -2436.5482 | M65: =L38-M38 -> -2436.5482 | ... BM65: =BL38-BM38 -> -998.01015
B66: Change in Accounts Payable | F66: =F47-E47 -> 19012.062 | G66: =G47-F47 -> 1290.9309 | H66: =H47-G47 -> 1291.364 | I66: =I47-H47 -> 1291.3705 | J66: =J47-I47 -> 1291.3706 | K66: =K47-J47 -> 1291.3706 | L66: =L47-K47 -> 1291.3706 | M66: =M47-L47 -> 1291.3706 | ... BM66: =BM47-BL47 -> 528.94538
B67: Change in Deferred Revenue | F67: =F48-E48 -> 52387.5 | G67: =G48-F48 -> 48823.312 | H67: =H48-G48 -> 43969.85 | I67: =I48-H48 -> 39097.048 | J67: =J48-I48 -> 34223.956 | K67: =K48-J48 -> 29350.859 | L67: =L48-K48 -> 24477.763 | M67: =M48-L48 -> 19604.666 | ... BM67: =BM48-BL48 -> 45.990157
B68: Total Operating Cash Flows | F68: =SUM(F63:F67) -> -166243.31 | G68: =SUM(G63:G67) -> -185293.52 | H68: =SUM(H63:H67) -> -187857.03 | I68: =SUM(I63:I67) -> -190439.48 | J68: =SUM(J63:J67) -> -193022.22 | K68: =SUM(K63:K67) -> -195604.96 | L68: =SUM(L63:L67) -> -198187.7 | M68: =SUM(M63:M67) -> -200770.44 | ... BM68: =SUM(BM63:BM67) -> -145553.59
B70: Investing Cash Flows
B71: Changes in Fixed Assets | F71: =E41-F41 -> 0 | G71: =F41-G41 -> 0 | H71: =G41-H41 -> 0 | I71: =H41-I41 -> 0 | J71: =I41-J41 -> 0 | K71: =J41-K41 -> 0 | L71: =K41-L41 -> 0 | M71: =L41-M41 -> 0 | ... BM71: =BL41-BM41 -> 0
B72: Total Investing Cash Flows | F72: =F71 -> 0 | G72: =G71 -> 0 | H72: =H71 -> 0 | I72: =I71 -> 0 | J72: =J71 -> 0 | K72: =K71 -> 0 | L72: =L71 -> 0 | M72: =M71 -> 0 | ... BM72: =BM71 -> 0
B74: Financing Cash Flows
B75: Changes in Paid in Capital | F75: =F52-E52 -> 0 | G75: =G52-F52 -> 0 | H75: =H52-G52 -> 0 | I75: =I52-H52 -> 0 | J75: =J52-I52 -> 0 | K75: =K52-J52 -> 0 | L75: =L52-K52 -> 0 | M75: =M52-L52 -> 0 | ... BM75: =BM52-BL52 -> 0
B76: Total Financing Cash Flows | F76: =F75 -> 0 | G76: =G75 -> 0 | H76: =H75 -> 0 | I76: =I75 -> 0 | J76: =J75 -> 0 | K76: =K75 -> 0 | L76: =L75 -> 0 | M76: =M75 -> 0 | ... BM76: =BM75 -> 0
B78: Beginning Cash | F78: =Assumptions!C198 -> 500000 | G78: =F82 -> 333756.69 | H78: =G82 -> 148463.16 | I78: =H82 -> -39393.865 | J78: =I82 -> -229833.35 | K78: =J82 -> -422855.56 | L78: =K82 -> -618460.52 | M78: =L82 -> -816648.22 | N78: =M82 -> -1017418.7 | ... BM78: =BL82 -> -9251482.6
B80: Change in Cash | F80: =F76+F72+F68 -> -166243.31 | G80: =G76+G72+G68 -> -185293.52 | H80: =H76+H72+H68 -> -187857.03 | I80: =I76+I72+I68 -> -190439.48 | J80: =J76+J72+J68 -> -193022.22 | K80: =K76+K72+K68 -> -195604.96 | L80: =L76+L72+L68 -> -198187.7 | M80: =M76+M72+M68 -> -200770.44 | ... BM80: =BM76+BM72+BM68 -> -145553.59
B82: Ending Cash | F82: =F78+F80 -> 333756.69 | G82: =G78+G80 -> 148463.16 | H82: =H78+H80 -> -39393.865 | I82: =I78+I80 -> -229833.35 | J82: =J78+J80 -> -422855.56 | K82: =K78+K80 -> -618460.52 | L82: =L78+L80 -> -816648.22 | M82: =M78+M80 -> -1017418.7 | ... BM82: =BM78+BM80 -> -9397036.2
B1009: Forecastr Template
