Workbook

Sheet Overview
C2: YOUR LOGO HERE
C4: Financial Model
G5: Welcome! This template was created by Forecastr's team of Financial Analysts and Fractional CFOs to help our fellow founders create better financial models for their startups and small businesses. Forecastr is an out-of-the-box finance function for your business. We provide the tools and support you need to create an investor-grade financial model. Our analysts work with you every step of the way to build a model that's customized to fit your business, keep it up to date, and generate insightful reports to share with your investors and other stakeholders. ✔ Impress your investors ✔ Hit your growth targets ✔ Never run out of cash
C7: Your Website Link Here
C10: Table of Contents
C12: Assumptions
C14: Financials
I18: SCHEDULE A MODELING SESSION WITH A MEMBER OF OUR TEAM

Sheet Assumptions
B1: Year Counter | H1: 1 | I1: 1 | J1: 1 | K1: 1 | L1: 1 | M1: 1 | N1: 1 | O1: 1 | P1: 1 | Q1: 1 | R1: 1 | S1: 1 | T1: =H1+1 -> 2 | U1: =I1+1 -> 2 | V1: =J1+1 -> 2 | W1: =K1+1 -> 2 | X1: =L1+1 -> 2 | Y1: =M1+1 -> 2 | Z1: =N1+1 -> 2 | AA1: =O1+1 -> 2 | ... BO1: =BC1+1 -> 5
B2: Year | H2: =YEAR(H4) -> 2026 | I2: =YEAR(I4) -> 2026 | J2: =YEAR(J4) -> 2026 | K2: =YEAR(K4) -> 2026 | L2: =YEAR(L4) -> 2026 | M2: =YEAR(M4) -> 2026 | N2: =YEAR(N4) -> 2026 | O2: =YEAR(O4) -> 2026 | ... BO2: =YEAR(BO4) -> 2031
B3: Month Counter | H3: 1 | I3: =H3+1 -> 2 | J3: =I3+1 -> 3 | K3: =J3+1 -> 4 | L3: =K3+1 -> 5 | M3: =L3+1 -> 6 | N3: =M3+1 -> 7 | O3: =N3+1 -> 8 | P3: =O3+1 -> 9 | ... BO3: =BN3+1 -> 60
B4: Date | H4: =eomonth(today(),0) -> 46081 | I4: =EOMONTH(H4,1) -> 46112 | J4: =EOMONTH(I4,1) -> 46142 | K4: =EOMONTH(J4,1) -> 46173 | L4: =EOMONTH(K4,1) -> 46203 | M4: =EOMONTH(L4,1) -> 46234 | N4: =EOMONTH(M4,1) -> 46265 | O4: =EOMONTH(N4,1) -> 46295 | P4: =EOMONTH(O4,1) -> 46326 | ... BO4: =EOMONTH(BN4,1) -> 47879
B6: Customer Acquisition:
B8: Build Customer Acquisition Channels
B10: Organic / Word of Mouth
B11: Web Traffic | D11: 1000 | H11: =D11 -> 1000 | I11: =H11 -> 1000 | J11: =I11 -> 1000 | K11: =J11 -> 1000 | L11: =K11 -> 1000 | M11: =L11 -> 1000 | N11: =M11 -> 1000 | O11: =N11 -> 1000 | P11: =O11 -> 1000 | ... BO11: =BN11 -> 1000
B12: Conversion Rate | D12: 0.05 | H12: =D12 -> 0.05 | I12: =H12 -> 0.05 | J12: =I12 -> 0.05 | K12: =J12 -> 0.05 | L12: =K12 -> 0.05 | M12: =L12 -> 0.05 | N12: =M12 -> 0.05 | O12: =N12 -> 0.05 | P12: =O12 -> 0.05 | ... BO12: =BN12 -> 0.05
B13: New Customers | H13: =H11*H12 -> 50 | I13: =I11*I12 -> 50 | J13: =J11*J12 -> 50 | K13: =K11*K12 -> 50 | L13: =L11*L12 -> 50 | M13: =M11*M12 -> 50 | N13: =N11*N12 -> 50 | O13: =O11*O12 -> 50 | ... BO13: =BO11*BO12 -> 50
B15: Paid Advertising
B16: Budget per Month | D16: 5000 | H16: =D16 -> 5000 | I16: =H16 -> 5000 | J16: =I16 -> 5000 | K16: =J16 -> 5000 | L16: =K16 -> 5000 | M16: =L16 -> 5000 | N16: =M16 -> 5000 | O16: =N16 -> 5000 | P16: =O16 -> 5000 | ... BO16: =BN16 -> 5000
B17: Average CPC | D17: 2 | H17: =D17 -> 2 | I17: =H17 -> 2 | J17: =I17 -> 2 | K17: =J17 -> 2 | L17: =K17 -> 2 | M17: =L17 -> 2 | N17: =M17 -> 2 | O17: =N17 -> 2 | P17: =O17 -> 2 | ... BO17: =BN17 -> 2
B18: Conversion Rate | D18: 0.05 | H18: =D18 -> 0.05 | I18: =H18 -> 0.05 | J18: =I18 -> 0.05 | K18: =J18 -> 0.05 | L18: =K18 -> 0.05 | M18: =L18 -> 0.05 | N18: =M18 -> 0.05 | O18: =N18 -> 0.05 | P18: =O18 -> 0.05 | ... BO18: =BN18 -> 0.05
B19: New Customers | H19: =(H16/H17)*H18 -> 125 | I19: =(I16/I17)*I18 -> 125 | J19: =(J16/J17)*J18 -> 125 | K19: =(K16/K17)*K18 -> 125 | L19: =(L16/L17)*L18 -> 125 | M19: =(M16/M17)*M18 -> 125 | N19: =(N16/N17)*N18 -> 125 | O19: =(O16/O17)*O18 -> 125 | ... BO19: =(BO16/BO17)*BO18 -> 125
B21: Affiliates
B22: Number of Affiliates | D22: 5 | H22: =D22 -> 5 | I22: =H22 -> 5 | J22: =I22 -> 5 | K22: =J22 -> 5 | L22: =K22 -> 5 | M22: =L22 -> 5 | N22: =M22 -> 5 | O22: =N22 -> 5 | P22: =O22 -> 5 | ... BO22: =BN22 -> 5
B23: New Monthly Leads per Affiliate | D23: 50 | H23: =D23 -> 50 | I23: =H23 -> 50 | J23: =I23 -> 50 | K23: =J23 -> 50 | L23: =K23 -> 50 | M23: =L23 -> 50 | N23: =M23 -> 50 | O23: =N23 -> 50 | P23: =O23 -> 50 | ... BO23: =BN23 -> 50
B24: Conversion Rate | D24: 0.05 | H24: =D24 -> 0.05 | I24: =H24 -> 0.05 | J24: =I24 -> 0.05 | K24: =J24 -> 0.05 | L24: =K24 -> 0.05 | M24: =L24 -> 0.05 | N24: =M24 -> 0.05 | O24: =N24 -> 0.05 | P24: =O24 -> 0.05 | ... BO24: =BN24 -> 0.05
B25: New Customers | H25: =H22*H23*H24 -> 12.5 | I25: =I22*I23*I24 -> 12.5 | J25: =J22*J23*J24 -> 12.5 | K25: =K22*K23*K24 -> 12.5 | L25: =L22*L23*L24 -> 12.5 | M25: =M22*M23*M24 -> 12.5 | N25: =N22*N23*N24 -> 12.5 | O25: =O22*O23*O24 -> 12.5 | ... BO25: =BO22*BO23*BO24 -> 12.5
B27: Conferences
B28: Conferences Atteneded | H28: 1 | I28: 0 | J28: 0 | K28: 0 | L28: 0 | M28: 0 | N28: 0 | O28: 0 | P28: 0 | Q28: 0 | R28: 0 | S28: 0 | T28: 0 | U28: 0 | V28: 0 | W28: 0 | X28: 0 | Y28: 0 | Z28: 0 | AA28: 0 | AB28: 0 | AC28: 0 | AD28: 0 | AE28: 0 | AF28: 0 | AG28: 0 | AH28: 0 | AI28: 0 | AJ28: 0 | AK28: 0 | AL28: 0 | AM28: 0 | AN28: 0 | AO28: 0 | AP28: 0 | AQ28: 0 | AR28: 0 | AS28: 0 | AT28: 0 | AU28: 0 | AV28: 0 | AW28: 0 | AX28: 0 | AY28: 0 | AZ28: 0 | BA28: 0 | BB28: 0 | BC28: 0 | BD28: 0 | BE28: 0 | BF28: 0 | BG28: 0 | BH28: 0 | BI28: 0 | BJ28: 0 | BK28: 0 | BL28: 0 | BM28: 0 | BN28: 0 | BO28: 0
B29: New Leads per Conference | D29: 50 | H29: =D29 -> 50 | I29: =H29 -> 50 | J29: =I29 -> 50 | K29: =J29 -> 50 | L29: =K29 -> 50 | M29: =L29 -> 50 | N29: =M29 -> 50 | O29: =N29 -> 50 | P29: =O29 -> 50 | ... BO29: =BN29 -> 50
B30: Conversion Rate | D30: 0.05 | H30: =D30 -> 0.05 | I30: =H30 -> 0.05 | J30: =I30 -> 0.05 | K30: =J30 -> 0.05 | L30: =K30 -> 0.05 | M30: =L30 -> 0.05 | N30: =M30 -> 0.05 | O30: =N30 -> 0.05 | P30: =O30 -> 0.05 | ... BO30: =BN30 -> 0.05
B31: New Customers | H31: =H28*H29*H30 -> 2.5 | I31: =I28*I29*I30 -> 0 | J31: =J28*J29*J30 -> 0 | K31: =K28*K29*K30 -> 0 | L31: =L28*L29*L30 -> 0 | M31: =M28*M29*M30 -> 0 | N31: =N28*N29*N30 -> 0 | O31: =O28*O29*O30 -> 0 | ... BO31: =BO28*BO29*BO30 -> 0
B33: Influencers
B34: Number of Influencers | D34: 2 | H34: =D34 -> 2 | I34: =H34 -> 2 | J34: =I34 -> 2 | K34: =J34 -> 2 | L34: =K34 -> 2 | M34: =L34 -> 2 | N34: =M34 -> 2 | O34: =N34 -> 2 | P34: =O34 -> 2 | ... BO34: =BN34 -> 2
B35: New Monthly Posts per Influencer | D35: 100 | H35: =D35 -> 100 | I35: =H35 -> 100 | J35: =I35 -> 100 | K35: =J35 -> 100 | L35: =K35 -> 100 | M35: =L35 -> 100 | N35: =M35 -> 100 | O35: =N35 -> 100 | P35: =O35 -> 100 | ... BO35: =BN35 -> 100
B36: New Monthly Leads per Post | D36: 5 | H36: =D36 -> 5 | I36: =H36 -> 5 | J36: =I36 -> 5 | K36: =J36 -> 5 | L36: =K36 -> 5 | M36: =L36 -> 5 | N36: =M36 -> 5 | O36: =N36 -> 5 | P36: =O36 -> 5 | ... BO36: =BN36 -> 5
B37: Conversion Rate | D37: 0.05 | H37: =D37 -> 0.05 | I37: =H37 -> 0.05 | J37: =I37 -> 0.05 | K37: =J37 -> 0.05 | L37: =K37 -> 0.05 | M37: =L37 -> 0.05 | N37: =M37 -> 0.05 | O37: =N37 -> 0.05 | P37: =O37 -> 0.05 | ... BO37: =BN37 -> 0.05
B38: New Customers | H38: =H34*H35*H36*H37 -> 50 | I38: =I34*I35*I36*I37 -> 50 | J38: =J34*J35*J36*J37 -> 50 | K38: =K34*K35*K36*K37 -> 50 | L38: =L34*L35*L36*L37 -> 50 | M38: =M34*M35*M36*M37 -> 50 | N38: =N34*N35*N36*N37 -> 50 | O38: =O34*O35*O36*O37 -> 50 | ... BO38: =BO34*BO35*BO36*BO37 -> 50
B40: Customer Referrals
B41: Previous Months New Customers | D41: =C71 | H41: =G71 | I41: =H71 -> 267.5 | J41: =I71 -> 274.0125 | K41: =J71 -> 274.11019 | L41: =K71 -> 274.11165 | M41: =L71 -> 274.11167 | N41: =M71 -> 274.11168 | O41: =N71 -> 274.11168 | ... BO41: =BN71 -> 274.11168
B42: Referral Percentage | D42: 0.3 | H42: =D42 -> 0.3 | I42: =H42 -> 0.3 | J42: =I42 -> 0.3 | K42: =J42 -> 0.3 | L42: =K42 -> 0.3 | M42: =L42 -> 0.3 | N42: =M42 -> 0.3 | O42: =N42 -> 0.3 | P42: =O42 -> 0.3 | ... BO42: =BN42 -> 0.3
B43: Conversion Rate | D43: 0.05 | H43: =D43 -> 0.05 | I43: =H43 -> 0.05 | J43: =I43 -> 0.05 | K43: =J43 -> 0.05 | L43: =K43 -> 0.05 | M43: =L43 -> 0.05 | N43: =M43 -> 0.05 | O43: =N43 -> 0.05 | P43: =O43 -> 0.05 | ... BO43: =BN43 -> 0.05
B44: New Customers | H44: =H41*H42*H43 -> 0 | I44: =I41*I42*I43 -> 4.0125 | J44: =J41*J42*J43 -> 4.1101875 | K44: =K41*K42*K43 -> 4.1116528 | L44: =L41*L42*L43 -> 4.1116748 | M44: =M41*M42*M43 -> 4.1116751 | N44: =N41*N42*N43 -> 4.1116751 | O44: =O41*O42*O43 -> 4.1116751 | ... BO44: =BO41*BO42*BO43 -> 4.1116751
B46: Partnerships
B47: Active Partnerships | D47: 2 | H47: =D47 -> 2 | I47: =H47 -> 2 | J47: =I47 -> 2 | K47: =J47 -> 2 | L47: =K47 -> 2 | M47: =L47 -> 2 | N47: =M47 -> 2 | O47: =N47 -> 2 | P47: =O47 -> 2 | ... BO47: =BN47 -> 2
B48: New Monthly Leads per Partnership | D48: 100 | H48: =D48 -> 100 | I48: =H48 -> 100 | J48: =I48 -> 100 | K48: =J48 -> 100 | L48: =K48 -> 100 | M48: =L48 -> 100 | N48: =M48 -> 100 | O48: =N48 -> 100 | P48: =O48 -> 100 | ... BO48: =BN48 -> 100
B49: Conversion Rate | D49: 0.05 | H49: =D49 -> 0.05 | I49: =H49 -> 0.05 | J49: =I49 -> 0.05 | K49: =J49 -> 0.05 | L49: =K49 -> 0.05 | M49: =L49 -> 0.05 | N49: =M49 -> 0.05 | O49: =N49 -> 0.05 | P49: =O49 -> 0.05 | ... BO49: =BN49 -> 0.05
B50: New Customers | H50: =H47*H48*H49 -> 10 | I50: =I47*I48*I49 -> 10 | J50: =J47*J48*J49 -> 10 | K50: =K47*K48*K49 -> 10 | L50: =L47*L48*L49 -> 10 | M50: =M47*M48*M49 -> 10 | N50: =N47*N48*N49 -> 10 | O50: =O47*O48*O49 -> 10 | ... BO50: =BO47*BO48*BO49 -> 10
B52: Email Marketing
B53: Mailing List Size | D53: 2000 | H53: =D53 -> 2000 | I53: =H53 -> 2000 | J53: =I53 -> 2000 | K53: =J53 -> 2000 | L53: =K53 -> 2000 | M53: =L53 -> 2000 | N53: =M53 -> 2000 | O53: =N53 -> 2000 | P53: =O53 -> 2000 | ... BO53: =BN53 -> 2000
B54: Average Number of Emails Sent a Month | D54: 2 | H54: =D54 -> 2 | I54: =H54 -> 2 | J54: =I54 -> 2 | K54: =J54 -> 2 | L54: =K54 -> 2 | M54: =L54 -> 2 | N54: =M54 -> 2 | O54: =N54 -> 2 | P54: =O54 -> 2 | ... BO54: =BN54 -> 2
B55: Response Rate per Email | D55: 0.05 | H55: =D55 -> 0.05 | I55: =H55 -> 0.05 | J55: =I55 -> 0.05 | K55: =J55 -> 0.05 | L55: =K55 -> 0.05 | M55: =L55 -> 0.05 | N55: =M55 -> 0.05 | O55: =N55 -> 0.05 | P55: =O55 -> 0.05 | ... BO55: =BN55 -> 0.05
B56: Conversion Rate | D56: 0.05 | H56: =D56 -> 0.05 | I56: =H56 -> 0.05 | J56: =I56 -> 0.05 | K56: =J56 -> 0.05 | L56: =K56 -> 0.05 | M56: =L56 -> 0.05 | N56: =M56 -> 0.05 | O56: =N56 -> 0.05 | P56: =O56 -> 0.05 | ... BO56: =BN56 -> 0.05
B57: New Customers | H57: =H53*H54*H55*H56 -> 10 | I57: =I53*I54*I55*I56 -> 10 | J57: =J53*J54*J55*J56 -> 10 | K57: =K53*K54*K55*K56 -> 10 | L57: =L53*L54*L55*L56 -> 10 | M57: =M53*M54*M55*M56 -> 10 | N57: =N53*N54*N55*N56 -> 10 | O57: =O53*O54*O55*O56 -> 10 | ... BO57: =BO53*BO54*BO55*BO56 -> 10
B59: Content Marketing
B60: New Pieces of Content | D60: 3 | H60: =D60 -> 3 | I60: =H60 -> 3 | J60: =I60 -> 3 | K60: =J60 -> 3 | L60: =K60 -> 3 | M60: =L60 -> 3 | N60: =M60 -> 3 | O60: =N60 -> 3 | P60: =O60 -> 3 | ... BO60: =BN60 -> 3
B61: New Leads per Piece of Content | D61: 50 | H61: =D61 -> 50 | I61: =H61 -> 50 | J61: =I61 -> 50 | K61: =J61 -> 50 | L61: =K61 -> 50 | M61: =L61 -> 50 | N61: =M61 -> 50 | O61: =N61 -> 50 | P61: =O61 -> 50 | ... BO61: =BN61 -> 50
B62: Conversion Rate | D62: 0.05 | H62: =D62 -> 0.05 | I62: =H62 -> 0.05 | J62: =I62 -> 0.05 | K62: =J62 -> 0.05 | L62: =K62 -> 0.05 | M62: =L62 -> 0.05 | N62: =M62 -> 0.05 | O62: =N62 -> 0.05 | P62: =O62 -> 0.05 | ... BO62: =BN62 -> 0.05
B63: New Customers | H63: =H60*H61*H62 -> 7.5 | I63: =I60*I61*I62 -> 7.5 | J63: =J60*J61*J62 -> 7.5 | K63: =K60*K61*K62 -> 7.5 | L63: =L60*L61*L62 -> 7.5 | M63: =M60*M61*M62 -> 7.5 | N63: =N60*N61*N62 -> 7.5 | O63: =O60*O61*O62 -> 7.5 | ... BO63: =BO60*BO61*BO62 -> 7.5
B65: Direct Sales Team
B66: Leads | D66: 25 | H66: =D66 -> 25 | I66: =H66 -> 25 | J66: =I66 -> 25 | K66: =J66 -> 25 | L66: =K66 -> 25 | M66: =L66 -> 25 | N66: =M66 -> 25 | O66: =N66 -> 25 | P66: =O66 -> 25 | ... BO66: =BN66 -> 25
B67: Sales Cycle | D67: 2 | H67: =D67 -> 2 | I67: =H67 -> 2 | J67: =I67 -> 2 | K67: =J67 -> 2 | L67: =K67 -> 2 | M67: =L67 -> 2 | N67: =M67 -> 2 | O67: =N67 -> 2 | P67: =O67 -> 2 | ... BO67: =BN67 -> 2
B68: Conversion Rate | D68: 0.2 | H68: =D68 -> 0.2 | I68: =H68 -> 0.2 | J68: =I68 -> 0.2 | K68: =J68 -> 0.2 | L68: =K68 -> 0.2 | M68: =L68 -> 0.2 | N68: =M68 -> 0.2 | O68: =N68 -> 0.2 | P68: =O68 -> 0.2 | ... BO68: =BN68 -> 0.2
B69: New Customers | H69: =IFERROR(offset(H66,,-H67+1)*H68,0) -> 0 | I69: =IFERROR(offset(I66,,-I67+1)*I68,0) -> 5 | J69: =IFERROR(offset(J66,,-J67+1)*J68,0) -> 5 | K69: =IFERROR(offset(K66,,-K67+1)*K68,0) -> 5 | L69: =IFERROR(offset(L66,,-L67+1)*L68,0) -> 5 | M69: =IFERROR(offset(M66,,-M67+1)*M68,0) -> 5 | N69: =IFERROR(offset(N66,,-N67+1)*N68,0) -> 5 | O69: =IFERROR(offset(O66,,-O67+1)*O68,0) -> 5 | ... BO69: =IFERROR(offset(BO66,,-BO67+1)*BO68,0) -> 5
B71: Total New Customers | H71: =H13+H19+H25+H31+H38+H44+H50+H57+H63+H69 -> 267.5 | I71: =I13+I19+I25+I31+I38+I44+I50+I57+I63+I69 -> 274.0125 | J71: =J13+J19+J25+J31+J38+J44+J50+J57+J63+J69 -> 274.11019 | K71: =K13+K19+K25+K31+K38+K44+K50+K57+K63+K69 -> 274.11165 | L71: =L13+L19+L25+L31+L38+L44+L50+L57+L63+L69 -> 274.11167 | M71: =M13+M19+M25+M31+M38+M44+M50+M57+M63+M69 -> 274.11168 | N71: =N13+N19+N25+N31+N38+N44+N50+N57+N63+N69 -> 274.11168 | O71: =O13+O19+O25+O31+O38+O44+O50+O57+O63+O69 -> 274.11168 | ... BO71: =BO13+BO19+BO25+BO31+BO38+BO44+BO50+BO57+BO63+BO69 -> 274.11168
B73: Revenue - Per Unit Monthly SaaS:
B75: Per Unit Monthly SaaS Tier 1
B76: % of Total New Customers | D76: 0.5 | H76: =D76 -> 0.5 | I76: =H76 -> 0.5 | J76: =I76 -> 0.5 | K76: =J76 -> 0.5 | L76: =K76 -> 0.5 | M76: =L76 -> 0.5 | N76: =M76 -> 0.5 | O76: =N76 -> 0.5 | P76: =O76 -> 0.5 | ... BO76: =BN76 -> 0.5
B77: New Customers | H77: =H76*H$71 -> 133.75 | I77: =I76*I$71 -> 137.00625 | J77: =J76*J$71 -> 137.05509 | K77: =K76*K$71 -> 137.05583 | L77: =L76*L$71 -> 137.05584 | M77: =M76*M$71 -> 137.05584 | N77: =N76*N$71 -> 137.05584 | O77: =O76*O$71 -> 137.05584 | ... BO77: =BO76*BO$71 -> 137.05584
B78: Churn Rate | D78: 0.05 | H78: =D78 -> 0.05 | I78: =H78 -> 0.05 | J78: =I78 -> 0.05 | K78: =J78 -> 0.05 | L78: =K78 -> 0.05 | M78: =L78 -> 0.05 | N78: =M78 -> 0.05 | O78: =N78 -> 0.05 | P78: =O78 -> 0.05 | ... BO78: =BN78 -> 0.05
B79: Churned Subscriptions | H79: =H82*H78 -> 0 | I79: =I82*I78 -> 6.6875 | J79: =J82*J78 -> 13.203437 | K79: =K82*K78 -> 19.39602 | L79: =L82*L78 -> 25.279011 | M79: =M82*M78 -> 30.867852 | N79: =N82*N78 -> 36.177251 | O79: =O82*O78 -> 41.221181 | ... BO79: =BO82*BO78 -> 130.40081
B80: Retained Subscriptions | H80: =H82-H79 -> 0 | I80: =I82-I79 -> 127.0625 | J80: =J82-J79 -> 250.86531 | K80: =K82-K79 -> 368.52439 | L80: =L82-L79 -> 480.3012 | M80: =M82-M79 -> 586.48919 | N80: =N82-N79 -> 687.36777 | O80: =O82-O79 -> 783.20243 | ... BO80: =BO82-BO79 -> 2477.6153
B81: Active Subscriptions | H81: =H77+H80 -> 133.75 | I81: =I77+I80 -> 264.06875 | J81: =J77+J80 -> 387.92041 | K81: =K77+K80 -> 505.58021 | L81: =L77+L80 -> 617.35704 | M81: =M77+M80 -> 723.54502 | N81: =N77+N80 -> 824.42361 | O81: =O77+O80 -> 920.25827 | ... BO81: =BO77+BO80 -> 2614.6712
B82: Previous Months Active Subsciptions | E82: MoM Growth | F82: MAX | H82: =G81 | I82: =H81 -> 133.75 | J82: =I81 -> 264.06875 | K82: =J81 -> 387.92041 | L82: =K81 -> 505.58021 | M82: =L81 -> 617.35704 | N82: =M81 -> 723.54502 | O82: =N81 -> 824.42361 | ... BO82: =BN81 -> 2608.0161
B83: Average Orders per User | D83: 2 | E83: 0.05 | F83: 10 | H83: =D83 -> 2 | I83: =H83*(1+$E$83) -> 2.1 | J83: =I83*(1+$E$83) -> 2.205 | K83: =J83*(1+$E$83) -> 2.31525 | L83: =K83*(1+$E$83) -> 2.4310125 | M83: =L83*(1+$E$83) -> 2.5525631 | N83: =M83*(1+$E$83) -> 2.6801913 | O83: =N83*(1+$E$83) -> 2.8142008 | P83: =O83*(1+$E$83) -> 2.9549109 | ... X83: =W83*(1+$E$83) -> 4.3657492 | Y83: =X83 -> 4.3657492 | Z83: =Y83 -> 4.3657492 | AA83: =Z83 -> 4.3657492 | AB83: =AA83 -> 4.3657492 | AC83: =AB83 -> 4.3657492 | AD83: =AC83 -> 4.3657492 | AE83: =AD83 -> 4.3657492 | AF83: =AE83 -> 4.3657492 | ... BO83: =BN83 -> 4.3657492
B84: Total Purchases this Month | H84: =H83*H81 -> 267.5 | I84: =I83*I81 -> 554.54437 | J84: =J83*J81 -> 855.3645 | K84: =K83*K81 -> 1170.5446 | L84: =L83*L81 -> 1500.8027 | M84: =M83*M81 -> 1846.8943 | N84: =N83*N81 -> 2209.613 | O84: =O83*O81 -> 2589.7916 | ... BO84: =BO83*BO81 -> 11414.998
B85: Average Price per Unit | D85: 10 | H85: =D85 -> 10 | I85: =H85 -> 10 | J85: =I85 -> 10 | K85: =J85 -> 10 | L85: =K85 -> 10 | M85: =L85 -> 10 | N85: =M85 -> 10 | O85: =N85 -> 10 | P85: =O85 -> 10 | ... BO85: =BN85 -> 10
B86: Revenue | H86: =H84*H85 -> 2675 | I86: =I84*I85 -> 5545.4438 | J86: =J84*J85 -> 8553.645 | K86: =K84*K85 -> 11705.446 | L86: =L84*L85 -> 15008.027 | M86: =M84*M85 -> 18468.943 | N86: =N84*N85 -> 22096.13 | O86: =O84*O85 -> 25897.916 | ... BO86: =BO84*BO85 -> 114149.98
B88: Per Unit Monthly SaaS Tier 2
B89: % of Total New Customers | D89: 0.3 | H89: =D89 -> 0.3 | I89: =H89 -> 0.3 | J89: =I89 -> 0.3 | K89: =J89 -> 0.3 | L89: =K89 -> 0.3 | M89: =L89 -> 0.3 | N89: =M89 -> 0.3 | O89: =N89 -> 0.3 | P89: =O89 -> 0.3 | ... BO89: =BN89 -> 0.3
B90: New Customers | H90: =H89*H$71 -> 80.25 | I90: =I89*I$71 -> 82.20375 | J90: =J89*J$71 -> 82.233056 | K90: =K89*K$71 -> 82.233496 | L90: =L89*L$71 -> 82.233502 | M90: =M89*M$71 -> 82.233503 | N90: =N89*N$71 -> 82.233503 | O90: =O89*O$71 -> 82.233503 | ... BO90: =BO89*BO$71 -> 82.233503
B91: Churn Rate | D91: 0.05 | H91: =D91 -> 0.05 | I91: =H91 -> 0.05 | J91: =I91 -> 0.05 | K91: =J91 -> 0.05 | L91: =K91 -> 0.05 | M91: =L91 -> 0.05 | N91: =M91 -> 0.05 | O91: =N91 -> 0.05 | P91: =O91 -> 0.05 | ... BO91: =BN91 -> 0.05
B92: Churned Subscriptions | H92: =H95*H91 -> 0 | I92: =I95*I91 -> 4.0125 | J92: =J95*J91 -> 7.9220625 | K92: =K95*K91 -> 11.637612 | L92: =L95*L91 -> 15.167406 | M92: =M95*M91 -> 18.520711 | N92: =N95*N91 -> 21.706351 | O92: =O95*O91 -> 24.732708 | ... BO92: =BO95*BO91 -> 78.240484
B93: Retained Subscriptions | H93: =H95-H92 -> 0 | I93: =I95-I92 -> 76.2375 | J93: =J95-J92 -> 150.51919 | K93: =K95-K92 -> 221.11463 | L93: =L95-L92 -> 288.18072 | M93: =M95-M92 -> 351.89351 | N93: =N95-N92 -> 412.42066 | O93: =O95-O92 -> 469.92146 | ... BO93: =BO95-BO92 -> 1486.5692
B94: Active Subscriptions | H94: =H90+H93 -> 80.25 | I94: =I90+I93 -> 158.44125 | J94: =J90+J93 -> 232.75224 | K94: =K90+K93 -> 303.34813 | L94: =L90+L93 -> 370.41422 | M94: =M90+M93 -> 434.12701 | N94: =N90+N93 -> 494.65417 | O94: =O90+O93 -> 552.15496 | ... BO94: =BO90+BO93 -> 1568.8027
B95: Previous Months Active Subsciptions | H95: =G94 | I95: =H94 -> 80.25 | J95: =I94 -> 158.44125 | K95: =J94 -> 232.75224 | L95: =K94 -> 303.34813 | M95: =L94 -> 370.41422 | N95: =M94 -> 434.12701 | O95: =N94 -> 494.65417 | ... BO95: =BN94 -> 1564.8097
B96: Average Units Purchased per Subscription | D96: 2 | H96: =D96 -> 2 | I96: =H96 -> 2 | J96: =I96 -> 2 | K96: =J96 -> 2 | L96: =K96 -> 2 | M96: =L96 -> 2 | N96: =M96 -> 2 | O96: =N96 -> 2 | P96: =O96 -> 2 | ... BO96: =BN96 -> 2
B97: Total Purchases this Month | H97: =H96*H94 -> 160.5 | I97: =I96*I94 -> 316.8825 | J97: =J96*J94 -> 465.50449 | K97: =K96*K94 -> 606.69625 | L97: =L96*L94 -> 740.82845 | M97: =M96*M94 -> 868.25403 | N97: =N96*N94 -> 989.30833 | O97: =O96*O94 -> 1104.3099 | ... BO97: =BO96*BO94 -> 3137.6054
B98: Average Price per Unit | D98: 25 | H98: =D98 -> 25 | I98: =H98 -> 25 | J98: =I98 -> 25 | K98: =J98 -> 25 | L98: =K98 -> 25 | M98: =L98 -> 25 | N98: =M98 -> 25 | O98: =N98 -> 25 | P98: =O98 -> 25 | ... BO98: =BN98 -> 25
B99: Revenue | H99: =H97*H98 -> 4012.5 | I99: =I97*I98 -> 7922.0625 | J99: =J97*J98 -> 11637.612 | K99: =K97*K98 -> 15167.406 | L99: =L97*L98 -> 18520.711 | M99: =M97*M98 -> 21706.351 | N99: =N97*N98 -> 24732.708 | O99: =O97*O98 -> 27607.748 | ... BO99: =BO97*BO98 -> 78440.135
B101: Per Unit Monthly SaaS Tier 3
B102: % of Total New Customers | D102: 0.2 | H102: =D102 -> 0.2 | I102: =H102 -> 0.2 | J102: =I102 -> 0.2 | K102: =J102 -> 0.2 | L102: =K102 -> 0.2 | M102: =L102 -> 0.2 | N102: =M102 -> 0.2 | O102: =N102 -> 0.2 | P102: =O102 -> 0.2 | ... BO102: =BN102 -> 0.2
B103: New Customers | H103: =H102*H$71 -> 53.5 | I103: =I102*I$71 -> 54.8025 | J103: =J102*J$71 -> 54.822038 | K103: =K102*K$71 -> 54.822331 | L103: =L102*L$71 -> 54.822335 | M103: =M102*M$71 -> 54.822335 | N103: =N102*N$71 -> 54.822335 | O103: =O102*O$71 -> 54.822335 | ... BO103: =BO102*BO$71 -> 54.822335
B104: Churn Rate | D104: 0.05 | H104: =D104 -> 0.05 | I104: =H104 -> 0.05 | J104: =I104 -> 0.05 | K104: =J104 -> 0.05 | L104: =K104 -> 0.05 | M104: =L104 -> 0.05 | N104: =M104 -> 0.05 | O104: =N104 -> 0.05 | P104: =O104 -> 0.05 | ... BO104: =BN104 -> 0.05
B105: Churned Subscriptions | H105: =H108*H104 -> 0 | I105: =I108*I104 -> 2.675 | J105: =J108*J104 -> 5.281375 | K105: =K108*K104 -> 7.7584081 | L105: =L108*L104 -> 10.111604 | M105: =M108*M104 -> 12.347141 | N105: =N108*N104 -> 14.4709 | O105: =O108*O104 -> 16.488472 | ... BO105: =BO108*BO104 -> 52.160323
B106: Retained Subscriptions | H106: =H108-H105 -> 0 | I106: =I108-I105 -> 50.825 | J106: =J108-J105 -> 100.34613 | K106: =K108-K105 -> 147.40975 | L106: =L108-L105 -> 192.12048 | M106: =M108-M105 -> 234.59567 | N106: =N108-N105 -> 274.94711 | O106: =O108-O105 -> 313.28097 | ... BO106: =BO108-BO105 -> 991.04613
B107: Active Subscriptions | H107: =H103+H106 -> 53.5 | I107: =I103+I106 -> 105.6275 | J107: =J103+J106 -> 155.16816 | K107: =K103+K106 -> 202.23208 | L107: =L103+L106 -> 246.94282 | M107: =M103+M106 -> 289.41801 | N107: =N103+N106 -> 329.76944 | O107: =O103+O106 -> 368.10331 | ... BO107: =BO103+BO106 -> 1045.8685
B108: Previous Months Active Subsciptions | H108: =G107 | I108: =H107 -> 53.5 | J108: =I107 -> 105.6275 | K108: =J107 -> 155.16816 | L108: =K107 -> 202.23208 | M108: =L107 -> 246.94282 | N108: =M107 -> 289.41801 | O108: =N107 -> 329.76944 | ... BO108: =BN107 -> 1043.2065
B109: Average Units Purchased per Subscription | D109: 2 | H109: =D109 -> 2 | I109: =H109 -> 2 | J109: =I109 -> 2 | K109: =J109 -> 2 | L109: =K109 -> 2 | M109: =L109 -> 2 | N109: =M109 -> 2 | O109: =N109 -> 2 | P109: =O109 -> 2 | ... BO109: =BN109 -> 2
B110: Total Purchases this Month | H110: =H109*H107 -> 107 | I110: =I109*I107 -> 211.255 | J110: =J109*J107 -> 310.33632 | K110: =K109*K107 -> 404.46417 | L110: =L109*L107 -> 493.88563 | M110: =M109*M107 -> 578.83602 | N110: =N109*N107 -> 659.53889 | O110: =O109*O107 -> 736.20661 | ... BO110: =BO109*BO107 -> 2091.7369
B111: Average Price per Unit | D111: 50 | H111: =D111 -> 50 | I111: =H111 -> 50 | J111: =I111 -> 50 | K111: =J111 -> 50 | L111: =K111 -> 50 | M111: =L111 -> 50 | N111: =M111 -> 50 | O111: =N111 -> 50 | P111: =O111 -> 50 | ... BO111: =BN111 -> 50
B112: Revenue | H112: =H110*H111 -> 5350 | I112: =I110*I111 -> 10562.75 | J112: =J110*J111 -> 15516.816 | K112: =K110*K111 -> 20223.208 | L112: =L110*L111 -> 24694.282 | M112: =M110*M111 -> 28941.801 | N112: =N110*N111 -> 32976.944 | O112: =O110*O111 -> 36810.331 | ... BO112: =BO110*BO111 -> 104586.85
B114: + ADD MORE
B117: People:
B119: Name | C119: Salary | D119: Benefits | E119: Start Date
B120: Person 1 | C120: 100000 | D120: 0.2 | E120: 43831 | H120: =IF(H$4>=$E120,($C120/12)*(1+$D120),0) -> 10000 | I120: =IF(I$4>=$E120,($C120/12)*(1+$D120),0) -> 10000 | J120: =IF(J$4>=$E120,($C120/12)*(1+$D120),0) -> 10000 | K120: =IF(K$4>=$E120,($C120/12)*(1+$D120),0) -> 10000 | L120: =IF(L$4>=$E120,($C120/12)*(1+$D120),0) -> 10000 | M120: =IF(M$4>=$E120,($C120/12)*(1+$D120),0) -> 10000 | N120: =IF(N$4>=$E120,($C120/12)*(1+$D120),0) -> 10000 | O120: =IF(O$4>=$E120,($C120/12)*(1+$D120),0) -> 10000 | ... BO120: =IF(BO$4>=$E120,($C120/12)*(1+$D120),0) -> 10000
B121: Person 2 | C121: 100000 | D121: 0.2 | E121: 43831 | H121: =IF(H$4>=$E121,($C121/12)*(1+$D121),0) -> 10000 | I121: =IF(I$4>=$E121,($C121/12)*(1+$D121),0) -> 10000 | J121: =IF(J$4>=$E121,($C121/12)*(1+$D121),0) -> 10000 | K121: =IF(K$4>=$E121,($C121/12)*(1+$D121),0) -> 10000 | L121: =IF(L$4>=$E121,($C121/12)*(1+$D121),0) -> 10000 | M121: =IF(M$4>=$E121,($C121/12)*(1+$D121),0) -> 10000 | N121: =IF(N$4>=$E121,($C121/12)*(1+$D121),0) -> 10000 | O121: =IF(O$4>=$E121,($C121/12)*(1+$D121),0) -> 10000 | ... BO121: =IF(BO$4>=$E121,($C121/12)*(1+$D121),0) -> 10000
...

Sheet Financials
B1: Year Counter | F1: 1 | G1: 1 | H1: 1 | I1: 1 | J1: 1 | K1: 1 | L1: 1 | M1: 1 | N1: 1 | O1: 1 | P1: 1 | Q1: 1 | R1: =F1+1 -> 2 | S1: =G1+1 -> 2 | T1: =H1+1 -> 2 | U1: =I1+1 -> 2 | V1: =J1+1 -> 2 | W1: =K1+1 -> 2 | X1: =L1+1 -> 2 | Y1: =M1+1 -> 2 | ... BM1: =BA1+1 -> 5
B2: Year | F2: =YEAR(F4) -> 2026 | G2: =YEAR(G4) -> 2026 | H2: =YEAR(H4) -> 2026 | I2: =YEAR(I4) -> 2026 | J2: =YEAR(J4) -> 2026 | K2: =YEAR(K4) -> 2026 | L2: =YEAR(L4) -> 2026 | M2: =YEAR(M4) -> 2026 | ... BM2: =YEAR(BM4) -> 2031
B3: Month Counter | F3: 1 | G3: =F3+1 -> 2 | H3: =G3+1 -> 3 | I3: =H3+1 -> 4 | J3: =I3+1 -> 5 | K3: =J3+1 -> 6 | L3: =K3+1 -> 7 | M3: =L3+1 -> 8 | N3: =M3+1 -> 9 | ... BM3: =BL3+1 -> 60
B4: Date | F4: =Assumptions!H4 -> 46081 | G4: =EOMONTH(F4,1) -> 46112 | H4: =EOMONTH(G4,1) -> 46142 | I4: =EOMONTH(H4,1) -> 46173 | J4: =EOMONTH(I4,1) -> 46203 | K4: =EOMONTH(J4,1) -> 46234 | L4: =EOMONTH(K4,1) -> 46265 | M4: =EOMONTH(L4,1) -> 46295 | N4: =EOMONTH(M4,1) -> 46326 | ... BM4: =EOMONTH(BL4,1) -> 47879
B6: Income Statement:
B8: Revenue | F8: =sum(F9:F11) -> 12037.5 | G8: =sum(G9:G11) -> 24030.256 | H8: =sum(H9:H11) -> 35708.073 | I8: =sum(I9:I11) -> 47096.061 | J8: =sum(J9:J11) -> 58223.02 | K8: =sum(K9:K11) -> 69117.095 | L8: =sum(L9:L11) -> 79805.783 | M8: =sum(M9:M11) -> 90315.995 | ... BM8: =sum(BM9:BM11) -> 297176.97
B9: =Assumptions!B75 -> Per Unit Monthly SaaS Tier 1 | F9: =Assumptions!H86 -> 2675 | G9: =Assumptions!I86 -> 5545.4438 | H9: =Assumptions!J86 -> 8553.645 | I9: =Assumptions!K86 -> 11705.446 | J9: =Assumptions!L86 -> 15008.027 | K9: =Assumptions!M86 -> 18468.943 | L9: =Assumptions!N86 -> 22096.13 | M9: =Assumptions!O86 -> 25897.916 | ... BN9: =Assumptions!BP86
B10: =Assumptions!B88 -> Per Unit Monthly SaaS Tier 2 | F10: =Assumptions!H99 -> 4012.5 | G10: =Assumptions!I99 -> 7922.0625 | H10: =Assumptions!J99 -> 11637.612 | I10: =Assumptions!K99 -> 15167.406 | J10: =Assumptions!L99 -> 18520.711 | K10: =Assumptions!M99 -> 21706.351 | L10: =Assumptions!N99 -> 24732.708 | M10: =Assumptions!O99 -> 27607.748 | ... BN10: =Assumptions!BP99
B11: =Assumptions!B101 -> Per Unit Monthly SaaS Tier 3 | F11: =Assumptions!H112 -> 5350 | G11: =Assumptions!I112 -> 10562.75 | H11: =Assumptions!J112 -> 15516.816 | I11: =Assumptions!K112 -> 20223.208 | J11: =Assumptions!L112 -> 24694.282 | K11: =Assumptions!M112 -> 28941.801 | L11: =Assumptions!N112 -> 32976.944 | M11: =Assumptions!O112 -> 36810.331 | ... BN11: =Assumptions!BP112
B13: COGS | F13: =Assumptions!H157 -> 4213.125 | G13: =Assumptions!I157 -> 8410.5897 | H13: =Assumptions!J157 -> 12497.826 | I13: =Assumptions!K157 -> 16483.621 | J13: =Assumptions!L157 -> 20378.057 | K13: =Assumptions!M157 -> 24190.983 | L13: =Assumptions!N157 -> 27932.024 | M13: =Assumptions!O157 -> 31610.598 | ... BM13: =Assumptions!BO157 -> 104011.94
B15: Gross Profit | F15: =F8-F13 -> 7824.375 | G15: =G8-G13 -> 15619.667 | H15: =H8-H13 -> 23210.248 | I15: =I8-I13 -> 30612.439 | J15: =J8-J13 -> 37844.963 | K15: =K8-K13 -> 44926.112 | L15: =L8-L13 -> 51873.759 | M15: =M8-M13 -> 58705.397 | ... BM15: =BM8-BM13 -> 193165.03
B16: Gross Margin | F16: =F15/F8 -> 0.65 | G16: =G15/G8 -> 0.65 | H16: =H15/H8 -> 0.65 | I16: =I15/I8 -> 0.65 | J16: =J15/J8 -> 0.65 | K16: =K15/K8 -> 0.65 | L16: =L15/L8 -> 0.65 | M16: =M15/M8 -> 0.65 | ... BM16: =BM15/BM8 -> 0.65
B18: Operating Expenses
B19: Salaries & Benefits | F19: =SUM(Assumptions!H120:H144) -> 202000 | G19: =SUM(Assumptions!I120:I144) -> 202000 | H19: =SUM(Assumptions!J120:J144) -> 202000 | I19: =SUM(Assumptions!K120:K144) -> 202000 | J19: =SUM(Assumptions!L120:L144) -> 202000 | K19: =SUM(Assumptions!M120:M144) -> 202000 | L19: =SUM(Assumptions!N120:N144) -> 202000 | M19: =SUM(Assumptions!O120:O144) -> 202000 | ... BM19: =SUM(Assumptions!BO120:BO144) -> 202000
B20: =Assumptions!B159 -> General & Admin | F20: =sum(Assumptions!H160:H167) -> 20000 | G20: =sum(Assumptions!I160:I167) -> 20000 | H20: =sum(Assumptions!J160:J167) -> 20000 | I20: =sum(Assumptions!K160:K167) -> 20000 | J20: =sum(Assumptions!L160:L167) -> 20000 | K20: =sum(Assumptions!M160:M167) -> 20000 | L20: =sum(Assumptions!N160:N167) -> 20000 | M20: =sum(Assumptions!O160:O167) -> 20000 | ... BM20: =sum(Assumptions!BO160:BO167) -> 20000
B21: =Assumptions!B170 -> Sales & Marketing | F21: =sum(Assumptions!H171:H172) -> 10963 | G21: =sum(Assumptions!I171:I172) -> 11922.421 | H21: =sum(Assumptions!J171:J172) -> 12856.646 | I21: =sum(Assumptions!K171:K172) -> 13767.685 | J21: =sum(Assumptions!L171:L172) -> 14657.842 | K21: =sum(Assumptions!M171:M172) -> 15529.368 | L21: =sum(Assumptions!N171:N172) -> 16384.463 | M21: =sum(Assumptions!O171:O172) -> 17225.28 | ... BM21: =sum(Assumptions!BO171:BO172) -> 33774.157
B22: =Assumptions!B175 -> Professional Fees | F22: =SUM(Assumptions!H176:H178) -> 4000 | G22: =SUM(Assumptions!I176:I178) -> 4000 | H22: =SUM(Assumptions!J176:J178) -> 4000 | I22: =SUM(Assumptions!K176:K178) -> 4000 | J22: =SUM(Assumptions!L176:L178) -> 4000 | K22: =SUM(Assumptions!M176:M178) -> 4000 | L22: =SUM(Assumptions!N176:N178) -> 4000 | M22: =SUM(Assumptions!O176:O178) -> 4000 | ... BM22: =SUM(Assumptions!BO176:BO178) -> 4000
B23: =Assumptions!B181 -> Other | F23: =Assumptions!H182 -> 1203.75 | G23: =Assumptions!I182 -> 2403.0256 | H23: =Assumptions!J182 -> 3570.8073 | I23: =Assumptions!K182 -> 4709.6061 | J23: =Assumptions!L182 -> 5822.302 | K23: =Assumptions!M182 -> 6911.7095 | L23: =Assumptions!N182 -> 7980.5783 | M23: =Assumptions!O182 -> 9031.5995 | ... BM23: =Assumptions!BO182 -> 29717.697
B24: Total Operating Expenses | F24: =SUM(F19:F23) -> 238166.75 | G24: =SUM(G19:G23) -> 240325.45 | H24: =SUM(H19:H23) -> 242427.45 | I24: =SUM(I19:I23) -> 244477.29 | J24: =SUM(J19:J23) -> 246480.14 | K24: =SUM(K19:K23) -> 248441.08 | L24: =SUM(L19:L23) -> 250365.04 | M24: =SUM(M19:M23) -> 252256.88 | ... BM24: =SUM(BM19:BM23) -> 289491.85
B26: EBITDA | F26: =F15-F24 -> -230342.38 | G26: =G15-G24 -> -224705.78 | H26: =H15-H24 -> -219217.21 | I26: =I15-I24 -> -213864.85 | J26: =J15-J24 -> -208635.18 | K26: =K15-K24 -> -203514.97 | L26: =L15-L24 -> -198491.28 | M26: =M15-M24 -> -193551.48 | ... BM26: =BM15-BM24 -> -96326.826
B27: Depreciation | F27: =SUM(Assumptions!H203:H206)-sum(Assumptions!E203:E206) -> 0 | G27: =SUM(Assumptions!I203:I206)-sum(Assumptions!H203:H206) -> 0 | H27: =SUM(Assumptions!J203:J206)-sum(Assumptions!I203:I206) -> 0 | I27: =SUM(Assumptions!K203:K206)-sum(Assumptions!J203:J206) -> 0 | J27: =SUM(Assumptions!L203:L206)-sum(Assumptions!K203:K206) -> 0 | K27: =SUM(Assumptions!M203:M206)-sum(Assumptions!L203:L206) -> 0 | L27: =SUM(Assumptions!N203:N206)-sum(Assumptions!M203:M206) -> 0 | M27: =SUM(Assumptions!O203:O206)-sum(Assumptions!N203:N206) -> 0 | N27: =SUM(Assumptions!P203:P206)-sum(Assumptions!O203:O206) -> 0 | ... BM27: =SUM(Assumptions!BO203:BO206)-sum(Assumptions!BN203:BN206) -> 0
B28: EBIT | F28: =F26-F27 -> -230342.38 | G28: =G26-G27 -> -224705.78 | H28: =H26-H27 -> -219217.21 | I28: =I26-I27 -> -213864.85 | J28: =J26-J27 -> -208635.18 | K28: =K26-K27 -> -203514.97 | L28: =L26-L27 -> -198491.28 | M28: =M26-M27 -> -193551.48 | ... BM28: =BM26-BM27 -> -96326.826
B29: Taxes | F29: =IF(F28>0,F28*Assumptions!$C$184,0) -> 0 | G29: =IF(G28>0,G28*Assumptions!$C$184,0) -> 0 | H29: =IF(H28>0,H28*Assumptions!$C$184,0) -> 0 | I29: =IF(I28>0,I28*Assumptions!$C$184,0) -> 0 | J29: =IF(J28>0,J28*Assumptions!$C$184,0) -> 0 | K29: =IF(K28>0,K28*Assumptions!$C$184,0) -> 0 | L29: =IF(L28>0,L28*Assumptions!$C$184,0) -> 0 | M29: =IF(M28>0,M28*Assumptions!$C$184,0) -> 0 | ... BM29: =IF(BM28>0,BM28*Assumptions!$C$184,0) -> 0
B30: Net Income | F30: =F28-F29 -> -230342.38 | G30: =G28-G29 -> -224705.78 | H30: =H28-H29 -> -219217.21 | I30: =I28-I29 -> -213864.85 | J30: =J28-J29 -> -208635.18 | K30: =K28-K29 -> -203514.97 | L30: =L28-L29 -> -198491.28 | M30: =M28-M29 -> -193551.48 | ... BM30: =BM28-BM29 -> -96326.826
B31: Net Margin | F31: =F30/F8 -> -19.1354 | G31: =G30/G8 -> -9.3509523 | H31: =H30/H8 -> -6.1391496 | I31: =I30/I8 -> -4.5410348 | J31: =J30/J8 -> -3.5833796 | K31: =K30/K8 -> -2.9444953 | L31: =L30/L8 -> -2.4871792 | M31: =M30/M8 -> -2.1430477 | ... BM31: =BM30/BM8 -> -0.32413961
B33: Balance Sheet:
B35: Assets
B36: Current Assets
B37: Cash | F37: =F80 -> 283828.81 | G37: =G80 -> 56304.735 | H37: =H80 -> -165656.76 | I37: =I80 -> -382197.79 | J37: =J80 -> -593447.8 | K37: =K80 -> -799522.88 | L37: =L80 -> -1000526 | M37: =M80 -> -1196547.4 | ... BM37: =BM80 -> -7660701.2
B38: Accounts Receivable | F38: =Assumptions!H194 -> 6018.75 | G38: =Assumptions!I194 -> 12015.128 | H38: =Assumptions!J194 -> 17854.037 | I38: =Assumptions!K194 -> 23548.03 | J38: =Assumptions!L194 -> 29111.51 | K38: =Assumptions!M194 -> 34558.548 | L38: =Assumptions!N194 -> 39902.891 | M38: =Assumptions!O194 -> 45157.997 | ... BM38: =Assumptions!BO194 -> 148588.48
B39: Total Current Assets | F39: =SUM(F37:F38) -> 289847.56 | G39: =SUM(G37:G38) -> 68319.863 | H39: =SUM(H37:H38) -> -147802.72 | I39: =SUM(I37:I38) -> -358649.76 | J39: =SUM(J37:J38) -> -564336.29 | K39: =SUM(K37:K38) -> -764964.33 | L39: =SUM(L37:L38) -> -960623.11 | M39: =SUM(M37:M38) -> -1151389.4 | ... BM39: =SUM(BM37:BM38) -> -7512112.7
B41: Fixed Assets | F41: =SUM(Assumptions!H196:H200) -> 0 | G41: =SUM(Assumptions!I196:I200) -> 0 | H41: =SUM(Assumptions!J196:J200) -> 0 | I41: =SUM(Assumptions!K196:K200) -> 0 | J41: =SUM(Assumptions!L196:L200) -> 0 | K41: =SUM(Assumptions!M196:M200) -> 0 | L41: =SUM(Assumptions!N196:N200) -> 0 | M41: =SUM(Assumptions!O196:O200) -> 0 | ... BM41: =SUM(Assumptions!BO196:BO200) -> 0
B42: Accumulated Depreciation | F42: =-SUM(Assumptions!H203:H206) -> 0 | G42: =-SUM(Assumptions!I203:I206) -> 0 | H42: =-SUM(Assumptions!J203:J206) -> 0 | I42: =-SUM(Assumptions!K203:K206) -> 0 | J42: =-SUM(Assumptions!L203:L206) -> 0 | K42: =-SUM(Assumptions!M203:M206) -> 0 | L42: =-SUM(Assumptions!N203:N206) -> 0 | M42: =-SUM(Assumptions!O203:O206) -> 0 | ... BM42: =-SUM(Assumptions!BO203:BO206) -> 0
B43: Total Assets | F43: =SUM(F39:F42) -> 289847.56 | G43: =SUM(G39:G42) -> 68319.863 | H43: =SUM(H39:H42) -> -147802.72 | I43: =SUM(I39:I42) -> -358649.76 | J43: =SUM(J39:J42) -> -564336.29 | K43: =SUM(K39:K42) -> -764964.33 | L43: =SUM(L39:L42) -> -960623.11 | M43: =SUM(M39:M42) -> -1151389.4 | ... BM43: =SUM(BM39:BM42) -> -7512112.7
B45: Liabilities & Owner's Equity
B46: Liabilities
B47: Accounts payable | F47: =Assumptions!H210 -> 20189.938 | G47: =Assumptions!I210 -> 23368.018 | H47: =Assumptions!J210 -> 26462.639 | I47: =Assumptions!K210 -> 29480.456 | J47: =Assumptions!L210 -> 32429.1 | K47: =Assumptions!M210 -> 35316.03 | L47: =Assumptions!N210 -> 38148.532 | M47: =Assumptions!O210 -> 40933.739 | ... BM47: =Assumptions!BO210 -> 95751.896
B48: Total Liabilities | F48: =F47 -> 20189.938 | G48: =G47 -> 23368.018 | H48: =H47 -> 26462.639 | I48: =I47 -> 29480.456 | J48: =J47 -> 32429.1 | K48: =K47 -> 35316.03 | L48: =L47 -> 38148.532 | M48: =M47 -> 40933.739 | ... BM48: =BM47 -> 95751.896
B50: Equity | E50: Prev Cash
B51: Paid In Capital | E51: =Assumptions!C192 -> 500000 | F51: =E51 -> 500000 | G51: =Assumptions!I224+$E51 -> 500000 | H51: =Assumptions!J224+$E51 -> 500000 | I51: =Assumptions!K224+$E51 -> 500000 | J51: =Assumptions!L224+$E51 -> 500000 | K51: =Assumptions!M224+$E51 -> 500000 | L51: =Assumptions!N224+$E51 -> 500000 | M51: =Assumptions!O224+$E51 -> 500000 | N51: =Assumptions!P224+$E51 -> 500000 | ... BM51: =Assumptions!BO224+$E51 -> 500000
B52: Accumulated Retained Earnings | F52: =E52+F30 -> -230342.38 | G52: =F52+G30 -> -455048.15 | H52: =G52+H30 -> -674265.36 | I52: =H52+I30 -> -888130.21 | J52: =I52+J30 -> -1096765.4 | K52: =J52+K30 -> -1300280.4 | L52: =K52+L30 -> -1498771.6 | M52: =L52+M30 -> -1692323.1 | ... BM52: =BL52+BM30 -> -8107864.6
B53: Total Equity | F53: =SUM(F51:F52) -> 269657.62 | G53: =SUM(G51:G52) -> 44951.845 | H53: =SUM(H51:H52) -> -174265.36 | I53: =SUM(I51:I52) -> -388130.21 | J53: =SUM(J51:J52) -> -596765.39 | K53: =SUM(K51:K52) -> -800280.36 | L53: =SUM(L51:L52) -> -998771.64 | M53: =SUM(M51:M52) -> -1192323.1 | ... BM53: =SUM(BM51:BM52) -> -7607864.6
B55: Total Liabilities & Owner's Equity | F55: =F53+F48 -> 289847.56 | G55: =G53+G48 -> 68319.863 | H55: =H53+H48 -> -147802.72 | I55: =I53+I48 -> -358649.76 | J55: =J53+J48 -> -564336.29 | K55: =K53+K48 -> -764964.33 | L55: =L53+L48 -> -960623.11 | M55: =M53+M48 -> -1151389.4 | ... BM55: =BM53+BM48 -> -7512112.7
B57: Balance Check | F57: =IF(ABS(F55-F43)>0.001,"ERROR","OK") -> OK | G57: =IF(ABS(G55-G43)>0.001,"ERROR","OK") -> OK | H57: =IF(ABS(H55-H43)>0.001,"ERROR","OK") -> OK | I57: =IF(ABS(I55-I43)>0.001,"ERROR","OK") -> OK | J57: =IF(ABS(J55-J43)>0.001,"ERROR","OK") -> OK | K57: =IF(ABS(K55-K43)>0.001,"ERROR","OK") -> OK | L57: =IF(ABS(L55-L43)>0.001,"ERROR","OK") -> OK | M57: =IF(ABS(M55-M43)>0.001,"ERROR","OK") -> OK | ... BM57: =IF(ABS(BM55-BM43)>0.001,"ERROR","OK") -> OK
B59: Statement of Cash Flows:
B61: Operating Cash Flows
B62: Net Income | F62: =F52-E52 -> -230342.38 | G62: =G52-F52 -> -224705.78 | H62: =H52-G52 -> -219217.21 | I62: =I52-H52 -> -213864.85 | J62: =J52-I52 -> -208635.18 | K62: =K52-J52 -> -203514.97 | L62: =L52-K52 -> -198491.28 | M62: =M52-L52 -> -193551.48 | ... BM62: =BM52-BL52 -> -96326.826
B63: Depreciation | F63: =E42-F42 -> 0 | G63: =F42-G42 -> 0 | H63: =G42-H42 -> 0 | I63: =H42-I42 -> 0 | J63: =I42-J42 -> 0 | K63: =J42-K42 -> 0 | L63: =K42-L42 -> 0 | M63: =L42-M42 -> 0 | ... BM63: =BL42-BM42 -> 0
B64: Change in Accounts Receivable | F64: =E38-F38 -> -6018.75 | G64: =F38-G38 -> -5996.3781 | H64: =G38-H38 -> -5838.9086 | I64: =H38-I38 -> -5693.9937 | J64: =I38-J38 -> -5563.4794 | K64: =J38-K38 -> -5447.0378 | L64: =K38-L38 -> -5344.3436 | M64: =L38-M38 -> -5255.1061 | ... BM64: =BL38-BM38 -> -378.19705
B65: Change in Accounts Payable | F65: =F47-E47 -> 20189.938 | G65: =G47-F47 -> 3178.0804 | H65: =H47-G47 -> 3094.6215 | I65: =I47-H47 -> 3017.8166 | J65: =J47-I47 -> 2948.6441 | K65: =K47-J47 -> 2886.9301 | L65: =L47-K47 -> 2832.5021 | M65: =M47-L47 -> 2785.2062 | ... BM65: =BM47-BL47 -> 200.44444
B66: Total Operating Cash Flows | F66: =SUM(F62:F65) -> -216171.19 | G66: =SUM(G62:G65) -> -227524.08 | H66: =SUM(H62:H65) -> -221961.49 | I66: =SUM(I62:I65) -> -216541.03 | J66: =SUM(J62:J65) -> -211250.02 | K66: =SUM(K62:K65) -> -206075.07 | L66: =SUM(L62:L65) -> -201003.12 | M66: =SUM(M62:M65) -> -196021.38 | ... BM66: =SUM(BM62:BM65) -> -96504.578
B68: Investing Cash Flows
B69: Changes in Fixed Assets | F69: =E41-F41 -> 0 | G69: =F41-G41 -> 0 | H69: =G41-H41 -> 0 | I69: =H41-I41 -> 0 | J69: =I41-J41 -> 0 | K69: =J41-K41 -> 0 | L69: =K41-L41 -> 0 | M69: =L41-M41 -> 0 | ... BM69: =BL41-BM41 -> 0
B70: Total Investing Cash Flows | F70: =F69 -> 0 | G70: =G69 -> 0 | H70: =H69 -> 0 | I70: =I69 -> 0 | J70: =J69 -> 0 | K70: =K69 -> 0 | L70: =L69 -> 0 | M70: =M69 -> 0 | ... BM70: =BM69 -> 0
B72: Financing Cash Flows
B73: Changes in Paid in Capital | F73: =F51-E51 -> 0 | G73: =G51-F51 -> 0 | H73: =H51-G51 -> 0 | I73: =I51-H51 -> 0 | J73: =J51-I51 -> 0 | K73: =K51-J51 -> 0 | L73: =L51-K51 -> 0 | M73: =M51-L51 -> 0 | ... BM73: =BM51-BL51 -> 0
B74: Total Financing Cash Flows | F74: =F73 -> 0 | G74: =G73 -> 0 | H74: =H73 -> 0 | I74: =I73 -> 0 | J74: =J73 -> 0 | K74: =K73 -> 0 | L74: =L73 -> 0 | M74: =M73 -> 0 | ... BM74: =BM73 -> 0
B76: Beginning Cash | F76: =Assumptions!C192 -> 500000 | G76: =F80 -> 283828.81 | H76: =G80 -> 56304.735 | I76: =H80 -> -165656.76 | J76: =I80 -> -382197.79 | K76: =J80 -> -593447.8 | L76: =K80 -> -799522.88 | M76: =L80 -> -1000526 | N76: =M80 -> -1196547.4 | ... BM76: =BL80 -> -7564196.6
B78: Change in Cash | F78: =F74+F70+F66 -> -216171.19 | G78: =G74+G70+G66 -> -227524.08 | H78: =H74+H70+H66 -> -221961.49 | I78: =I74+I70+I66 -> -216541.03 | J78: =J74+J70+J66 -> -211250.02 | K78: =K74+K70+K66 -> -206075.07 | L78: =L74+L70+L66 -> -201003.12 | M78: =M74+M70+M66 -> -196021.38 | ... BM78: =BM74+BM70+BM66 -> -96504.578
B80: Ending Cash | F80: =F76+F78 -> 283828.81 | G80: =G76+G78 -> 56304.735 | H80: =H76+H78 -> -165656.76 | I80: =I76+I78 -> -382197.79 | J80: =J76+J78 -> -593447.8 | K80: =K76+K78 -> -799522.88 | L80: =L76+L78 -> -1000526 | M80: =M76+M78 -> -1196547.4 | ... BM80: =BM76+BM78 -> -7660701.2
B1007: Forecastr Template
