Workbook

Sheet Overview
C2: YOUR LOGO HERE
C4: Financial Model
G5: Welcome! This template was created by Forecastr's team of Financial Analysts and Fractional CFOs to help our fellow founders create better financial models for their startups and small businesses. Forecastr is an out-of-the-box finance function for your business. We provide the tools and support you need to create an investor-grade financial model. Our analysts work with you every step of the way to build a model that's customized to fit your business, keep it up to date, and generate insightful reports to share with your investors and other stakeholders. ✔ Impress your investors ✔ Hit your growth targets ✔ Never run out of cash
C7: Your Website Link Here
C10: Table of Contents
C12: Assumptions
C14: Financials
I18: SCHEDULE A MODELING SESSION WITH A MEMBER OF OUR TEAM

Sheet Assumptions
B1: Year Counter | T1: 1 | U1: 1 | V1: 1 | W1: 1 | X1: 1 | Y1: 1 | Z1: 1 | AA1: 1 | AB1: 1 | AC1: 1 | AD1: 1 | AE1: 1 | AF1: =T1+1 -> 2 | AG1: =U1+1 -> 2 | AH1: =V1+1 -> 2 | AI1: =W1+1 -> 2 | AJ1: =X1+1 -> 2 | AK1: =Y1+1 -> 2 | AL1: =Z1+1 -> 2 | AM1: =AA1+1 -> 2 | ... CA1: =BO1+1 -> 5
B2: Year | T2: =YEAR(T4) -> 2024 | U2: =YEAR(U4) -> 2024 | V2: =YEAR(V4) -> 2024 | W2: =YEAR(W4) -> 2024 | X2: =YEAR(X4) -> 2024 | Y2: =YEAR(Y4) -> 2024 | Z2: =YEAR(Z4) -> 2024 | AA2: =YEAR(AA4) -> 2024 | ... CA2: =YEAR(CA4) -> 2028
B3: Month Counter | T3: 1 | U3: =T3+1 -> 2 | V3: =U3+1 -> 3 | W3: =V3+1 -> 4 | X3: =W3+1 -> 5 | Y3: =X3+1 -> 6 | Z3: =Y3+1 -> 7 | AA3: =Z3+1 -> 8 | AB3: =AA3+1 -> 9 | ... CA3: =BZ3+1 -> 60
B4: Date | T4: 45292 | U4: =EOMONTH(T4,1) -> 45351 | V4: =EOMONTH(U4,1) -> 45382 | W4: =EOMONTH(V4,1) -> 45412 | X4: =EOMONTH(W4,1) -> 45443 | Y4: =EOMONTH(X4,1) -> 45473 | Z4: =EOMONTH(Y4,1) -> 45504 | AA4: =EOMONTH(Z4,1) -> 45535 | AB4: =EOMONTH(AA4,1) -> 45565 | ... CA4: =EOMONTH(BZ4,1) -> 47118
B6: Customer Acquisition:
B10: Regular Schools Sales | D10: Start Value | E10: MoM Growth
B11: Sales Leads | D11: 10 | E11: 0.02 | T11: =D11 -> 10 | U11: =T11*(1+$E$11) -> 10.2 | V11: =U11*(1+$E$11) -> 10.404 | W11: =V11*(1+$E$11) -> 10.61208 | X11: =W11*(1+$E$11) -> 10.824322 | Y11: =X11*(1+$E$11) -> 11.040808 | Z11: =Y11*(1+$E$11) -> 11.261624 | AA11: =Z11*(1+$E$11) -> 11.486857 | AB11: =AA11*(1+$E$11) -> 11.716594 | ... CA11: =BZ11*(1+$E$11) -> 32.166969
B12: Sales Cycle | D12: 2 | T12: =D12 -> 2 | U12: =T12 -> 2 | V12: =U12 -> 2 | W12: =V12 -> 2 | X12: =W12 -> 2 | Y12: =X12 -> 2 | Z12: =Y12 -> 2 | AA12: =Z12 -> 2 | AB12: =AA12 -> 2 | ... CA12: =BZ12 -> 2
B13: Conversion Rate | D13: 0.25 | T13: =D13 -> 0.25 | U13: =T13 -> 0.25 | V13: =U13 -> 0.25 | W13: =V13 -> 0.25 | X13: =W13 -> 0.25 | Y13: =X13 -> 0.25 | Z13: =Y13 -> 0.25 | AA13: =Z13 -> 0.25 | AB13: =AA13 -> 0.25 | ... CA13: =BZ13 -> 0.25
B14: New Regular Schools | T14: =IFERROR(offset(T11,,-T12+1)*T13,0) -> 0 | U14: =IFERROR(offset(U11,,-U12+1)*U13,0) -> 2.5 | V14: =IFERROR(offset(V11,,-V12+1)*V13,0) -> 2.55 | W14: =IFERROR(offset(W11,,-W12+1)*W13,0) -> 2.601 | X14: =IFERROR(offset(X11,,-X12+1)*X13,0) -> 2.65302 | Y14: =IFERROR(offset(Y11,,-Y12+1)*Y13,0) -> 2.7060804 | Z14: =IFERROR(offset(Z11,,-Z12+1)*Z13,0) -> 2.760202 | AA14: =IFERROR(offset(AA11,,-AA12+1)*AA13,0) -> 2.815406 | ... CA14: =IFERROR(offset(CA11,,-CA12+1)*CA13,0) -> 7.8840609
B16: Large Schools Sales | D16: Start Value | E16: MoM Growth
B17: Sales Leads | D17: 10 | E17: 0.02 | T17: =D17 -> 10 | U17: =T17*(1+$E$17) -> 10.2 | V17: =U17*(1+$E$17) -> 10.404 | W17: =V17*(1+$E$17) -> 10.61208 | X17: =W17*(1+$E$17) -> 10.824322 | Y17: =X17*(1+$E$17) -> 11.040808 | Z17: =Y17*(1+$E$17) -> 11.261624 | AA17: =Z17*(1+$E$17) -> 11.486857 | AB17: =AA17*(1+$E$17) -> 11.716594 | ... CA17: =BZ17*(1+$E$17) -> 32.166969
B18: Sales Cycle | D18: 6 | T18: =D18 -> 6 | U18: =T18 -> 6 | V18: =U18 -> 6 | W18: =V18 -> 6 | X18: =W18 -> 6 | Y18: =X18 -> 6 | Z18: =Y18 -> 6 | AA18: =Z18 -> 6 | AB18: =AA18 -> 6 | ... CA18: =BZ18 -> 6
B19: Conversion Rate | D19: 0.1 | T19: =D19 -> 0.1 | U19: =T19 -> 0.1 | V19: =U19 -> 0.1 | W19: =V19 -> 0.1 | X19: =W19 -> 0.1 | Y19: =X19 -> 0.1 | Z19: =Y19 -> 0.1 | AA19: =Z19 -> 0.1 | AB19: =AA19 -> 0.1 | ... CA19: =BZ19 -> 0.1
B20: New Large Schools | T20: =IFERROR(offset(T17,,-T18+1)*T19,0) -> 0 | U20: =IFERROR(offset(U17,,-U18+1)*U19,0) -> 0 | V20: =IFERROR(offset(V17,,-V18+1)*V19,0) -> 0 | W20: =IFERROR(offset(W17,,-W18+1)*W19,0) -> 0 | X20: =IFERROR(offset(X17,,-X18+1)*X19,0) -> 0 | Y20: =IFERROR(offset(Y17,,-Y18+1)*Y19,0) -> 1 | Z20: =IFERROR(offset(Z17,,-Z18+1)*Z19,0) -> 1.02 | AA20: =IFERROR(offset(AA17,,-AA18+1)*AA19,0) -> 1.0404 | ... CA20: =IFERROR(offset(CA17,,-CA18+1)*CA19,0) -> 2.9134614
B23: Total New Schools | T23: =sum(T20,T14) -> 0 | U23: =sum(U20,U14) -> 2.5 | V23: =sum(V20,V14) -> 2.55 | W23: =sum(W20,W14) -> 2.601 | X23: =sum(X20,X14) -> 2.65302 | Y23: =sum(Y20,Y14) -> 3.7060804 | Z23: =sum(Z20,Z14) -> 3.780202 | AA23: =sum(AA20,AA14) -> 3.855806 | ... CA23: =sum(CA20,CA14) -> 10.797522
B25: Revenue - Per Unit Annual SaaS:
B27: Regular School Licenses
B28: New Regular Schools | T28: =T14 -> 0 | U28: =U14 -> 2.5 | V28: =V14 -> 2.55 | W28: =W14 -> 2.601 | X28: =X14 -> 2.65302 | Y28: =Y14 -> 2.7060804 | Z28: =Z14 -> 2.760202 | AA28: =AA14 -> 2.815406 | ... CA28: =CA14 -> 7.8840609
B29: Billed Subscriptions | H29: 0 | I29: 0 | J29: 0 | K29: 0 | L29: 0 | M29: 0 | N29: 0 | O29: 0 | P29: 0 | Q29: 0 | R29: 0 | T29: =T28+T34 -> 0 | U29: =U28+U34 -> 2.5 | V29: =V28+V34 -> 2.55 | W29: =W28+W34 -> 2.601 | X29: =X28+X34 -> 2.65302 | Y29: =Y28+Y34 -> 2.7060804 | Z29: =Z28+Z34 -> 2.760202 | AA29: =AA28+AA34 -> 2.815406 | ... CA29: =CA28+CA34 -> 19.221469
B30: Subscriptions Available for Renewal | T30: =H29 -> 0 | U30: =I29 -> 0 | V30: =J29 -> 0 | W30: =K29 -> 0 | X30: =L29 -> 0 | Y30: =M29 -> 0 | Z30: =N29 -> 0 | AA30: =O29 -> 0 | ... CA30: =BO29 -> 14.171761
B31: Subscriptions In-between Billing Cycles | T31: =T36-T30 -> 0 | U31: =U36-U30 -> 0 | V31: =V36-V30 -> 2.5 | W31: =W36-W30 -> 5.05 | X31: =X36-X30 -> 7.651 | Y31: =Y36-Y30 -> 10.30402 | Z31: =Z36-Z30 -> 13.0101 | AA31: =AA36-AA30 -> 15.770302 | ... CA31: =CA36-CA30 -> 187.11368
B32: Annual Churn Rate | D32: 0.2 | T32: =D32 -> 0.2 | U32: =T32 -> 0.2 | V32: =U32 -> 0.2 | W32: =V32 -> 0.2 | X32: =W32 -> 0.2 | Y32: =X32 -> 0.2 | Z32: =Y32 -> 0.2 | AA32: =Z32 -> 0.2 | AB32: =AA32 -> 0.2 | ... CA32: =BZ32 -> 0.2
B33: Churned Licenses | T33: =T30*T32 -> 0 | U33: =U30*U32 -> 0 | V33: =V30*V32 -> 0 | W33: =W30*W32 -> 0 | X33: =X30*X32 -> 0 | Y33: =Y30*Y32 -> 0 | Z33: =Z30*Z32 -> 0 | AA33: =AA30*AA32 -> 0 | ... CA33: =CA30*CA32 -> 2.8343521
B34: Renewed Licenses | T34: =T30-T33 -> 0 | U34: =U30-U33 -> 0 | V34: =V30-V33 -> 0 | W34: =W30-W33 -> 0 | X34: =X30-X33 -> 0 | Y34: =Y30-Y33 -> 0 | Z34: =Z30-Z33 -> 0 | AA34: =AA30-AA33 -> 0 | ... CA34: =CA30-CA33 -> 11.337408
B35: Total Regular School Licenses | T35: =T29+T31 -> 0 | U35: =U29+U31 -> 2.5 | V35: =V29+V31 -> 5.05 | W35: =W29+W31 -> 7.651 | X35: =X29+X31 -> 10.30402 | Y35: =Y29+Y31 -> 13.0101 | Z35: =Z29+Z31 -> 15.770302 | AA35: =AA29+AA31 -> 18.585708 | ... CA35: =CA29+CA31 -> 206.33515
B36: Previous Months Active Subsciptions | T36: =G35 | U36: =T35 -> 0 | V36: =U35 -> 2.5 | W36: =V35 -> 5.05 | X36: =W35 -> 7.651 | Y36: =X35 -> 10.30402 | Z36: =Y35 -> 13.0101 | AA36: =Z35 -> 15.770302 | AB36: =AA35 -> 18.585708 | ... CA36: =BZ35 -> 201.28544
B37: Average Students per School | D37: 30 | T37: =D37 -> 30 | U37: =T37 -> 30 | V37: =U37 -> 30 | W37: =V37 -> 30 | X37: =W37 -> 30 | Y37: =X37 -> 30 | Z37: =Y37 -> 30 | AA37: =Z37 -> 30 | AB37: =AA37 -> 30 | ... CA37: =BZ37 -> 30
B38: Total Students | T38: =T37*T29 -> 0 | U38: =U37*U29 -> 75 | V38: =V37*V29 -> 76.5 | W38: =W37*W29 -> 78.03 | X38: =X37*X29 -> 79.5906 | Y38: =Y37*Y29 -> 81.182412 | Z38: =Z37*Z29 -> 82.80606 | AA38: =AA37*AA29 -> 84.462181 | ... CA38: =CA37*CA29 -> 576.64408
B39: Average Price per Student | D39: 72 | T39: =D39 -> 72 | U39: =T39 -> 72 | V39: =U39 -> 72 | W39: =V39 -> 72 | X39: =W39 -> 72 | Y39: =X39 -> 72 | Z39: =Y39 -> 72 | AA39: =Z39 -> 72 | AB39: =AA39 -> 72 | ... CA39: =BZ39 -> 72
B40: Cash Collected | T40: =T38*T39 -> 0 | U40: =U38*U39 -> 5400 | V40: =V38*V39 -> 5508 | W40: =W38*W39 -> 5618.16 | X40: =X38*X39 -> 5730.5232 | Y40: =Y38*Y39 -> 5845.1337 | Z40: =Z38*Z39 -> 5962.0363 | AA40: =AA38*AA39 -> 6081.2771 | ... CA40: =CA38*CA39 -> 41518.374
B41: Revenue | T41: =(T39/12)*T35*T37 -> 0 | U41: =(U39/12)*U35*U37 -> 450 | V41: =(V39/12)*V35*V37 -> 909 | W41: =(W39/12)*W35*W37 -> 1377.18 | X41: =(X39/12)*X35*X37 -> 1854.7236 | Y41: =(Y39/12)*Y35*Y37 -> 2341.8181 | Z41: =(Z39/12)*Z35*Z37 -> 2838.6544 | AA41: =(AA39/12)*AA35*AA37 -> 3345.4275 | ... CA41: =(CA39/12)*CA35*CA37 -> 37140.327
B43: Large School Licenses
B44: New Large Schools | T44: =T20 -> 0 | U44: =U20 -> 0 | V44: =V20 -> 0 | W44: =W20 -> 0 | X44: =X20 -> 0 | Y44: =Y20 -> 1 | Z44: =Z20 -> 1.02 | AA44: =AA20 -> 1.0404 | ... CA44: =CA20 -> 2.9134614
B45: Billed Subscriptions | H45: 0 | I45: 0 | J45: 0 | K45: 0 | L45: 0 | M45: 0 | N45: 0 | O45: 0 | P45: 0 | Q45: 0 | R45: 0 | S45: 0 | T45: =T44+T50 -> 0 | U45: =U44+U50 -> 0 | V45: =V44+V50 -> 0 | W45: =W44+W50 -> 0 | X45: =X44+X50 -> 0 | Y45: =Y44+Y50 -> 1 | Z45: =Z44+Z50 -> 1.02 | AA45: =AA44+AA50 -> 1.0404 | ... CA45: =CA44+CA50 -> 7.1030666
B46: Subscriptions Available for Renewal | T46: =H45 -> 0 | U46: =I45 -> 0 | V46: =J45 -> 0 | W46: =K45 -> 0 | X46: =L45 -> 0 | Y46: =M45 -> 0 | Z46: =N45 -> 0 | AA46: =O45 -> 0 | ... CA46: =BO45 -> 5.2370065
B47: Subscriptions In-between Billing Cycles | T47: =T52-T46 -> 0 | U47: =U52-U46 -> 0 | V47: =V52-V46 -> 0 | W47: =W52-W46 -> 0 | X47: =X52-X46 -> 0 | Y47: =Y52-Y46 -> 0 | Z47: =Z52-Z46 -> 1 | AA47: =AA52-AA46 -> 2.02 | ... CA47: =CA52-CA46 -> 67.586001
B48: Annual Churn Rate | D48: 0.2 | T48: =D48 -> 0.2 | U48: =T48 -> 0.2 | V48: =U48 -> 0.2 | W48: =V48 -> 0.2 | X48: =W48 -> 0.2 | Y48: =X48 -> 0.2 | Z48: =Y48 -> 0.2 | AA48: =Z48 -> 0.2 | AB48: =AA48 -> 0.2 | ... CA48: =BZ48 -> 0.2
B49: Churned Licenses | T49: =T46*T48 -> 0 | U49: =U46*U48 -> 0 | V49: =V46*V48 -> 0 | W49: =W46*W48 -> 0 | X49: =X46*X48 -> 0 | Y49: =Y46*Y48 -> 0 | Z49: =Z46*Z48 -> 0 | AA49: =AA46*AA48 -> 0 | ... CA49: =CA46*CA48 -> 1.0474013
B50: Renewed Licenses | T50: =T46-T49 -> 0 | U50: =U46-U49 -> 0 | V50: =V46-V49 -> 0 | W50: =W46-W49 -> 0 | X50: =X46-X49 -> 0 | Y50: =Y46-Y49 -> 0 | Z50: =Z46-Z49 -> 0 | AA50: =AA46-AA49 -> 0 | ... CA50: =CA46-CA49 -> 4.1896052
B51: Total Regular School Licenses | T51: =T45+T47 -> 0 | U51: =U45+U47 -> 0 | V51: =V45+V47 -> 0 | W51: =W45+W47 -> 0 | X51: =X45+X47 -> 0 | Y51: =Y45+Y47 -> 1 | Z51: =Z45+Z47 -> 2.02 | AA51: =AA45+AA47 -> 3.0604 | ... CA51: =CA45+CA47 -> 74.689067
B52: Previous Months Active Subsciptions | T52: =G51 | U52: =T51 -> 0 | V52: =U51 -> 0 | W52: =V51 -> 0 | X52: =W51 -> 0 | Y52: =X51 -> 0 | Z52: =Y51 -> 1 | AA52: =Z51 -> 2.02 | AB52: =AA51 -> 3.0604 | ... CA52: =BZ51 -> 72.823007
B53: Average Students per School | D53: 60 | T53: =D53 -> 60 | U53: =T53 -> 60 | V53: =U53 -> 60 | W53: =V53 -> 60 | X53: =W53 -> 60 | Y53: =X53 -> 60 | Z53: =Y53 -> 60 | AA53: =Z53 -> 60 | AB53: =AA53 -> 60 | ... CA53: =BZ53 -> 60
B54: Total Students | T54: =T53*T45 -> 0 | U54: =U53*U45 -> 0 | V54: =V53*V45 -> 0 | W54: =W53*W45 -> 0 | X54: =X53*X45 -> 0 | Y54: =Y53*Y45 -> 60 | Z54: =Z53*Z45 -> 61.2 | AA54: =AA53*AA45 -> 62.424 | ... CA54: =CA53*CA45 -> 426.184
B55: Average Price per Student | D55: 72 | T55: =D55 -> 72 | U55: =T55 -> 72 | V55: =U55 -> 72 | W55: =V55 -> 72 | X55: =W55 -> 72 | Y55: =X55 -> 72 | Z55: =Y55 -> 72 | AA55: =Z55 -> 72 | AB55: =AA55 -> 72 | ... CA55: =BZ55 -> 72
B56: Cash Collected | T56: =T54*T55 -> 0 | U56: =U54*U55 -> 0 | V56: =V54*V55 -> 0 | W56: =W54*W55 -> 0 | X56: =X54*X55 -> 0 | Y56: =Y54*Y55 -> 4320 | Z56: =Z54*Z55 -> 4406.4 | AA56: =AA54*AA55 -> 4494.528 | ... CA56: =CA54*CA55 -> 30685.248
B57: Revenue | T57: =(T55/12)*T51*T53 -> 0 | U57: =(U55/12)*U51*U53 -> 0 | V57: =(V55/12)*V51*V53 -> 0 | W57: =(W55/12)*W51*W53 -> 0 | X57: =(X55/12)*X51*X53 -> 0 | Y57: =(Y55/12)*Y51*Y53 -> 360 | Z57: =(Z55/12)*Z51*Z53 -> 727.2 | AA57: =(AA55/12)*AA51*AA53 -> 1101.744 | ... CA57: =(CA55/12)*CA51*CA53 -> 26888.064
B59: Per Unit Annual SaaS Tier 3
B60: % of Total New Customers | D60: 0.2 | T60: =D60 -> 0.2 | U60: =T60 -> 0.2 | V60: =U60 -> 0.2 | W60: =V60 -> 0.2 | X60: =W60 -> 0.2 | Y60: =X60 -> 0.2 | Z60: =Y60 -> 0.2 | AA60: =Z60 -> 0.2 | AB60: =AA60 -> 0.2 | ... CA60: =BZ60 -> 0.2
B61: New Customers | T61: =T60*T$23 -> 0 | U61: =U60*U$23 -> 0.5 | V61: =V60*V$23 -> 0.51 | W61: =W60*W$23 -> 0.5202 | X61: =X60*X$23 -> 0.530604 | Y61: =Y60*Y$23 -> 0.74121608 | Z61: =Z60*Z$23 -> 0.7560404 | AA61: =AA60*AA$23 -> 0.77116121 | ... CA61: =CA60*CA$23 -> 2.1595045
B62: Billed Subscriptions | H62: 0 | I62: 0 | J62: 0 | K62: 0 | L62: 0 | M62: 0 | N62: 0 | O62: 0 | P62: 0 | Q62: 0 | R62: 0 | S62: 0 | T62: =T61+T67 -> 0 | U62: =U61+U67 -> 0.5 | V62: =V61+V67 -> 0.51 | W62: =W61+W67 -> 0.5202 | X62: =X61+X67 -> 0.530604 | Y62: =Y61+Y67 -> 0.74121608 | Z62: =Z61+Z67 -> 0.7560404 | AA62: =AA61+AA67 -> 0.77116121 | ... CA62: =CA61+CA67 -> 5.2649072
B63: Subscriptions Available for Renewal | T63: =H62 -> 0 | U63: =I62 -> 0 | V63: =J62 -> 0 | W63: =K62 -> 0 | X63: =L62 -> 0 | Y63: =M62 -> 0 | Z63: =N62 -> 0 | AA63: =O62 -> 0 | ... CA63: =BO62 -> 3.8817534
B64: Subscriptions In-between Billing Cycles | T64: =T69-T63 -> 0 | U64: =U69-U63 -> 0 | V64: =V69-V63 -> 0.5 | W64: =W69-W63 -> 1.01 | X64: =X69-X63 -> 1.5302 | Y64: =Y69-Y63 -> 2.060804 | Z64: =Z69-Z63 -> 2.8020201 | AA64: =AA69-AA63 -> 3.5580605 | ... CA64: =CA69-CA63 -> 50.939936
B65: Annual Churn Rate | D65: 0.2 | T65: =D65 -> 0.2 | U65: =T65 -> 0.2 | V65: =U65 -> 0.2 | W65: =V65 -> 0.2 | X65: =W65 -> 0.2 | Y65: =X65 -> 0.2 | Z65: =Y65 -> 0.2 | AA65: =Z65 -> 0.2 | AB65: =AA65 -> 0.2 | ... CA65: =BZ65 -> 0.2
B66: Churned Subscriptions | T66: =T63*T65 -> 0 | U66: =U63*U65 -> 0 | V66: =V63*V65 -> 0 | W66: =W63*W65 -> 0 | X66: =X63*X65 -> 0 | Y66: =Y63*Y65 -> 0 | Z66: =Z63*Z65 -> 0 | AA66: =AA63*AA65 -> 0 | ... CA66: =CA63*CA65 -> 0.77635068
B67: Renewed Susbcriptions | T67: =T63-T66 -> 0 | U67: =U63-U66 -> 0 | V67: =V63-V66 -> 0 | W67: =W63-W66 -> 0 | X67: =X63-X66 -> 0 | Y67: =Y63-Y66 -> 0 | Z67: =Z63-Z66 -> 0 | AA67: =AA63-AA66 -> 0 | ... CA67: =CA63-CA66 -> 3.1054027
B68: Active Subscriptions | T68: =T62+T64 -> 0 | U68: =U62+U64 -> 0.5 | V68: =V62+V64 -> 1.01 | W68: =W62+W64 -> 1.5302 | X68: =X62+X64 -> 2.060804 | Y68: =Y62+Y64 -> 2.8020201 | Z68: =Z62+Z64 -> 3.5580605 | AA68: =AA62+AA64 -> 4.3292217 | ... CA68: =CA62+CA64 -> 56.204843
B69: Previous Months Active Subsciptions | T69: =G68 | U69: =T68 -> 0 | V69: =U68 -> 0.5 | W69: =V68 -> 1.01 | X69: =W68 -> 1.5302 | Y69: =X68 -> 2.060804 | Z69: =Y68 -> 2.8020201 | AA69: =Z68 -> 3.5580605 | AB69: =AA68 -> 4.3292217 | ... CA69: =BZ68 -> 54.821689
B70: Average Units Purchased per Subscription | D70: 2 | T70: =D70 -> 2 | U70: =T70 -> 2 | V70: =U70 -> 2 | W70: =V70 -> 2 | X70: =W70 -> 2 | Y70: =X70 -> 2 | Z70: =Y70 -> 2 | AA70: =Z70 -> 2 | AB70: =AA70 -> 2 | ... CA70: =BZ70 -> 2
B71: Total Purchases this Month | T71: =T70*T62 -> 0 | U71: =U70*U62 -> 1 | V71: =V70*V62 -> 1.02 | W71: =W70*W62 -> 1.0404 | X71: =X70*X62 -> 1.061208 | Y71: =Y70*Y62 -> 1.4824322 | Z71: =Z70*Z62 -> 1.5120808 | AA71: =AA70*AA62 -> 1.5423224 | ... CA71: =CA70*CA62 -> 10.529814
B72: Average Annual Price per Unit | D72: 300 | T72: =D72 -> 300 | U72: =T72 -> 300 | V72: =U72 -> 300 | W72: =V72 -> 300 | X72: =W72 -> 300 | Y72: =X72 -> 300 | Z72: =Y72 -> 300 | AA72: =Z72 -> 300 | AB72: =AA72 -> 300 | ... CA72: =BZ72 -> 300
B73: Bookings | T73: =T71*T72 -> 0 | U73: =U71*U72 -> 300 | V73: =V71*V72 -> 306 | W73: =W71*W72 -> 312.12 | X73: =X71*X72 -> 318.3624 | Y73: =Y71*Y72 -> 444.72965 | Z73: =Z71*Z72 -> 453.62424 | AA73: =AA71*AA72 -> 462.69673 | ... CA73: =CA71*CA72 -> 3158.9443
B74: Revenue | T74: =(T72/12)*T68*T70 -> 0 | U74: =(U72/12)*U68*U70 -> 25 | V74: =(V72/12)*V68*V70 -> 50.5 | W74: =(W72/12)*W68*W70 -> 76.51 | X74: =(X72/12)*X68*X70 -> 103.0402 | Y74: =(Y72/12)*Y68*Y70 -> 140.101 | Z74: =(Z72/12)*Z68*Z70 -> 177.90302 | AA74: =(AA72/12)*AA68*AA70 -> 216.46108 | ... CA74: =(CA72/12)*CA68*CA70 -> 2810.2422
B76: + ADD MORE
B78: People:
B80: Name | C80: Salary | D80: Benefits | E80: Start Date
B81: Head of Marketing | C81: 80000 | D81: 0.2 | E81: 45444 | T81: =IF(T$4>=$E81,($C81/12)*(1+$D81),0) -> 0 | U81: =IF(U$4>=$E81,($C81/12)*(1+$D81),0) -> 0 | V81: =IF(V$4>=$E81,($C81/12)*(1+$D81),0) -> 0 | W81: =IF(W$4>=$E81,($C81/12)*(1+$D81),0) -> 0 | X81: =IF(X$4>=$E81,($C81/12)*(1+$D81),0) -> 0 | Y81: =IF(Y$4>=$E81,($C81/12)*(1+$D81),0) -> 8000 | Z81: =IF(Z$4>=$E81,($C81/12)*(1+$D81),0) -> 8000 | AA81: =IF(AA$4>=$E81,($C81/12)*(1+$D81),0) -> 8000 | ... CA81: =IF(CA$4>=$E81,($C81/12)*(1+$D81),0) -> 8000
B82: Person 2 | C82: 0 | D82: 0.2 | E82: 43831 | T82: =IF(T$4>=$E82,($C82/12)*(1+$D82),0) -> 0 | U82: =IF(U$4>=$E82,($C82/12)*(1+$D82),0) -> 0 | V82: =IF(V$4>=$E82,($C82/12)*(1+$D82),0) -> 0 | W82: =IF(W$4>=$E82,($C82/12)*(1+$D82),0) -> 0 | X82: =IF(X$4>=$E82,($C82/12)*(1+$D82),0) -> 0 | Y82: =IF(Y$4>=$E82,($C82/12)*(1+$D82),0) -> 0 | Z82: =IF(Z$4>=$E82,($C82/12)*(1+$D82),0) -> 0 | AA82: =IF(AA$4>=$E82,($C82/12)*(1+$D82),0) -> 0 | ... CA82: =IF(CA$4>=$E82,($C82/12)*(1+$D82),0) -> 0
B83: Person 3 | C83: 0 | D83: 0.2 | E83: 44075 | T83: =IF(T$4>=$E83,($C83/12)*(1+$D83),0) -> 0 | U83: =IF(U$4>=$E83,($C83/12)*(1+$D83),0) -> 0 | V83: =IF(V$4>=$E83,($C83/12)*(1+$D83),0) -> 0 | W83: =IF(W$4>=$E83,($C83/12)*(1+$D83),0) -> 0 | X83: =IF(X$4>=$E83,($C83/12)*(1+$D83),0) -> 0 | Y83: =IF(Y$4>=$E83,($C83/12)*(1+$D83),0) -> 0 | Z83: =IF(Z$4>=$E83,($C83/12)*(1+$D83),0) -> 0 | AA83: =IF(AA$4>=$E83,($C83/12)*(1+$D83),0) -> 0 | ... CA83: =IF(CA$4>=$E83,($C83/12)*(1+$D83),0) -> 0
B84: Person 4 | C84: 0 | D84: 0.2 | E84: 43831 | T84: =IF(T$4>=$E84,($C84/12)*(1+$D84),0) -> 0 | U84: =IF(U$4>=$E84,($C84/12)*(1+$D84),0) -> 0 | V84: =IF(V$4>=$E84,($C84/12)*(1+$D84),0) -> 0 | W84: =IF(W$4>=$E84,($C84/12)*(1+$D84),0) -> 0 | X84: =IF(X$4>=$E84,($C84/12)*(1+$D84),0) -> 0 | Y84: =IF(Y$4>=$E84,($C84/12)*(1+$D84),0) -> 0 | Z84: =IF(Z$4>=$E84,($C84/12)*(1+$D84),0) -> 0 | AA84: =IF(AA$4>=$E84,($C84/12)*(1+$D84),0) -> 0 | ... CA84: =IF(CA$4>=$E84,($C84/12)*(1+$D84),0) -> 0
B85: Person 5 | C85: 0 | D85: 0.2 | E85: 43891 | T85: =IF(T$4>=$E85,($C85/12)*(1+$D85),0) -> 0 | U85: =IF(U$4>=$E85,($C85/12)*(1+$D85),0) -> 0 | V85: =IF(V$4>=$E85,($C85/12)*(1+$D85),0) -> 0 | W85: =IF(W$4>=$E85,($C85/12)*(1+$D85),0) -> 0 | X85: =IF(X$4>=$E85,($C85/12)*(1+$D85),0) -> 0 | Y85: =IF(Y$4>=$E85,($C85/12)*(1+$D85),0) -> 0 | Z85: =IF(Z$4>=$E85,($C85/12)*(1+$D85),0) -> 0 | AA85: =IF(AA$4>=$E85,($C85/12)*(1+$D85),0) -> 0 | ... CA85: =IF(CA$4>=$E85,($C85/12)*(1+$D85),0) -> 0
B86: Person 6 | C86: 0 | D86: 0.2 | E86: 43983 | T86: =IF(T$4>=$E86,($C86/12)*(1+$D86),0) -> 0 | U86: =IF(U$4>=$E86,($C86/12)*(1+$D86),0) -> 0 | V86: =IF(V$4>=$E86,($C86/12)*(1+$D86),0) -> 0 | W86: =IF(W$4>=$E86,($C86/12)*(1+$D86),0) -> 0 | X86: =IF(X$4>=$E86,($C86/12)*(1+$D86),0) -> 0 | Y86: =IF(Y$4>=$E86,($C86/12)*(1+$D86),0) -> 0 | Z86: =IF(Z$4>=$E86,($C86/12)*(1+$D86),0) -> 0 | AA86: =IF(AA$4>=$E86,($C86/12)*(1+$D86),0) -> 0 | ... CA86: =IF(CA$4>=$E86,($C86/12)*(1+$D86),0) -> 0
B87: Person 7 | C87: 0 | D87: 0.2 | E87: 44075 | T87: =IF(T$4>=$E87,($C87/12)*(1+$D87),0) -> 0 | U87: =IF(U$4>=$E87,($C87/12)*(1+$D87),0) -> 0 | V87: =IF(V$4>=$E87,($C87/12)*(1+$D87),0) -> 0 | W87: =IF(W$4>=$E87,($C87/12)*(1+$D87),0) -> 0 | X87: =IF(X$4>=$E87,($C87/12)*(1+$D87),0) -> 0 | Y87: =IF(Y$4>=$E87,($C87/12)*(1+$D87),0) -> 0 | Z87: =IF(Z$4>=$E87,($C87/12)*(1+$D87),0) -> 0 | AA87: =IF(AA$4>=$E87,($C87/12)*(1+$D87),0) -> 0 | ... CA87: =IF(CA$4>=$E87,($C87/12)*(1+$D87),0) -> 0
B88: Person 8 | C88: 0 | D88: 0.2 | E88: 44166 | T88: =IF(T$4>=$E88,($C88/12)*(1+$D88),0) -> 0 | U88: =IF(U$4>=$E88,($C88/12)*(1+$D88),0) -> 0 | V88: =IF(V$4>=$E88,($C88/12)*(1+$D88),0) -> 0 | W88: =IF(W$4>=$E88,($C88/12)*(1+$D88),0) -> 0 | X88: =IF(X$4>=$E88,($C88/12)*(1+$D88),0) -> 0 | Y88: =IF(Y$4>=$E88,($C88/12)*(1+$D88),0) -> 0 | Z88: =IF(Z$4>=$E88,($C88/12)*(1+$D88),0) -> 0 | AA88: =IF(AA$4>=$E88,($C88/12)*(1+$D88),0) -> 0 | ... CA88: =IF(CA$4>=$E88,($C88/12)*(1+$D88),0) -> 0
B89: Person 9 | C89: 0 | D89: 0.2 | E89: 44256 | T89: =IF(T$4>=$E89,($C89/12)*(1+$D89),0) -> 0 | U89: =IF(U$4>=$E89,($C89/12)*(1+$D89),0) -> 0 | V89: =IF(V$4>=$E89,($C89/12)*(1+$D89),0) -> 0 | W89: =IF(W$4>=$E89,($C89/12)*(1+$D89),0) -> 0 | X89: =IF(X$4>=$E89,($C89/12)*(1+$D89),0) -> 0 | Y89: =IF(Y$4>=$E89,($C89/12)*(1+$D89),0) -> 0 | Z89: =IF(Z$4>=$E89,($C89/12)*(1+$D89),0) -> 0 | AA89: =IF(AA$4>=$E89,($C89/12)*(1+$D89),0) -> 0 | ... CA89: =IF(CA$4>=$E89,($C89/12)*(1+$D89),0) -> 0
B90: Person 10 | C90: 0 | D90: 0.2 | E90: 44348 | T90: =IF(T$4>=$E90,($C90/12)*(1+$D90),0) -> 0 | U90: =IF(U$4>=$E90,($C90/12)*(1+$D90),0) -> 0 | V90: =IF(V$4>=$E90,($C90/12)*(1+$D90),0) -> 0 | W90: =IF(W$4>=$E90,($C90/12)*(1+$D90),0) -> 0 | X90: =IF(X$4>=$E90,($C90/12)*(1+$D90),0) -> 0 | Y90: =IF(Y$4>=$E90,($C90/12)*(1+$D90),0) -> 0 | Z90: =IF(Z$4>=$E90,($C90/12)*(1+$D90),0) -> 0 | AA90: =IF(AA$4>=$E90,($C90/12)*(1+$D90),0) -> 0 | ... CA90: =IF(CA$4>=$E90,($C90/12)*(1+$D90),0) -> 0
B91: Person 11 | C91: 0 | D91: 0.2 | E91: 43831 | T91: =IF(T$4>=$E91,($C91/12)*(1+$D91),0) -> 0 | U91: =IF(U$4>=$E91,($C91/12)*(1+$D91),0) -> 0 | V91: =IF(V$4>=$E91,($C91/12)*(1+$D91),0) -> 0 | W91: =IF(W$4>=$E91,($C91/12)*(1+$D91),0) -> 0 | X91: =IF(X$4>=$E91,($C91/12)*(1+$D91),0) -> 0 | Y91: =IF(Y$4>=$E91,($C91/12)*(1+$D91),0) -> 0 | Z91: =IF(Z$4>=$E91,($C91/12)*(1+$D91),0) -> 0 | AA91: =IF(AA$4>=$E91,($C91/12)*(1+$D91),0) -> 0 | ... CA91: =IF(CA$4>=$E91,($C91/12)*(1+$D91),0) -> 0
B92: Person 12 | C92: 0 | D92: 0.2 | E92: 43831 | T92: =IF(T$4>=$E92,($C92/12)*(1+$D92),0) -> 0 | U92: =IF(U$4>=$E92,($C92/12)*(1+$D92),0) -> 0 | V92: =IF(V$4>=$E92,($C92/12)*(1+$D92),0) -> 0 | W92: =IF(W$4>=$E92,($C92/12)*(1+$D92),0) -> 0 | X92: =IF(X$4>=$E92,($C92/12)*(1+$D92),0) -> 0 | Y92: =IF(Y$4>=$E92,($C92/12)*(1+$D92),0) -> 0 | Z92: =IF(Z$4>=$E92,($C92/12)*(1+$D92),0) -> 0 | AA92: =IF(AA$4>=$E92,($C92/12)*(1+$D92),0) -> 0 | ... CA92: =IF(CA$4>=$E92,($C92/12)*(1+$D92),0) -> 0
... B104: Person 24 | C104: 0 | D104: 0.2 | E104: 44256 | T104: =IF(T$4>=$E104,($C104/12)*(1+$D104),0) -> 0 | U104: =IF(U$4>=$E104,($C104/12)*(1+$D104),0) -> 0 | V104: =IF(V$4>=$E104,($C104/12)*(1+$D104),0) -> 0 | W104: =IF(W$4>=$E104,($C104/12)*(1+$D104),0) -> 0 | X104: =IF(X$4>=$E104,($C104/12)*(1+$D104),0) -> 0 | Y104: =IF(Y$4>=$E104,($C104/12)*(1+$D104),0) -> 0 | Z104: =IF(Z$4>=$E104,($C104/12)*(1+$D104),0) -> 0 | AA104: =IF(AA$4>=$E104,($C104/12)*(1+$D104),0) -> 0 | ... CA104: =IF(CA$4>=$E104,($C104/12)*(1+$D104),0) -> 0
B105: Person 25 | C105: 0 | D105: 0.2 | T105: =IF(T$4>=$G105,($C105/12)*(1+$D105),0) -> 0 | U105: =IF(U$4>=$G105,($C105/12)*(1+$D105),0) -> 0 | V105: =IF(V$4>=$G105,($C105/12)*(1+$D105),0) -> 0 | W105: =IF(W$4>=$G105,($C105/12)*(1+$D105),0) -> 0 | X105: =IF(X$4>=$G105,($C105/12)*(1+$D105),0) -> 0 | Y105: =IF(Y$4>=$G105,($C105/12)*(1+$D105),0) -> 0 | Z105: =IF(Z$4>=$G105,($C105/12)*(1+$D105),0) -> 0 | AA105: =IF(AA$4>=$G105,($C105/12)*(1+$D105),0) -> 0 | ... CA105: =IF(CA$4>=$G105,($C105/12)*(1+$D105),0) -> 0
B107: Expenses:
B109: Costs of Goods Sold | C109: % Revenue
B110: Database & Hosting | C110: 0.02 | T110: =Financials!F$8*$C110 -> 0 | U110: =Financials!G$8*$C110 -> 9.5 | V110: =Financials!H$8*$C110 -> 19.19 | W110: =Financials!I$8*$C110 -> 29.0738 | X110: =Financials!J$8*$C110 -> 39.155276 | Y110: =Financials!K$8*$C110 -> 56.838382 | Z110: =Financials!L$8*$C110 -> 74.875149 | AA110: =Financials!M$8*$C110 -> 93.272652 | ... CA110: =Financials!BM$8*$C110 -> 1336.7727
B111: Payment Processing | C111: 0.03 | T111: =Financials!F$8*$C111 -> 0 | U111: =Financials!G$8*$C111 -> 14.25 | V111: =Financials!H$8*$C111 -> 28.785 | W111: =Financials!I$8*$C111 -> 43.6107 | X111: =Financials!J$8*$C111 -> 58.732914 | Y111: =Financials!K$8*$C111 -> 85.257572 | Z111: =Financials!L$8*$C111 -> 112.31272 | AA111: =Financials!M$8*$C111 -> 139.90898 | ... CA111: =Financials!BM$8*$C111 -> 2005.159
B112: Other | C112: 0.05 | T112: =Financials!F$8*$C112 -> 0 | U112: =Financials!G$8*$C112 -> 23.75 | V112: =Financials!H$8*$C112 -> 47.975 | W112: =Financials!I$8*$C112 -> 72.6845 | X112: =Financials!J$8*$C112 -> 97.88819 | Y112: =Financials!K$8*$C112 -> 142.09595 | Z112: =Financials!L$8*$C112 -> 187.18787 | AA112: =Financials!M$8*$C112 -> 233.18163 | ... CA112: =Financials!BM$8*$C112 -> 3341.9317
B113: COGS 1 | C113: 0.05 | T113: =Financials!F$8*$C113 -> 0 | U113: =Financials!G$8*$C113 -> 23.75 | V113: =Financials!H$8*$C113 -> 47.975 | W113: =Financials!I$8*$C113 -> 72.6845 | X113: =Financials!J$8*$C113 -> 97.88819 | Y113: =Financials!K$8*$C113 -> 142.09595 | Z113: =Financials!L$8*$C113 -> 187.18787 | AA113: =Financials!M$8*$C113 -> 233.18163 | ... CA113: =Financials!BM$8*$C113 -> 3341.9317
B114: COGS 2 | C114: 0.05 | T114: =Financials!F$8*$C114 -> 0 | U114: =Financials!G$8*$C114 -> 23.75 | V114: =Financials!H$8*$C114 -> 47.975 | W114: =Financials!I$8*$C114 -> 72.6845 | X114: =Financials!J$8*$C114 -> 97.88819 | Y114: =Financials!K$8*$C114 -> 142.09595 | Z114: =Financials!L$8*$C114 -> 187.18787 | AA114: =Financials!M$8*$C114 -> 233.18163 | ... CA114: =Financials!BM$8*$C114 -> 3341.9317
B115: COGS 3 | C115: 0.05 | T115: =Financials!F$8*$C115 -> 0 | U115: =Financials!G$8*$C115 -> 23.75 | V115: =Financials!H$8*$C115 -> 47.975 | W115: =Financials!I$8*$C115 -> 72.6845 | X115: =Financials!J$8*$C115 -> 97.88819 | Y115: =Financials!K$8*$C115 -> 142.09595 | Z115: =Financials!L$8*$C115 -> 187.18787 | AA115: =Financials!M$8*$C115 -> 233.18163 | ... CA115: =Financials!BM$8*$C115 -> 3341.9317
B116: COGS 4 | C116: 0.05 | T116: =Financials!F$8*$C116 -> 0 | U116: =Financials!G$8*$C116 -> 23.75 | V116: =Financials!H$8*$C116 -> 47.975 | W116: =Financials!I$8*$C116 -> 72.6845 | X116: =Financials!J$8*$C116 -> 97.88819 | Y116: =Financials!K$8*$C116 -> 142.09595 | Z116: =Financials!L$8*$C116 -> 187.18787 | AA116: =Financials!M$8*$C116 -> 233.18163 | ... CA116: =Financials!BM$8*$C116 -> 3341.9317
B117: COGS 5 | C117: 0.05 | T117: =Financials!F$8*$C117 -> 0 | U117: =Financials!G$8*$C117 -> 23.75 | V117: =Financials!H$8*$C117 -> 47.975 | W117: =Financials!I$8*$C117 -> 72.6845 | X117: =Financials!J$8*$C117 -> 97.88819 | Y117: =Financials!K$8*$C117 -> 142.09595 | Z117: =Financials!L$8*$C117 -> 187.18787 | AA117: =Financials!M$8*$C117 -> 233.18163 | ... CA117: =Financials!BM$8*$C117 -> 3341.9317
B118: Total | T118: =sum(T110:T117) -> 0 | U118: =sum(U110:U117) -> 166.25 | V118: =sum(V110:V117) -> 335.825 | W118: =sum(W110:W117) -> 508.7915 | X118: =sum(X110:X117) -> 685.21733 | Y118: =sum(Y110:Y117) -> 994.67168 | Z118: =sum(Z110:Z117) -> 1310.3151 | AA118: =sum(AA110:AA117) -> 1632.2714 | ... CA118: =sum(CA110:CA117) -> 23393.522
B120: General & Admin
B121: Rent & Utilities | C121: 2500 | T121: =C121 -> 2500 | U121: =T121 -> 2500 | V121: =U121 -> 2500 | W121: =V121 -> 2500 | X121: =W121 -> 2500 | Y121: =X121 -> 2500 | Z121: =Y121 -> 2500 | AA121: =Z121 -> 2500 | AB121: =AA121 -> 2500 | ... CA121: =BZ121 -> 2500
B122: Dues & Subscriptions | C122: 2500 | T122: =C122 -> 2500 | U122: =T122 -> 2500 | V122: =U122 -> 2500 | W122: =V122 -> 2500 | X122: =W122 -> 2500 | Y122: =X122 -> 2500 | Z122: =Y122 -> 2500 | AA122: =Z122 -> 2500 | AB122: =AA122 -> 2500 | ... CA122: =BZ122 -> 2500
B123: Travel & Entertainment | C123: 2500 | T123: =C123 -> 2500 | U123: =T123 -> 2500 | V123: =U123 -> 2500 | W123: =V123 -> 2500 | X123: =W123 -> 2500 | Y123: =X123 -> 2500 | Z123: =Y123 -> 2500 | AA123: =Z123 -> 2500 | AB123: =AA123 -> 2500 | ... CA123: =BZ123 -> 2500
B124: Office Supplies | C124: 2500 | T124: =C124 -> 2500 | U124: =T124 -> 2500 | V124: =U124 -> 2500 | W124: =V124 -> 2500 | X124: =W124 -> 2500 | Y124: =X124 -> 2500 | Z124: =Y124 -> 2500 | AA124: =Z124 -> 2500 | AB124: =AA124 -> 2500 | ... CA124: =BZ124 -> 2500
B125: Product & Development | C125: 2500 | T125: =C125 -> 2500 | U125: =T125 -> 2500 | V125: =U125 -> 2500 | W125: =V125 -> 2500 | X125: =W125 -> 2500 | Y125: =X125 -> 2500 | Z125: =Y125 -> 2500 | AA125: =Z125 -> 2500 | AB125: =AA125 -> 2500 | ... CA125: =BZ125 -> 2500
B126: General & Admin 1 | C126: 2500 | T126: =C126 -> 2500 | U126: =T126 -> 2500 | V126: =U126 -> 2500 | W126: =V126 -> 2500 | X126: =W126 -> 2500 | Y126: =X126 -> 2500 | Z126: =Y126 -> 2500 | AA126: =Z126 -> 2500 | AB126: =AA126 -> 2500 | ... CA126: =BZ126 -> 2500
B127: General & Admin 2 | C127: 2500 | T127: =C127 -> 2500 | U127: =T127 -> 2500 | V127: =U127 -> 2500 | W127: =V127 -> 2500 | X127: =W127 -> 2500 | Y127: =X127 -> 2500 | Z127: =Y127 -> 2500 | AA127: =Z127 -> 2500 | AB127: =AA127 -> 2500 | ... CA127: =BZ127 -> 2500
B128: General & Admin 3 | C128: 2500 | T128: =C128 -> 2500 | U128: =T128 -> 2500 | V128: =U128 -> 2500 | W128: =V128 -> 2500 | X128: =W128 -> 2500 | Y128: =X128 -> 2500 | Z128: =Y128 -> 2500 | AA128: =Z128 -> 2500 | AB128: =AA128 -> 2500 | ... CA128: =BZ128 -> 2500
...

Sheet Financials
B1: Year Counter | F1: 1 | G1: 1 | H1: 1 | I1: 1 | J1: 1 | K1: 1 | L1: 1 | M1: 1 | N1: 1 | O1: 1 | P1: 1 | Q1: 1 | R1: =F1+1 -> 2 | S1: =G1+1 -> 2 | T1: =H1+1 -> 2 | U1: =I1+1 -> 2 | V1: =J1+1 -> 2 | W1: =K1+1 -> 2 | X1: =L1+1 -> 2 | Y1: =M1+1 -> 2 | ... BM1: =BA1+1 -> 5
B2: Year | F2: =YEAR(F4) -> 2024 | G2: =YEAR(G4) -> 2024 | H2: =YEAR(H4) -> 2024 | I2: =YEAR(I4) -> 2024 | J2: =YEAR(J4) -> 2024 | K2: =YEAR(K4) -> 2024 | L2: =YEAR(L4) -> 2024 | M2: =YEAR(M4) -> 2024 | ... BM2: =YEAR(BM4) -> 2028
B3: Month Counter | F3: 1 | G3: =F3+1 -> 2 | H3: =G3+1 -> 3 | I3: =H3+1 -> 4 | J3: =I3+1 -> 5 | K3: =J3+1 -> 6 | L3: =K3+1 -> 7 | M3: =L3+1 -> 8 | N3: =M3+1 -> 9 | ... BM3: =BL3+1 -> 60
B4: Date | F4: =Assumptions!T4 -> 45292 | G4: =EOMONTH(F4,1) -> 45351 | H4: =EOMONTH(G4,1) -> 45382 | I4: =EOMONTH(H4,1) -> 45412 | J4: =EOMONTH(I4,1) -> 45443 | K4: =EOMONTH(J4,1) -> 45473 | L4: =EOMONTH(K4,1) -> 45504 | M4: =EOMONTH(L4,1) -> 45535 | N4: =EOMONTH(M4,1) -> 45565 | ... BM4: =EOMONTH(BL4,1) -> 47118
B6: Income Statement:
B8: Revenue | F8: =sum(F9:F11) -> 0 | G8: =sum(G9:G11) -> 475 | H8: =sum(H9:H11) -> 959.5 | I8: =sum(I9:I11) -> 1453.69 | J8: =sum(J9:J11) -> 1957.7638 | K8: =sum(K9:K11) -> 2841.9191 | L8: =sum(L9:L11) -> 3743.7575 | M8: =sum(M9:M11) -> 4663.6326 | ... BM8: =sum(BM9:BM11) -> 66838.633
B9: =Assumptions!B27 -> Regular School Licenses | F9: =Assumptions!T41 -> 0 | G9: =Assumptions!U41 -> 450 | H9: =Assumptions!V41 -> 909 | I9: =Assumptions!W41 -> 1377.18 | J9: =Assumptions!X41 -> 1854.7236 | K9: =Assumptions!Y41 -> 2341.8181 | L9: =Assumptions!Z41 -> 2838.6544 | M9: =Assumptions!AA41 -> 3345.4275 | ... BN9: =Assumptions!CB41
B10: =Assumptions!B43 -> Large School Licenses | F10: =Assumptions!T57 -> 0 | G10: =Assumptions!U57 -> 0 | H10: =Assumptions!V57 -> 0 | I10: =Assumptions!W57 -> 0 | J10: =Assumptions!X57 -> 0 | K10: =Assumptions!Y57 -> 360 | L10: =Assumptions!Z57 -> 727.2 | M10: =Assumptions!AA57 -> 1101.744 | ... BN10: =Assumptions!CB57
B11: =Assumptions!B59 -> Per Unit Annual SaaS Tier 3 | F11: =Assumptions!T74 -> 0 | G11: =Assumptions!U74 -> 25 | H11: =Assumptions!V74 -> 50.5 | I11: =Assumptions!W74 -> 76.51 | J11: =Assumptions!X74 -> 103.0402 | K11: =Assumptions!Y74 -> 140.101 | L11: =Assumptions!Z74 -> 177.90302 | M11: =Assumptions!AA74 -> 216.46108 | ... BN11: =Assumptions!CB74
B13: COGS | F13: =Assumptions!T118 -> 0 | G13: =Assumptions!U118 -> 166.25 | H13: =Assumptions!V118 -> 335.825 | I13: =Assumptions!W118 -> 508.7915 | J13: =Assumptions!X118 -> 685.21733 | K13: =Assumptions!Y118 -> 994.67168 | L13: =Assumptions!Z118 -> 1310.3151 | M13: =Assumptions!AA118 -> 1632.2714 | ... BN13: =Assumptions!CB118
B15: Gross Profit | F15: =F8-F13 -> 0 | G15: =G8-G13 -> 308.75 | H15: =H8-H13 -> 623.675 | I15: =I8-I13 -> 944.8985 | J15: =J8-J13 -> 1272.5465 | K15: =K8-K13 -> 1847.2474 | L15: =L8-L13 -> 2433.4423 | M15: =M8-M13 -> 3031.3612 | ... BM15: =BM8-BM13 -> 43445.112
B16: Gross Margin | F16: =F15/F8 -> #DIV/0! | G16: =G15/G8 -> 0.65 | H16: =H15/H8 -> 0.65 | I16: =I15/I8 -> 0.65 | J16: =J15/J8 -> 0.65 | K16: =K15/K8 -> 0.65 | L16: =L15/L8 -> 0.65 | M16: =M15/M8 -> 0.65 | ... BM16: =BM15/BM8 -> 0.65
B18: Operating Expenses
B19: Salaries & Benefits | F19: =SUM(Assumptions!T81:T105) -> 0 | G19: =SUM(Assumptions!U81:U105) -> 0 | H19: =SUM(Assumptions!V81:V105) -> 0 | I19: =SUM(Assumptions!W81:W105) -> 0 | J19: =SUM(Assumptions!X81:X105) -> 0 | K19: =SUM(Assumptions!Y81:Y105) -> 8000 | L19: =SUM(Assumptions!Z81:Z105) -> 8000 | M19: =SUM(Assumptions!AA81:AA105) -> 8000 | ... BM19: =SUM(Assumptions!CA81:CA105) -> 8000
B20: =Assumptions!B120 -> General & Admin | F20: =sum(Assumptions!T121:T128) -> 20000 | G20: =sum(Assumptions!U121:U128) -> 20000 | H20: =sum(Assumptions!V121:V128) -> 20000 | I20: =sum(Assumptions!W121:W128) -> 20000 | J20: =sum(Assumptions!X121:X128) -> 20000 | K20: =sum(Assumptions!Y121:Y128) -> 20000 | L20: =sum(Assumptions!Z121:Z128) -> 20000 | M20: =sum(Assumptions!AA121:AA128) -> 20000 | ... BM20: =sum(Assumptions!CA121:CA128) -> 20000
B21: =Assumptions!B131 -> Sales & Marketing | F21: =sum(Assumptions!T132:T133) -> 10000 | G21: =sum(Assumptions!U132:U133) -> 10038 | H21: =sum(Assumptions!V132:V133) -> 10076.76 | I21: =sum(Assumptions!W132:W133) -> 10116.295 | J21: =sum(Assumptions!X132:X133) -> 10156.621 | K21: =sum(Assumptions!Y132:Y133) -> 10227.354 | L21: =sum(Assumptions!Z132:Z133) -> 10299.501 | M21: =sum(Assumptions!AA132:AA133) -> 10373.091 | ... BM21: =sum(Assumptions!CA132:CA133) -> 15347.091
B22: =Assumptions!B136 -> Professional Fees | F22: =SUM(Assumptions!T137:T139) -> 5500 | G22: =SUM(Assumptions!U137:U139) -> 5500 | H22: =SUM(Assumptions!V137:V139) -> 5500 | I22: =SUM(Assumptions!W137:W139) -> 5500 | J22: =SUM(Assumptions!X137:X139) -> 5500 | K22: =SUM(Assumptions!Y137:Y139) -> 5500 | L22: =SUM(Assumptions!Z137:Z139) -> 5500 | M22: =SUM(Assumptions!AA137:AA139) -> 5500 | ... BM22: =SUM(Assumptions!CA137:CA139) -> 5500
B23: =Assumptions!B142 -> Other | F23: =Assumptions!T143 -> 0 | G23: =Assumptions!U143 -> 47.5 | H23: =Assumptions!V143 -> 95.95 | I23: =Assumptions!W143 -> 145.369 | J23: =Assumptions!X143 -> 195.77638 | K23: =Assumptions!Y143 -> 284.19191 | L23: =Assumptions!Z143 -> 374.37575 | M23: =Assumptions!AA143 -> 466.36326 | ... BM23: =Assumptions!CA143 -> 6683.8633
B24: Total Operating Expenses | F24: =SUM(F19:F23) -> 35500 | G24: =SUM(G19:G23) -> 35585.5 | H24: =SUM(H19:H23) -> 35672.71 | I24: =SUM(I19:I23) -> 35761.664 | J24: =SUM(J19:J23) -> 35852.397 | K24: =SUM(K19:K23) -> 44011.545 | L24: =SUM(L19:L23) -> 44173.876 | M24: =SUM(M19:M23) -> 44339.454 | ... BM24: =SUM(BM19:BM23) -> 55530.954
B26: EBITDA | F26: =F15-F24 -> -35500 | G26: =G15-G24 -> -35276.75 | H26: =H15-H24 -> -35049.035 | I26: =I15-I24 -> -34816.766 | J26: =J15-J24 -> -34579.851 | K26: =K15-K24 -> -42164.298 | L26: =L15-L24 -> -41740.434 | M26: =M15-M24 -> -41308.093 | ... BM26: =BM15-BM24 -> -12085.842
B27: Depreciation | F27: =SUM(Assumptions!T164:T167)-sum(Assumptions!G164:G167) -> 0 | G27: =SUM(Assumptions!U164:U167)-sum(Assumptions!T164:T167) -> 0 | H27: =SUM(Assumptions!V164:V167)-sum(Assumptions!U164:U167) -> 0 | I27: =SUM(Assumptions!W164:W167)-sum(Assumptions!V164:V167) -> 0 | J27: =SUM(Assumptions!X164:X167)-sum(Assumptions!W164:W167) -> 0 | K27: =SUM(Assumptions!Y164:Y167)-sum(Assumptions!X164:X167) -> 0 | L27: =SUM(Assumptions!Z164:Z167)-sum(Assumptions!Y164:Y167) -> 0 | M27: =SUM(Assumptions!AA164:AA167)-sum(Assumptions!Z164:Z167) -> 0 | N27: =SUM(Assumptions!AB164:AB167)-sum(Assumptions!AA164:AA167) -> 0 | ... BM27: =SUM(Assumptions!CA164:CA167)-sum(Assumptions!BZ164:BZ167) -> 0
B28: EBIT | F28: =F26-F27 -> -35500 | G28: =G26-G27 -> -35276.75 | H28: =H26-H27 -> -35049.035 | I28: =I26-I27 -> -34816.766 | J28: =J26-J27 -> -34579.851 | K28: =K26-K27 -> -42164.298 | L28: =L26-L27 -> -41740.434 | M28: =M26-M27 -> -41308.093 | ... BM28: =BM26-BM27 -> -12085.842
B29: Taxes | F29: =IF(F28>0,F28*Assumptions!$C$145,0) -> 0 | G29: =IF(G28>0,G28*Assumptions!$C$145,0) -> 0 | H29: =IF(H28>0,H28*Assumptions!$C$145,0) -> 0 | I29: =IF(I28>0,I28*Assumptions!$C$145,0) -> 0 | J29: =IF(J28>0,J28*Assumptions!$C$145,0) -> 0 | K29: =IF(K28>0,K28*Assumptions!$C$145,0) -> 0 | L29: =IF(L28>0,L28*Assumptions!$C$145,0) -> 0 | M29: =IF(M28>0,M28*Assumptions!$C$145,0) -> 0 | ... BM29: =IF(BM28>0,BM28*Assumptions!$C$145,0) -> 0
B30: Net Income | F30: =F28-F29 -> -35500 | G30: =G28-G29 -> -35276.75 | H30: =H28-H29 -> -35049.035 | I30: =I28-I29 -> -34816.766 | J30: =J28-J29 -> -34579.851 | K30: =K28-K29 -> -42164.298 | L30: =L28-L29 -> -41740.434 | M30: =M28-M29 -> -41308.093 | ... BM30: =BM28-BM29 -> -12085.842
B31: Net Margin | F31: =F30/F8 -> #DIV/0! | G31: =G30/G8 -> -74.266842 | H31: =H30/H8 -> -36.528437 | I31: =I30/I8 -> -23.950612 | J31: =J30/J8 -> -17.662933 | K31: =K30/K8 -> -14.836558 | L31: =L30/L8 -> -11.149342 | M31: =M30/M8 -> -8.8574929 | ... BM31: =BM30/BM8 -> -0.18082121
B33: Balance Sheet:
B35: Assets
B36: Current Assets
B37: Cash | F37: =F82 -> 7250 | G37: =G82 -> 977067.62 | H37: =H82 -> 946739.85 | I37: =I82 -> 916263.77 | J37: =J82 -> 885636.43 | K37: =K82 -> 850996.93 | L37: =L82 -> 816086.79 | M37: =M82 -> 780900.6 | ... BM37: =BM82 -> -335060.15
B38: Accounts Receivable | F38: =Assumptions!T155 -> 0 | G38: =Assumptions!U155 -> 237.5 | H38: =Assumptions!V155 -> 479.75 | I38: =Assumptions!W155 -> 726.845 | J38: =Assumptions!X155 -> 978.8819 | K38: =Assumptions!Y155 -> 1420.9595 | L38: =Assumptions!Z155 -> 1871.8787 | M38: =Assumptions!AA155 -> 2331.8163 | ... BM38: =Assumptions!CA155 -> 33419.317
B39: Total Current Assets | F39: =SUM(F37:F38) -> 7250 | G39: =SUM(G37:G38) -> 977305.12 | H39: =SUM(H37:H38) -> 947219.6 | I39: =SUM(I37:I38) -> 916990.62 | J39: =SUM(J37:J38) -> 886615.31 | K39: =SUM(K37:K38) -> 852417.89 | L39: =SUM(L37:L38) -> 817958.67 | M39: =SUM(M37:M38) -> 783232.42 | ... BM39: =SUM(BM37:BM38) -> -301640.83
B41: Fixed Assets | F41: =SUM(Assumptions!T157:T161) -> 0 | G41: =SUM(Assumptions!U157:U161) -> 0 | H41: =SUM(Assumptions!V157:V161) -> 0 | I41: =SUM(Assumptions!W157:W161) -> 0 | J41: =SUM(Assumptions!X157:X161) -> 0 | K41: =SUM(Assumptions!Y157:Y161) -> 0 | L41: =SUM(Assumptions!Z157:Z161) -> 0 | M41: =SUM(Assumptions!AA157:AA161) -> 0 | ... BM41: =SUM(Assumptions!CA157:CA161) -> 0
B42: Accumulated Depreciation | F42: =-SUM(Assumptions!T164:T167) -> 0 | G42: =-SUM(Assumptions!U164:U167) -> 0 | H42: =-SUM(Assumptions!V164:V167) -> 0 | I42: =-SUM(Assumptions!W164:W167) -> 0 | J42: =-SUM(Assumptions!X164:X167) -> 0 | K42: =-SUM(Assumptions!Y164:Y167) -> 0 | L42: =-SUM(Assumptions!Z164:Z167) -> 0 | M42: =-SUM(Assumptions!AA164:AA167) -> 0 | ... BM42: =-SUM(Assumptions!CA164:CA167) -> 0
B43: Total Assets | F43: =SUM(F39:F42) -> 7250 | G43: =SUM(G39:G42) -> 977305.12 | H43: =SUM(H39:H42) -> 947219.6 | I43: =SUM(I39:I42) -> 916990.62 | J43: =SUM(J39:J42) -> 886615.31 | K43: =SUM(K39:K42) -> 852417.89 | L43: =SUM(L39:L42) -> 817958.67 | M43: =SUM(M39:M42) -> 783232.42 | ... BM43: =SUM(BM39:BM42) -> -301640.83
B45: Liabilities & Owner's Equity
B46: Liabilities
B47: Accounts payable | F47: =Assumptions!T171 -> 12750 | G47: =Assumptions!U171 -> 12856.875 | H47: =Assumptions!V171 -> 12965.888 | I47: =Assumptions!W171 -> 13077.08 | J47: =Assumptions!X171 -> 13190.497 | K47: =Assumptions!Y171 -> 13389.432 | L47: =Assumptions!Z171 -> 13592.345 | M47: =Assumptions!AA171 -> 13799.317 | ... BM47: =Assumptions!CA171 -> 27788.692
B48: Deferred Revenue | F48: =Assumptions!T173 -> 0 | G48: =Assumptions!U173 -> 5225 | H48: =Assumptions!V173 -> 10079.5 | I48: =Assumptions!W173 -> 14556.09 | J48: =Assumptions!X173 -> 18647.212 | K48: =Assumptions!Y173 -> 26415.156 | L48: =Assumptions!Z173 -> 33493.459 | M48: =Assumptions!AA173 -> 39868.328 | ... BN48: =Assumptions!CB173
B49: Total Liabilities | F49: =sum(F47:F48) -> 12750 | G49: =sum(G47:G48) -> 18081.875 | H49: =sum(H47:H48) -> 23045.388 | I49: =sum(I47:I48) -> 27633.17 | J49: =sum(J47:J48) -> 31837.709 | K49: =sum(K47:K48) -> 39804.588 | L49: =sum(L47:L48) -> 47085.805 | M49: =sum(M47:M48) -> 53667.646 | ... BM49: =sum(BM47:BM48) -> 414893.28
B51: Equity | E51: Prev Cash
B52: Paid In Capital | E52: =Assumptions!C153 -> 30000 | F52: =E52 -> 30000 | G52: =Assumptions!U187+$E52 -> 1030000 | H52: =Assumptions!V187+$E52 -> 1030000 | I52: =Assumptions!W187+$E52 -> 1030000 | J52: =Assumptions!X187+$E52 -> 1030000 | K52: =Assumptions!Y187+$E52 -> 1030000 | L52: =Assumptions!Z187+$E52 -> 1030000 | M52: =Assumptions!AA187+$E52 -> 1030000 | N52: =Assumptions!AB187+$E52 -> 1030000 | ... BM52: =Assumptions!CA187+$E52 -> 1030000
B53: Accumulated Retained Earnings | F53: =E53+F30 -> -35500 | G53: =F53+G30 -> -70776.75 | H53: =G53+H30 -> -105825.79 | I53: =H53+I30 -> -140642.55 | J53: =I53+J30 -> -175222.4 | K53: =J53+K30 -> -217386.7 | L53: =K53+L30 -> -259127.13 | M53: =L53+M30 -> -300435.23 | ... BM53: =BL53+BM30 -> -1746534.1
B54: Total Equity | F54: =SUM(F52:F53) -> -5500 | G54: =SUM(G52:G53) -> 959223.25 | H54: =SUM(H52:H53) -> 924174.21 | I54: =SUM(I52:I53) -> 889357.45 | J54: =SUM(J52:J53) -> 854777.6 | K54: =SUM(K52:K53) -> 812613.3 | L54: =SUM(L52:L53) -> 770872.87 | M54: =SUM(M52:M53) -> 729564.77 | ... BM54: =SUM(BM52:BM53) -> -716534.11
B56: Total Liabilities & Owner's Equity | F56: =F54+F49 -> 7250 | G56: =G54+G49 -> 977305.12 | H56: =H54+H49 -> 947219.6 | I56: =I54+I49 -> 916990.62 | J56: =J54+J49 -> 886615.31 | K56: =K54+K49 -> 852417.89 | L56: =L54+L49 -> 817958.67 | M56: =M54+M49 -> 783232.42 | ... BM56: =BM54+BM49 -> -301640.83
B58: Balance Check | F58: =IF(ABS(F56-F43)>0.001,"ERROR","OK") -> OK | G58: =IF(ABS(G56-G43)>0.001,"ERROR","OK") -> OK | H58: =IF(ABS(H56-H43)>0.001,"ERROR","OK") -> OK | I58: =IF(ABS(I56-I43)>0.001,"ERROR","OK") -> OK | J58: =IF(ABS(J56-J43)>0.001,"ERROR","OK") -> OK | K58: =IF(ABS(K56-K43)>0.001,"ERROR","OK") -> OK | L58: =IF(ABS(L56-L43)>0.001,"ERROR","OK") -> OK | M58: =IF(ABS(M56-M43)>0.001,"ERROR","OK") -> OK | ... BM58: =IF(ABS(BM56-BM43)>0.001,"ERROR","OK") -> OK
B60: Statement of Cash Flows:
B62: Operating Cash Flows
B63: Net Income | F63: =F53-E53 -> -35500 | G63: =G53-F53 -> -35276.75 | H63: =H53-G53 -> -35049.035 | I63: =I53-H53 -> -34816.766 | J63: =J53-I53 -> -34579.851 | K63: =K53-J53 -> -42164.298 | L63: =L53-K53 -> -41740.434 | M63: =M53-L53 -> -41308.093 | ... BM63: =BM53-BL53 -> -12085.842
B64: Depreciation | F64: =E42-F42 -> 0 | G64: =F42-G42 -> 0 | H64: =G42-H42 -> 0 | I64: =H42-I42 -> 0 | J64: =I42-J42 -> 0 | K64: =J42-K42 -> 0 | L64: =K42-L42 -> 0 | M64: =L42-M42 -> 0 | ... BM64: =BL42-BM42 -> 0
B65: Change in Accounts Receivable | F65: =E38-F38 -> 0 | G65: =F38-G38 -> -237.5 | H65: =G38-H38 -> -242.25 | I65: =H38-I38 -> -247.095 | J65: =I38-J38 -> -252.0369 | K65: =J38-K38 -> -442.07764 | L65: =K38-L38 -> -450.91919 | M65: =L38-M38 -> -459.93757 | ... BM65: =BL38-BM38 -> -824.94346
B66: Change in Accounts Payable | F66: =F47-E47 -> 12750 | G66: =G47-F47 -> 106.875 | H66: =H47-G47 -> 109.0125 | I66: =I47-H47 -> 111.19275 | J66: =J47-I47 -> 113.41661 | K66: =K47-J47 -> 198.93494 | L66: =L47-K47 -> 202.91364 | M66: =M47-L47 -> 206.97191 | ... BM66: =BM47-BL47 -> 371.22456
B67: Change in Deferred Revenue | F67: =F48-E48 -> 0 | G67: =G48-F48 -> 5225 | H67: =H48-G48 -> 4854.5 | I67: =I48-H48 -> 4476.59 | J67: =J48-I48 -> 4091.1218 | K67: =K48-J48 -> 7767.9442 | L67: =L48-K48 -> 7078.3031 | M67: =M48-L48 -> 6374.8692 | ... BM67: =BM48-BL48 -> 8523.933
B68: Total Operating Cash Flows | F68: =sum(F63:F67) -> -22750 | G68: =sum(G63:G67) -> -30182.375 | H68: =sum(H63:H67) -> -30327.772 | I68: =sum(I63:I67) -> -30476.078 | J68: =sum(J63:J67) -> -30627.35 | K68: =sum(K63:K67) -> -34639.497 | L68: =sum(L63:L67) -> -34910.136 | M68: =sum(M63:M67) -> -35186.189 | ... BM68: =sum(BM63:BM67) -> -4015.6283
B70: Investing Cash Flows
B71: Changes in Fixed Assets | F71: =E41-F41 -> 0 | G71: =F41-G41 -> 0 | H71: =G41-H41 -> 0 | I71: =H41-I41 -> 0 | J71: =I41-J41 -> 0 | K71: =J41-K41 -> 0 | L71: =K41-L41 -> 0 | M71: =L41-M41 -> 0 | ... BM71: =BL41-BM41 -> 0
B72: Total Investing Cash Flows | F72: =F71 -> 0 | G72: =G71 -> 0 | H72: =H71 -> 0 | I72: =I71 -> 0 | J72: =J71 -> 0 | K72: =K71 -> 0 | L72: =L71 -> 0 | M72: =M71 -> 0 | ... BM72: =BM71 -> 0
B74: Financing Cash Flows
B75: Changes in Paid in Capital | F75: =F52-E52 -> 0 | G75: =G52-F52 -> 1000000 | H75: =H52-G52 -> 0 | I75: =I52-H52 -> 0 | J75: =J52-I52 -> 0 | K75: =K52-J52 -> 0 | L75: =L52-K52 -> 0 | M75: =M52-L52 -> 0 | ... BM75: =BM52-BL52 -> 0
B76: Total Financing Cash Flows | F76: =F75 -> 0 | G76: =G75 -> 1000000 | H76: =H75 -> 0 | I76: =I75 -> 0 | J76: =J75 -> 0 | K76: =K75 -> 0 | L76: =L75 -> 0 | M76: =M75 -> 0 | ... BM76: =BM75 -> 0
B78: Beginning Cash | F78: =Assumptions!C153 -> 30000 | G78: =F82 -> 7250 | H78: =G82 -> 977067.62 | I78: =H82 -> 946739.85 | J78: =I82 -> 916263.77 | K78: =J82 -> 885636.43 | L78: =K82 -> 850996.93 | M78: =L82 -> 816086.79 | N78: =M82 -> 780900.6 | ... BM78: =BL82 -> -331044.52
B80: Change in Cash | F80: =F76+F72+F68 -> -22750 | G80: =G76+G72+G68 -> 969817.62 | H80: =H76+H72+H68 -> -30327.772 | I80: =I76+I72+I68 -> -30476.078 | J80: =J76+J72+J68 -> -30627.35 | K80: =K76+K72+K68 -> -34639.497 | L80: =L76+L72+L68 -> -34910.136 | M80: =M76+M72+M68 -> -35186.189 | ... BM80: =BM76+BM72+BM68 -> -4015.6283
B82: Ending Cash | F82: =F78+F80 -> 7250 | G82: =G78+G80 -> 977067.62 | H82: =H78+H80 -> 946739.85 | I82: =I78+I80 -> 916263.77 | J82: =J78+J80 -> 885636.43 | K82: =K78+K80 -> 850996.93 | L82: =L78+L80 -> 816086.79 | M82: =M78+M80 -> 780900.6 | ... BM82: =BM78+BM80 -> -335060.15
B1010: Forecastr Template
